Workbook
Name A: #REF!
Name acum: #REF!
Name acum: #REF!
Name acum: #REF!
Name COM_INTERCOMPANY: 'Resultado Intercompany'!$B$1:$C$21
Name Copia: #REF!
Name Copia: #REF!
Name Copia: #REF!
Name d: #REF!
Name d: #REF!
Name d: #REF!
Name dez: #REF!
Name dez: #REF!
Name dez: #REF!
Name miguel: #REF!
Name miguel: #REF!
Name miguel: #REF!
Name NÍVEL: [1]Plan1!$E$1:$E$65536
Name nov: #REF!
Name nov: #REF!
Name nov: #REF!
Name O: #REF!
Name OUT: #REF!
Name OUT: #REF!
Name OUT: #REF!
Name RECEITA: #REF!
Name RECEITA: #REF!
Name RECEITA: #REF!
Name sim: #REF!
Name sim: #REF!
Name sim: #REF!
Name trim: #REF!
Name trim: #REF!
Name trim: #REF!
Name VALORES: [1]Plan1!$BY$1:$BY$65536

Sheet Passo a Passo
A1: Cotas | C1: TOTAIS 20 E 21 | E1: DRE 2025 | G1: Resumo DRE 2 BACKUP
A2: BRUNO | C2: Nada a fazer, está automático | E2: Está automático, alterar somente no início do ano | G2: Não alterar. Devo tirar
A5: Pessoas | C5: Honorários | E5: Resultado Orçado | G5: Resumo DRE Outros 2
A6: BRUNO | C6: Nada a fazer, está automático | E6: Está automático, alterar somente no início do ano | G6: Não alterar. Devo tirar
A9: DRE | C9: GLOSAS | E9: OKR
A10: A planilha do DRE é enviada por e-mail | C10: Nada a fazer, está automático | E10: Está automático, alterar somente no início do ano
A11: Excluir linhas em branco e que não são necessárias da planilha DRE
A12: Linhas 29, 50, 51, 55, 56, 59, 60 e 63 em diante
C13: Impostos | E13: Projeção 2025
A14: Copiar a coluna do mês da planilha DRE e copiar valores no mês do Informações Gerenciais | C14: Nada a fazer, está automático | E14: Está automático, alterar somente no início do ano
A15: Copiar a coluna de % do mês anterior e copiar na coluna % do mês corrente
A17: Coluna Evolução (AW): ajustar a célula AW3 para o mês corrente/mês anterior | C17: Resultado Intercompany | E17: Resumo DRE 2
A18: Copiar para todas as células abaixo (até a linha 48) e apagar os que derem erro | C18: Somente simulação | E18: Copiar do mês anterior, colar no final e trocar o mês para o mês atual
C21: Crescimento | E21: Resumo DRE 2 Outros
C22: Nada a fazer, está automático | E22: Copiar do mês anterior, colar no final e trocar o mês para o mês atual
C25: Aux Antecipação
C26: Nada a fazer, está automático
C29: Antecipação Consolidado
C30: Nada a fazer, está automático
C33: Antecipação Lucros GAN
C34: Nada a fazer, está automático
C37: Antecipação Lucros GAA
C38: Nada a fazer, está automático
C41: Antecipação Lucros GAA
C42: Nada a fazer, está automático

Sheet TOTAIS  20 E 21
A1: Mês | B1: 43101 | C1: 43132 | D1: 43160 | E1: 43191 | F1: 43221 | G1: 43252 | H1: 43282 | I1: 43313 | J1: 43344 | K1: 43374 | L1: 43405 | M1: 43435 | N1: 43466 | O1: 43497 | P1: 43525 | Q1: 43556 | R1: 43586 | S1: 43617 | T1: 43647 | U1: 43678 | V1: 43709 | W1: 43739 | X1: 43770 | Y1: 43800 | Z1: 43831 | AA1: 43862 | AB1: 43891 | AC1: 43922 | AD1: 43952 | AE1: 43983 | AF1: 44013 | AG1: 44044 | AH1: 44075 | AI1: 44105 | AJ1: 44136 | AK1: 44166 | AL1: 44197 | AM1: 44228 | AN1: 44256 | AO1: 44287 | AP1: 44317 | AQ1: 44348 | AR1: 44378 | AS1: 44409 | AT1: 44440 | AU1: 44470 | AV1: 44501 | AW1: 44531 | AX1: 44562 | AY1: 44593 | AZ1: 44621 | BA1: 44652 | BB1: 44682 | BC1: 44713 | BD1: 44743 | BE1: 44774 | BF1: 44805 | BG1: 44835 | BH1: 44866 | BI1: 44896 | BJ1: 44927 | BK1: 44958 | BL1: 44986 | BM1: 45017 | BN1: 45047 | BO1: 45078 | BP1: 45108 | BQ1: 45139 | BR1: 45170 | BS1: 45200 | BT1: 45231 | BU1: 45261 | BV1: 45292 | BW1: 45323 | BX1: 45352 | BY1: 45383 | BZ1: 45413 | CA1: 45444 | CB1: 45474 | CC1: 45505 | CD1: 45536 | CE1: 45566 | CF1: 45597 | CG1: 45627 | CH1: 45658 | CI1: 45689 | CJ1: 45717 | CK1: 45748 | CL1: 45778 | CM1: 45809 | CN1: 45839 | CO1: 45870 | CP1: 45901 | CQ1: 45931 | CR1: 45962 | CS1: 45992 | CT1: 46023 | CU1: 46054 | CV1: 46082 | CW1: 46113 | CX1: 46143 | CY1: 46174 | CZ1: 46204 | DA1: 46235 | DB1: 46266 | DC1: 46296 | DD1: 46327 | DE1: 46357
A2: RECEITA | B2: 1307223.8 | C2: 1533151.6 | D2: 990409.83 | E2: 1675538.8 | F2: 1390304.1 | G2: 1429726.9 | H2: 1617844.9 | I2: 1754379.8 | J2: 1464234.7 | K2: 2097191.6 | L2: 1576315.3 | M2: 1978552.7 | N2: 1467400.1 | O2: 1032717.8 | P2: 1313738 | Q2: 1330213.9 | R2: 1973924 | S2: 2136174.2 | T2: 1983098.6 | U2: 2276787.9 | V2: 1849436 | W2: 1853373.7 | X2: 2489722.6 | Y2: 1833456.7 | Z2: 2128952.8 | AA2: 1573272.1 | AB2: 2476961.4 | AC2: 2086485.9 | AD2: 2038109.1 | AE2: 1960087.8 | AF2: 2449578.4 | AG2: 1751404.7 | AH2: 2636104.9 | AI2: 1991057.4 | AJ2: 2890477.2 | AK2: 2672542.4 | AL2: 2160275.2 | AM2: 1729170.6 | AN2: 1408118.2 | AO2: 2194304.1 | AP2: 2650378.8 | AQ2: 2209415.5 | AR2: 2332555.9 | AS2: 2180870.1 | AT2: 2274247.4 | AU2: 2588760.7 | AV2: 2581281.1 | AW2: 3002777.1 | AX2: 2236775.4 | AY2: 1432655.2 | AZ2: 2011358.9 | BA2: 2659031 | BB2: 3006579.8 | BC2: 2464901.4 | BD2: 2501382.1 | BE2: 2204860 | BF2: 2556896 | BG2: 2707697.4 | BH2: 2415882.5 | BI2: 2692784.6 | BJ2: 2859585.3 | BK2: 2290503.6 | BL2: 2258763.8 | BM2: 3226365.2 | BN2: 2759630.7 | BO2: 2764496.3 | BP2: 2839189 | BQ2: 3801574.8 | BR2: 3346794.8 | BS2: 3245706.1 | BT2: 3479448.7 | BU2: 4923248.9 | BV2: 3209755.3 | BW2: 3256937.7 | BX2: 2605192.5 | BY2: 3293581.6 | BZ2: 3629988.7 | CA2: 4068124.1 | CB2: 4640246.4 | CC2: 3454210 | CD2: 4253136.9 | CE2: 4658140.7 | CF2: 6144339 | CG2: 5312105.9 | CH2: 4402653.9 | CI2: 4086254.3 | CJ2: 4048194.3 | CK2: 3939627.5 | CL2: 3548210.9 | CM2: 4304516.3 | CN2: 4526009.4 | CO2: 4828600.7 | CP2: 4420476.6 | CQ2: 4300330.3 | CR2: 4681796.7 | CS2: 7347433 | CT2: =[2]Resumo!B15 -> 3839058 | CU2: =[2]Resumo!C15 -> 3623744.1 | CV2: =[2]Resumo!D15 -> 4695972.1 | CW2: =[2]Resumo!E15 -> 0 | CX2: =[2]Resumo!F15 -> 0 | CY2: =[2]Resumo!G15 -> 0 | CZ2: =[2]Resumo!H15 -> 0 | DA2: =[2]Resumo!I15 -> 0 | ... DE2: =[2]Resumo!M15 -> 0
A3: DESPESAS DIRETAS | B3: 708765.42 | C3: 634595.95 | D3: 662041.81 | E3: 742911.37 | F3: 759469.18 | G3: 777423.25 | H3: 883382.09 | I3: 891520.17 | J3: 900333.46 | K3: 920790.36 | L3: 920494.07 | M3: 930857.65 | N3: 890181.42 | O3: 829951.36 | P3: 820806.1 | Q3: 902503.24 | R3: 982451.85 | S3: 1040351.8 | T3: 1001203.4 | U3: 946275.41 | V3: 968576.62 | W3: 969050.69 | X3: 1056477.2 | Y3: 1041487.4 | Z3: 1039086.5 | AA3: 938429.41 | AB3: 899844.27 | AC3: 963963.86 | AD3: 900554.9 | AE3: 793490.17 | AF3: 808317.45 | AG3: 809656.85 | AH3: 772069.07 | AI3: 892189.83 | AJ3: 924546.81 | AK3: 1393054.9 | AL3: 415285.19 | AM3: 821040.81 | AN3: 840932.52 | AO3: 860631.29 | AP3: 898437.04 | AQ3: 925258.58 | AR3: 1001705 | AS3: 1096711.4 | AT3: 1082372 | AU3: 1112579.8 | AV3: 1184774.8 | AW3: 1219497.1 | AX3: 1114140.1 | AY3: 1090075.3 | AZ3: 1101136.5 | BA3: 1153879.6 | BB3: 1153290.8 | BC3: 1120894.3 | BD3: 1175595.8 | BE3: 1147607.9 | BF3: 1118378.4 | BG3: 1219122.6 | BH3: 1265784.8 | BI3: 1486797.5 | BJ3: 1307199.6 | BK3: 1215843.7 | BL3: 1332484.4 | BM3: 1366011 | BN3: 1464995.9 | BO3: 1497743 | BP3: 1504470.8 | BQ3: 1468213.9 | BR3: 1440400.7 | BS3: 1575549.3 | BT3: 1585489.8 | BU3: 1644131.1 | BV3: 1553728.7 | BW3: 1501690 | BX3: 1464061.7 | BY3: 1614515.8 | BZ3: 1686791.7 | CA3: 1669217.5 | CB3: 1801187 | CC3: 1746801.2 | CD3: 1790384.3 | CE3: 1949759.5 | CF3: 1962547.7 | CG3: 1933941.4 | CH3: 1870683.4 | CI3: 1806440.4 | CJ3: 1790545.5 | CK3: 1972373.8 | CL3: 1946905.7 | CM3: 2090154.5 | CN3: 2029865.2 | CO3: 1992411.5 | CP3: 2322824.3 | CQ3: 2015292.8 | CR3: 2207852.6 | CS3: 2336604.6 | CT3: =[2]Resumo!B4 -> 2155945.7 | CU3: =[2]Resumo!C4 -> 2075571.3 | CV3: =[2]Resumo!D4 -> 2061591.4 | CW3: =[2]Resumo!E4 -> 0 | CX3: =[2]Resumo!F4 -> 0 | CY3: =[2]Resumo!G4 -> 0 | CZ3: =[2]Resumo!H4 -> 0 | DA3: =[2]Resumo!I4 -> 0 | ... DE3: =[2]Resumo!M4 -> 0
A4: RATEIO | B4: 332194.72 | C4: 293454.54 | D4: 325566.3 | E4: 330675.78 | F4: 330206.32 | G4: 332778.34 | H4: 366709.99 | I4: 356096.92 | J4: 350277.46 | K4: 419661.83 | L4: 419150.69 | M4: 387617.05 | N4: 335686.65 | O4: 389728.84 | P4: 361294.86 | Q4: 340054.08 | R4: 395127.24 | S4: 369936.62 | T4: 391682.35 | U4: 352480.19 | V4: 373168.78 | W4: 389476.32 | X4: 421483.83 | Y4: 362754.21 | Z4: 361623.24 | AA4: 376692.69 | AB4: 367446.84 | AC4: 339909.64 | AD4: 306880.81 | AE4: 354039 | AF4: 346357.49 | AG4: 365009.91 | AH4: 298807.21 | AI4: 365121.2 | AJ4: 430185.28 | AK4: 398005.1 | AL4: 319539.55 | AM4: 348986.27 | AN4: 435814.08 | AO4: 468530.36 | AP4: 405485.03 | AQ4: 382632.07 | AR4: 388403.94 | AS4: 433471.59 | AT4: 380178.73 | AU4: 394002.7 | AV4: 461423.25 | AW4: 520471.7 | AX4: =[3]Resumo!$B$6 -> 411197.23 | AY4: 370795.09 | AZ4: 482868.54 | BA4: 431323.36 | BB4: =[4]Resumo!F6 -> 410612.91 | BC4: =[4]Resumo!G6 -> 438065.66 | BD4: 495251.26 | BE4: 457057.15 | BF4: 482871.9 | BG4: 488973.14 | BH4: 520395.27 | BI4: 535746.53 | BJ4: 525614.49 | BK4: 728482.32 | BL4: 664470.47 | BM4: 572589.57 | BN4: 606099.92 | BO4: 582232.94 | BP4: 516776.07 | BQ4: 580786.49 | BR4: 681582.65 | BS4: 782798.52 | BT4: 626646.6 | BU4: 985291.68 | BV4: 627328.59 | BW4: 518616.76 | BX4: 571591.12 | BY4: 623411.41 | BZ4: 560543.91 | CA4: 596168.44 | CB4: 608089.79 | CC4: 591644.87 | CD4: 597510.21 | CE4: 666795.74 | CF4: 993644.13 | CG4: 1187654.4 | CH4: 522627.38 | CI4: 730178.33 | CJ4: 750656.43 | CK4: 675211.26 | CL4: 780059.86 | CM4: 802238.9 | CN4: 788622.46 | CO4: 738958.34 | CP4: 752322.23 | CQ4: 793137.38 | CR4: 839169.33 | CS4: 909814.03 | CT4: =[2]Resumo!B6 -> 837978.39 | CU4: =[2]Resumo!C6 -> 797117.8 | CV4: =[2]Resumo!D6 -> 1008083.3 | CW4: =[2]Resumo!E6 -> 0 | CX4: =[2]Resumo!F6 -> 0 | CY4: =[2]Resumo!G6 -> 0 | CZ4: =[2]Resumo!H6 -> 0 | DA4: =[2]Resumo!I6 -> 0 | ... DE4: =[2]Resumo!M6 -> 0
A5: IMPOSTOS | B5: 210944.92 | C5: 226407.3 | D5: 195634.8 | E5: 218328.2 | F5: 203735.55 | G5: 196595.38 | H5: 235885.75 | I5: 261422.16 | J5: 239946.41 | K5: 276209.16 | L5: 256866.81 | M5: 314449.01 | N5: 271211.48 | O5: 231422.09 | P5: 260109.57 | Q5: 239030.85 | R5: 232490.53 | S5: 292201.04 | T5: 314124.08 | U5: 314923.33 | V5: 310952.75 | W5: 267928.56 | X5: 343552.54 | Y5: 297743.48 | Z5: 362815.5 | AA5: 302477.74 | AB5: 220426.78 | AC5: 124999.88 | AD5: 119216.88 | AE5: 125261.23 | AF5: 380329.81 | AG5: 345364.76 | AH5: 394835.44 | AI5: 415158.69 | AJ5: 488420.69 | AK5: 461838.32 | AL5: 405804.91 | AM5: 383117.74 | AN5: 367696.38 | AO5: 321574.66 | AP5: 347745.43 | AQ5: 311827.91 | AR5: 420139.04 | AS5: 417868.74 | AT5: 447683.54 | AU5: 479411.87 | AV5: 476625.54 | AW5: 496429.22 | AX5: =[3]Resumo!$B$10 -> 423761.89 | AY5: 396357.71 | AZ5: 418368.58 | BA5: 425611.61 | BB5: =[4]Resumo!F10 -> 478195.25 | BC5: =[4]Resumo!G10 -> 423247.79 | BD5: 464440.59 | BE5: 445200.58 | BF5: 475341.88 | BG5: 463963.06 | BH5: 467278.49 | BI5: 482432.6 | BJ5: 324082.69 | BK5: 257112.66 | BL5: 304168.46 | BM5: 509520.34 | BN5: 497284.81 | BO5: 471048.18 | BP5: 581694.54 | BQ5: 598087.77 | BR5: 544122.9 | BS5: 631456.76 | BT5: 643026.28 | BU5: 718241.35 | BV5: 680191.5 | BW5: 630667.99 | BX5: 650151.33 | BY5: 552891.73 | BZ5: 576432.91 | CA5: 653479.23 | CB5: 770054.08 | CC5: 694145.02 | CD5: 715390.39 | CE5: 786401.31 | CF5: 854779.57 | CG5: 853342.66 | CH5: 1040647.4 | CI5: 839361.01 | CJ5: 908903.32 | CK5: 774000.14 | CL5: 712671.4 | CM5: 770881.2 | CN5: 877117.36 | CO5: 848538.76 | CP5: 933960.87 | CQ5: 841937.24 | CR5: 1000419.2 | CS5: 1221280.6 | CT5: =[2]Resumo!B10 -> 882839.52 | CU5: =[2]Resumo!C10 -> 795514.76 | CV5: =[2]Resumo!D10 -> 834112.59 | CW5: =[2]Resumo!E10 -> 0 | CX5: =[2]Resumo!F10 -> 0 | CY5: =[2]Resumo!G10 -> 0 | CZ5: =[2]Resumo!H10 -> 0 | DA5: =[2]Resumo!I10 -> 0 | ... DE5: =[2]Resumo!M10 -> 0
A6: EBITDA CONTÁBIL | N6: 195555.99 | O6: -163955.75 | P6: 108080.72 | Q6: 52222.846 | R6: 596502.3 | S6: 688988.91 | T6: 557484.98 | U6: 941952.45 | V6: 539912.2 | W6: 527099.02 | X6: 1043822.3 | Y6: 460837.31 | Z6: 752279.52 | AA6: 288094.68 | AB6: 1231684.4 | AC6: 809596.06 | AD6: 843158.53 | AE6: 824281.16 | AF6: 1307004 | AG6: 588323.81 | AH6: 1568343.8 | AI6: 749082.05 | AJ6: 1548171.5 | AK6: 884123.16 | AL6: 1427584.3 | AM6: 564742.87 | AN6: 168689.34 | AO6: 904350.76 | AP6: 1383868.9 | AQ6: 922214.51 | AR6: 955331.41 | AS6: 672459.22 | AT6: 830475.83 | AU6: 1088586 | AV6: 959424.3 | AW6: 1273180.1 | AX6: 720354.63 | AY6: -20420.79 | AZ6: 457895.25 | BA6: 1088552.5 | BB6: 1450341.9 | BC6: 907886.58 | BD6: 836100.1 | BE6: 608298.97 | BF6: 967265.53 | BG6: 1036299.7 | BH6: 677927.71 | BI6: 724723.27 | BJ6: 2192974.6 | BK6: 1490674 | BL6: 1460217.5 | BM6: 2480554.9 | BN6: 1911789.8 | BO6: 1874919.7 | BP6: 2056242.9 | BQ6: 3003304.4 | BR6: 2460871.4 | BS6: 2181433.9 | BT6: 2538064.1 | BU6: 3591757.8
A7: EBITDA GERENCIAL | BJ7: 1116308.6 | BK7: 443156.21 | BL7: 361151.55 | BM7: 1391814.3 | BN7: 782545.29 | BO7: 718360.32 | BP7: 868397.64 | BQ7: 1799057 | BR7: 1271487.7 | BS7: 929643.29 | BT7: 1303758.4 | BU7: 2339803.9 | BV7: - | BW7: - | BX7: - | BY7: - | BZ7: 1263545.8 | CA7: 1696832.8 | CB7: 2062867 | CC7: 1002841.3 | CD7: 1696216.2 | CE7: 1843459.1 | CF7: 3303573.9 | CG7: 2515839.4 | CH7: 1786081.1 | CI7: 1801912.2 | CJ7: 1734464.9 | CK7: 1402504.9 | CL7: 914588.29 | CM7: 1614308 | CT7: =IF(DRE!AX36="","",DRE!AX36) | CU7: =IF(DRE!AY36="","",DRE!AY36) | CV7: =IF(DRE!AZ36="","",DRE!AZ36) | CW7: =IF(DRE!BA36="","",DRE!BA36) | CX7: =IF(DRE!BB36="","",DRE!BB36) | CY7: =IF(DRE!BC36="","",DRE!BC36) | CZ7: =IF(DRE!BD36="","",DRE!BD36) | DA7: =IF(DRE!BE36="","",DRE!BE36) | ... DE7: =IF(DRE!BI36="","",DRE!BI36)
A8: CUSTOS E DESPESAS | B8: =B3+B4+B5 -> 1251905.1 | C8: =C3+C4+C5 -> 1154457.8 | D8: =D3+D4+D5 -> 1183242.9 | E8: =E3+E4+E5 -> 1291915.3 | F8: =F3+F4+F5 -> 1293411 | G8: =G3+G4+G5 -> 1306797 | H8: =H3+H4+H5 -> 1485977.8 | I8: =I3+I4+I5 -> 1509039.3 | ... BI8: =BI3+BI4+BI5 -> 2504976.7 | BJ8: 2156896.8 | BK8: 2201438.7 | BL8: 2301123.3 | BM8: 2448120.9 | BN8: 2568380.6 | BO8: 2551024.1 | BP8: 2602941.4 | BQ8: 2647088.2 | BR8: 2666106.3 | BS8: 2989804.6 | BT8: 2855162.7 | BU8: 3347664.1 | BV8: 2861248.8 | BW8: 2650974.7 | BX8: 2685804.2 | BY8: 2790818.9 | BZ8: 2823768.5 | CA8: 2918865.1 | CB8: 3179330.9 | CC8: 3032591.1 | CD8: 3103284.9 | CE8: 3402956.6 | CF8: 3810971.4 | CG8: 3974938.4 | CH8: 3433958.2 | CI8: 3375979.7 | CJ8: 3450105.3 | CK8: 3421585.2 | CL8: 3439636.9 | CM8: 3663274.6 | CN8: 3695605.1 | CO8: 3579908.6 | CP8: 4009107.4 | CQ8: 3650367.4 | CR8: 4047441.1 | CS8: 4467699.2 | CT8: =IFERROR(CT3+CT4+CT5,"") -> 3876763.6 | CU8: =IFERROR(CU3+CU4+CU5,"") -> 3668203.8 | CV8: =IFERROR(CV3+CV4+CV5,"") -> 3903787.4 | CW8: =IFERROR(CW3+CW4+CW5,"") -> 0 | CX8: =IFERROR(CX3+CX4+CX5,"") -> 0 | CY8: =IFERROR(CY3+CY4+CY5,"") -> 0 | CZ8: =IFERROR(CZ3+CZ4+CZ5,"") -> 0 | DA8: =IFERROR(DA3+DA4+DA5,"") -> 0 | ... DE8: =IFERROR(DE3+DE4+DE5,"") -> 0
A9: RESULTADO IG | B9: =B2-B8 -> 55318.732 | C9: =C2-C8 -> 378693.83 | D9: =D2-D8 -> -192833.08 | E9: =E2-E8 -> 383623.47 | F9: =F2-F8 -> 96893.083 | G9: =G2-G8 -> 122929.91 | H9: =H2-H8 -> 131867.03 | I9: =I2-I8 -> 245340.54 | ... BI9: =BI2-BI8 -> 187807.98 | BJ9: 702688.5 | BK9: 89064.961 | BL9: -42359.506 | BM9: 778244.29 | BN9: 191250.14 | BO9: 213472.21 | BP9: 236247.6 | BQ9: 1154486.7 | BR9: 680688.55 | BS9: 255901.55 | BT9: 624285.97 | BU9: 1575584.8 | BV9: 348506.47 | BW9: 605962.94 | BX9: -80611.71 | BY9: 502762.71 | BZ9: 806220.24 | CA9: 1149259 | CB9: 1460915.5 | CC9: 421618.87 | CD9: 1149852 | CE9: 1255184.1 | CF9: 2333367.6 | CG9: 1337167.5 | CH9: 968695.78 | CI9: 710274.57 | CJ9: 598089.08 | CK9: 518042.31 | CL9: 108573.95 | CM9: 641241.7 | CN9: 830404.33 | CO9: 1248692.2 | CP9: 411369.25 | CQ9: 649962.84 | CR9: 634355.57 | CS9: 2879733.8 | CT9: =IFERROR(CT2-CT8,"") -> -37705.652 | CU9: =IFERROR(CU2-CU8,"") -> -44459.741 | CV9: =IFERROR(CV2-CV8,"") -> 792184.77 | CW9: =IFERROR(CW2-CW8,"") -> 0 | CX9: =IFERROR(CX2-CX8,"") -> 0 | CY9: =IFERROR(CY2-CY8,"") -> 0 | CZ9: =IFERROR(CZ2-CZ8,"") -> 0 | DA9: =IFERROR(DA2-DA8,"") -> 0 | ... DE9: =IFERROR(DE2-DE8,"") -> 0
A10: OBS Receita | BJ10: ANOMALIAS A MAIOR - 530k Mercado Livre - 230k Santander - 200k UOL - 100k | BK10: ANOMALIAS A MAIOR - 210k Intercompany - 210k | BL10: ANOMALIAS A MAIOR - 80k Intercompany - 80k | BM10: ANOMALIAS A MAIOR - 255k ENEL-SP 175k Intercompany - 80k | BN10: ANOMALIAS A MAIOR - 80k Itercompany - 80k ANOMALIAS A MENOR - 175k ENEL-SP 175k | BO10: ANOMALIAS A MAIOR - 80k Intercompany - 80k ANOMALIAS A MENOR Leader - Receita represada Naturgy - Receita represada | BS10: ANOMALIAS A MAIOR - 170k Intercompany - 170k (entra em receitas e sai em despesas) | BU10: ANOMALIAS A MAIOR - 1,7 M Antecipação de notas da Vivo (jan e fev de 2024) - 600k Recebimento de notas atrasadas da BRK - 400k Intercompany - 400k (entra em receitas e sai em despesas) Sucumbências - 300k | BW10: ANOMALIAS A MAIOR - 600k Antecipação de receita de cliente - 600k | CA10: 1. Tivemos (+) 1 milhão no Itaú, recuperação de receita - Parabéns! 2. Não tivemos Vivo (-) 300k - antecipação feita 3. Não tivemos Mercado Livre - prazo alterado (-) 600k Total (+) 100k | CB10: 1. Sucumbências aumentaram em (+) 410k 2. Mercado Livre (+) 500k - antecipamos para gestão de caixa 3. Santander (+) 100k Total (+) 1.000k | CC10: 1. Mercado Livre (-) 600k - não tivemos pois antecipamos em julho Total (-) 600k | CD10: 1. Sucumbências (+) 300k 2. UOL/Estratégico (+) 100k 3. MRS (+) 100k Total (+) 500k Saneamento - Pendência no faturamento de (+) 600k Deve ser liberado em novembro | CF10: 1. Recebimento do atrasado Saneamento 900k 2- Enel SP recebemos esse mês o referente ao mês passado 170k 3. Santander a maior 300k 4. Intercompany 400k Total a maior 1770k Tenho um entendimento que o nosso novo volume de faturamento monta em 4,2MM | CL10: 1- Receita represada de clientes: 450k 2- Sazonalidade MeLi: Jan: recebe em maio / Prazo 90 dias A menor em torno de 300k 3- Cliente com redução de honorário por negociação em contrato: 150k Com esses eventos, a receita seria no mínimo: 4.498k (3748k + 750k)
A11: OBS Custos | BJ11: ANOMALIAS A MENOR - 180k Impostos - 180k | BK11: ANOMALIAS A MAIOR - 210K Intercompany - 210k ANOMALIAS A MENOR - 180k Impostos - 180k | BL11: ANOMALIAS A MAIOR - 80K Intercompany - 80k ANOMALIAS A MENOR - 180k Impostos - 180k | BM11: ANOMALIAS A MAIOR - 324k Impostos - 180k Intercompany - 80k Correspondentes - 50k Vivo - 14k ANOMALIAS A MENOR - 69k Processos Trabalhistas - 69k | BN11: ANOMALIAS A MAIOR - 279k Pessoal - Vivo - 83k Intercompany - 80k Correspondentes - 70k Glosas - 30k Dep recursal - 16k | BO11: ANOMALIAS A MAIOR - 305k Condenações e Depósitos Recursais - Trabalhista - 130K Pessoal - Vivo - 95k Intercompany - 80k | BP11: ANOMALIAS A MAIOR - 100k Processos trabalhistas Rescisão e férias elevados Alguns eventos Festa Soft Line pago em julho ref junho e julho | BS11: ANOMALIAS A MAIOR - 152k Investimento na festa - 70k Imposto ref trimestre anterior a maior - 60k Correspondentes - 22k | BU11: ANOMALIAS A MAIOR - 400k Intercompany - 400k | BW11: ANOMALIAS A MENOR Correspondentes - recesso Intercompany Impostos GAT | BX11: Evolução x 1o Tri 2023 1. Impostos - parte 520k, deixamos de pagar pelo parcelamento 2. Impostos - parte 450k - evolução pelo aumento do faturamento 3. Pessoas - aumento de times - 400k Total 1,4 milhão | CF11: 1. Pagamento 13º Salário 110k 2. Correspondente a maior 50k 3. Intercompany 400k Total a maior 560k Algumas despesas iniciadas para a festa de Final de Ano e Nova Unidade SP
A12: SUCUMBÊNCIA | Z12: 48459.63 | AA12: 15393.73 | AB12: 9094.42 | AC12: 9069.62 | AD12: 14114.65 | AE12: 66299.88 | AF12: 16874.65 | AG12: 22271.86 | AH12: 9498.26 | AI12: 46340.98 | AJ12: 11279 | AK12: 35578.24 | AL12: 11588.99 | AM12: 32223.18 | AN12: 15309.96 | AO12: 45722.61 | AP12: 34502.25 | AQ12: 37779.75 | AR12: 42094.58 | AS12: 45636.69 | AT12: 45175.41 | AU12: 39850.58 | AV12: 83465.23 | AW12: 86874.45 | AX12: 29746.63 | AY12: 18941.76 | AZ12: 32915.16 | BA12: 106067.72 | BB12: 64119.41 | BC12: 111006.47 | BD12: 11551.85 | BE12: 130378.64 | BF12: 66227.94 | BG12: 80018.85 | BH12: 182634.19 | BI12: 133376.75 | BJ12: 17722.4 | BK12: 37863.44 | BL12: 17778.03 | BM12: 37235.69 | BN12: 38944.1 | BO12: 86275.06 | BP12: 171883.22 | BQ12: 77700.86 | BR12: 240605.86 | BS12: 171332.58 | BT12: 165965.22 | BU12: 339598.13 | BV12: =[5]Sucumbências!BD44 -> 45577.95 | BW12: =[5]Sucumbências!BE44 -> 257734.04 | BX12: =[5]Sucumbências!BF44 -> 133547.93 | BY12: =[5]Sucumbências!BG44 -> 39191.42 | BZ12: =[5]Sucumbências!BH44 -> 112128.08 | CA12: =[5]Sucumbências!BI44 -> 187391.46 | CB12: =[5]Sucumbências!BJ44 -> 410618.01 | CC12: =[5]Sucumbências!BK44 -> 303810.37 | ... CG12: =[5]Sucumbências!BO44 -> 889365.66 | CH12: 367038.29 | CI12: 389371.93 | CJ12: 397295.7 | CK12: 321630.05 | CL12: 513933.32 | CM12: 233201.97 | CN12: 112779.26 | CO12: 579410.41 | CP12: 387892.36 | CQ12: 426678.63 | CR12: 247509.19 | CS12: 501699.87 | CT12: =[5]Sucumbências!CD44 -> 430573.42 | CU12: =[5]Sucumbências!CE44 -> 410980.78 | CV12: =[5]Sucumbências!CF44 -> 0 | CW12: =[5]Sucumbências!CG44 -> 0 | CX12: =[5]Sucumbências!CH44 -> 0 | CY12: =[5]Sucumbências!CI44 -> 0 | CZ12: =[5]Sucumbências!CJ44 -> 0 | DA12: =[5]Sucumbências!CK44 -> 0 | ... DE12: =[5]Sucumbências!CO44 -> 0
A13: GLOSAS | Z13: 15818.67 | AA13: 19856.42 | AB13: 27171.63 | AC13: 300 | AD13: 5304.8 | AE13: 1476.66 | AF13: 8208.94 | AG13: 608.23 | AH13: 4276.55 | AI13: 7719.49 | AJ13: 56314.59 | AK13: 11300 | AL13: 0 | AM13: 0 | AN13: 0 | AO13: 3331.13 | AP13: 5311.54 | AQ13: 6512.89 | AR13: 3779.88 | AS13: 35269.8 | AT13: 25874.19 | AU13: 21889.69 | AV13: 25793.59 | AW13: 13816.28 | AX13: 11747.12 | AY13: 5696.73 | AZ13: 5693.35 | BA13: 7446.7 | BB13: 14391.15 | BC13: 14336.19 | BD13: 2040.76 | BE13: 5100.35 | BF13: 6902.78 | BG13: 14970.92 | BH13: 13723.56 | BI13: 176797.66 | BJ13: 17170.8 | BK13: 22510 | BL13: 32443.95 | BM13: 17170.8 | BN13: 28040.83 | BO13: 65037.66 | BP13: 21614.62 | BQ13: 22194.29 | BR13: 23943.87 | BS13: 32073.5 | BT13: 41254.85 | BU13: 32755.25 | BV13: =IF(BV2="","",GLOSAS!BD43) -> 22436.78 | BW13: =IF(BW2="","",GLOSAS!BE43) -> 37827.72 | BX13: =IF(BX2="","",GLOSAS!BF43) -> 13762.51 | BY13: =IF(BY2="","",GLOSAS!BG43) -> 36048.9 | BZ13: =IF(BZ2="","",GLOSAS!BH43) -> 69000.39 | CA13: =IF(CA2="","",GLOSAS!BI43) -> 43713.2 | CB13: =IF(CB2="","",GLOSAS!BJ43) -> 150696.85 | CC13: =IF(CC2="","",GLOSAS!BK43) -> 78157.04 | ... CG13: =IF(CG2="","",GLOSAS!BO43) -> 48676.61 | CH13: 28380.25 | CI13: 46323.67 | CJ13: 30467.12 | CK13: 48258.81 | CL13: -25177.88 | CM13: 141289.77 | CN13: 36171.73 | CO13: 21721.53 | CP13: 252293.12 | CQ13: 31609.76 | CR13: 63494.05 | CS13: 21560.92 | CT13: =IF(CT2="","",GLOSAS!CD43) -> 9114.04 | CU13: =IF(CU2="","",GLOSAS!CE43) -> 23550.57 | CV13: =IF(CV2="","",GLOSAS!CF43) -> 31308.16 | CW13: =IF(CW2="","",GLOSAS!CG43) -> 0 | CX13: =IF(CX2="","",GLOSAS!CH43) -> 0 | CY13: =IF(CY2="","",GLOSAS!CI43) -> 0 | CZ13: =IF(CZ2="","",GLOSAS!CJ43) -> 0 | DA13: =IF(DA2="","",GLOSAS!CK43) -> 0 | ... DE13: =IF(DE2="","",GLOSAS!CO43) -> 0
A14: IMPOSTO SUCUMBÊNCIA | Z14: =IF(Z2="","",Z12*0.1) -> 4845.963 | AA14: =IF(AA2="","",AA12*0.1) -> 1539.373 | AB14: =IF(AB2="","",AB12*0.1) -> 909.442 | AC14: =IF(AC2="","",AC12*0.1) -> 906.962 | AD14: =IF(AD2="","",AD12*0.1) -> 1411.465 | AE14: =IF(AE2="","",AE12*0.1) -> 6629.988 | AF14: =IF(AF2="","",AF12*0.1) -> 1687.465 | AG14: =IF(AG2="","",AG12*0.1) -> 2227.186 | ... CG14: =IF(CG2="","",CG12*0.1) -> 88936.566 | CH14: 36703.829 | CI14: 38937.193 | CJ14: 39729.57 | CK14: 32163.005 | CL14: 51393.332 | CM14: 23320.197 | CN14: 11277.926 | CO14: 57941.041 | CP14: 38789.236 | CQ14: 42667.863 | CR14: 24750.919 | CS14: 50169.987 | CT14: =IF(CT2="","",CT12*0.1) -> 43057.342 | CU14: =IF(CU2="","",CU12*0.1) -> 41098.078 | CV14: =IF(CV2="","",CV12*0.1) -> 0 | CW14: =IF(CW2="","",CW12*0.1) -> 0 | CX14: =IF(CX2="","",CX12*0.1) -> 0 | CY14: =IF(CY2="","",CY12*0.1) -> 0 | CZ14: =IF(CZ2="","",CZ12*0.1) -> 0 | DA14: =IF(DA2="","",DA12*0.1) -> 0 | ... DE14: =IF(DE2="","",DE12*0.1) -> 0
A15: IMPOSTOS SEM SUCUMBÊNCIA | Z15: =IF(Z2="","",Z5-Z14) -> 357969.54 | AA15: =IF(AA2="","",AA5-AA14) -> 300938.36 | AB15: =IF(AB2="","",AB5-AB14) -> 219517.34 | AC15: =IF(AC2="","",AC5-AC14) -> 124092.92 | AD15: =IF(AD2="","",AD5-AD14) -> 117805.42 | AE15: =IF(AE2="","",AE5-AE14) -> 118631.25 | AF15: =IF(AF2="","",AF5-AF14) -> 378642.35 | AG15: =IF(AG2="","",AG5-AG14) -> 343137.57 | ... CG15: =IF(CG2="","",CG5-CG14) -> 764406.09 | CH15: 1003943.6 | CI15: 800423.82 | CJ15: 869173.75 | CK15: 741837.14 | CL15: 661278.07 | CM15: 747561 | CN15: 865839.43 | CO15: 790597.72 | CP15: 895171.63 | CQ15: 799269.38 | CR15: 975668.31 | CS15: 1171110.6 | CT15: =IF(CT2="","",CT5-CT14) -> 839782.18 | CU15: =IF(CU2="","",CU5-CU14) -> 754416.68 | CV15: =IF(CV2="","",CV5-CV14) -> 834112.59 | CW15: =IF(CW2="","",CW5-CW14) -> 0 | CX15: =IF(CX2="","",CX5-CX14) -> 0 | CY15: =IF(CY2="","",CY5-CY14) -> 0 | CZ15: =IF(CZ2="","",CZ5-CZ14) -> 0 | DA15: =IF(DA2="","",DA5-DA14) -> 0 | ... DE15: =IF(DE2="","",DE5-DE14) -> 0
A16: RECEITA SEM SUCUMBÊNCIAS | Z16: =IF(Z2="","",Z2-Z12) -> 2080493.2 | AA16: =IF(AA2="","",AA2-AA12) -> 1557878.4 | AB16: =IF(AB2="","",AB2-AB12) -> 2467867 | AC16: =IF(AC2="","",AC2-AC12) -> 2077416.3 | AD16: =IF(AD2="","",AD2-AD12) -> 2023994.4 | AE16: =IF(AE2="","",AE2-AE12) -> 1893787.9 | AF16: =IF(AF2="","",AF2-AF12) -> 2432703.7 | AG16: =IF(AG2="","",AG2-AG12) -> 1729132.9 | ... CG16: =IF(CG2="","",CG2-CG12) -> 4422740.2 | CH16: 4035615.7 | CI16: 3696882.3 | CJ16: 3650898.6 | CK16: 3617997.5 | CL16: 3034277.6 | CM16: 4071314.3 | CN16: 4413230.1 | CO16: 4249190.3 | CP16: 4032584.3 | CQ16: 3873651.7 | CR16: 4434287.5 | CS16: 6845733.2 | CT16: =IF(CT2="","",CT2-CT12) -> 3408484.5 | CU16: =IF(CU2="","",CU2-CU12) -> 3212763.3 | CV16: =IF(CV2="","",CV2-CV12) -> 4695972.1 | CW16: =IF(CW2="","",CW2-CW12) -> 0 | CX16: =IF(CX2="","",CX2-CX12) -> 0 | CY16: =IF(CY2="","",CY2-CY12) -> 0 | CZ16: =IF(CZ2="","",CZ2-CZ12) -> 0 | DA16: =IF(DA2="","",DA2-DA12) -> 0 | ... DE16: =IF(DE2="","",DE2-DE12) -> 0
A17: CUSTOS SEM SUCUMBÊNCIAS | Z17: =IF(Z2="","",Z3+Z4+Z15) -> 1758679.3 | AA17: =IF(AA2="","",AA3+AA4+AA15) -> 1616060.5 | AB17: =IF(AB2="","",AB3+AB4+AB15) -> 1486808.5 | AC17: =IF(AC2="","",AC3+AC4+AC15) -> 1427966.4 | AD17: =IF(AD2="","",AD3+AD4+AD15) -> 1325241.1 | AE17: =IF(AE2="","",AE3+AE4+AE15) -> 1266160.4 | AF17: =IF(AF2="","",AF3+AF4+AF15) -> 1533317.3 | AG17: =IF(AG2="","",AG3+AG4+AG15) -> 1517804.3 | ... CG17: =IF(CG2="","",CG3+CG4+CG15) -> 3886001.8 | CH17: 3397254.3 | CI17: 3337042.5 | CJ17: 3410375.7 | CK17: 3389422.2 | CL17: 3388243.6 | CM17: 3639954.4 | CN17: 3684327.1 | CO17: 3521967.5 | CP17: 3970318.1 | CQ17: 3607699.6 | CR17: 4022690.2 | CS17: 4417529.2 | CT17: =IF(CT2="","",CT3+CT4+CT15) -> 3833706.3 | CU17: =IF(CU2="","",CU3+CU4+CU15) -> 3627105.8 | CV17: =IF(CV2="","",CV3+CV4+CV15) -> 3903787.4 | CW17: =IF(CW2="","",CW3+CW4+CW15) -> 0 | CX17: =IF(CX2="","",CX3+CX4+CX15) -> 0 | CY17: =IF(CY2="","",CY3+CY4+CY15) -> 0 | CZ17: =IF(CZ2="","",CZ3+CZ4+CZ15) -> 0 | DA17: =IF(DA2="","",DA3+DA4+DA15) -> 0 | ... DE17: =IF(DE2="","",DE3+DE4+DE15) -> 0
A18: RESULTADO SEM SUCUMBÊNCIAS | Z18: =Z16-Z3-Z4-Z5 -> 316967.94 | AA18: =AA16-AA3-AA4-AA5 -> -59721.478 | AB18: =AB16-AB3-AB4-AB5 -> 980149.12 | AC18: =AC16-AC3-AC4-AC5 -> 648542.94 | AD18: =AD16-AD3-AD4-AD5 -> 697341.82 | AE18: =AE16-AE3-AE4-AE5 -> 620997.47 | AF18: =AF16-AF3-AF4-AF5 -> 897698.99 | AG18: =AG16-AG3-AG4-AG5 -> 209101.34 | ... BU18: =BU16-BU3-BU4-BU5 -> 1235986.7 | BV18: =IF(BV2="","",BV16-BV3-BV4-BV5) -> 302928.52 | BW18: =IF(BW2="","",BW16-BW3-BW4-BW5) -> 348228.9 | BX18: =IF(BX2="","",BX16-BX3-BX4-BX5) -> -214159.64 | BY18: =IF(BY2="","",BY16-BY3-BY4-BY5) -> 463571.29 | BZ18: =IF(BZ2="","",BZ16-BZ3-BZ4-BZ5) -> 694092.16 | CA18: =IF(CA2="","",CA16-CA3-CA4-CA5) -> 961867.52 | CB18: =IF(CB2="","",CB16-CB3-CB4-CB5) -> 1050297.5 | CC18: =IF(CC2="","",CC16-CC3-CC4-CC5) -> 117808.5 | ... CG18: =IF(CG2="","",CG16-CG3-CG4-CG5) -> 447801.84 | CH18: 601657.49 | CI18: 320902.64 | CJ18: 200793.38 | CK18: 196412.26 | CL18: -405359.37 | CM18: 408039.73 | CN18: 717625.07 | CO18: 669281.75 | CP18: 23476.89 | CQ18: 223284.21 | CR18: 386846.38 | CS18: 2378033.9 | CT18: =IF(CT2="","",CT16-CT3-CT4-CT5) -> -468279.07 | CU18: =IF(CU2="","",CU16-CU3-CU4-CU5) -> -455440.52 | CV18: =IF(CV2="","",CV16-CV3-CV4-CV5) -> 792184.77 | CW18: =IF(CW2="","",CW16-CW3-CW4-CW5) -> 0 | CX18: =IF(CX2="","",CX16-CX3-CX4-CX5) -> 0 | CY18: =IF(CY2="","",CY16-CY3-CY4-CY5) -> 0 | CZ18: =IF(CZ2="","",CZ16-CZ3-CZ4-CZ5) -> 0 | DA18: =IF(DA2="","",DA16-DA3-DA4-DA5) -> 0 | ... DE18: =IF(DE2="","",DE16-DE3-DE4-DE5) -> 0
A19: RESULTADO SEM SUCUMBÊNCIAS PAINEL | Z19: =IF(Z2="","",Z16-Z17) -> 321813.9 | AA19: =IF(AA2="","",AA16-AA17) -> -58182.105 | AB19: =IF(AB2="","",AB16-AB17) -> 981058.56 | AC19: =IF(AC2="","",AC16-AC17) -> 649449.9 | AD19: =IF(AD2="","",AD16-AD17) -> 698753.28 | AE19: =IF(AE2="","",AE16-AE17) -> 627627.46 | AF19: =IF(AF2="","",AF16-AF17) -> 899386.45 | AG19: =IF(AG2="","",AG16-AG17) -> 211328.52 | ... CG19: =IF(CG2="","",CG16-CG17) -> 536738.41 | CH19: 638361.32 | CI19: 359839.83 | CJ19: 240522.95 | CK19: 228575.26 | CL19: -353966.04 | CM19: 431359.93 | CN19: 728903 | CO19: 727222.79 | CP19: 62266.126 | CQ19: 265952.08 | CR19: 411597.3 | CS19: 2428203.9 | CT19: =IF(CT2="","",CT16-CT17) -> -425221.73 | CU19: =IF(CU2="","",CU16-CU17) -> -414342.44 | CV19: =IF(CV2="","",CV16-CV17) -> 792184.77 | CW19: =IF(CW2="","",CW16-CW17) -> 0 | CX19: =IF(CX2="","",CX16-CX17) -> 0 | CY19: =IF(CY2="","",CY16-CY17) -> 0 | CZ19: =IF(CZ2="","",CZ16-CZ17) -> 0 | DA19: =IF(DA2="","",DA16-DA17) -> 0 | ... DE19: =IF(DE2="","",DE16-DE17) -> 0
A20: INTERCOMPANY | BJ20: 0 | BK20: 210000 | BL20: 80000 | BM20: 80000 | BN20: 80000 | BO20: 80000 | BP20: 0 | BQ20: 0 | BR20: 110000 | BS20: 170000 | BT20: 0 | BU20: 400000 | BV20: 50000 | BW20: 0 | BX20: 0 | BY20: 0 | BZ20: 0 | CA20: 0 | CB20: 0 | CC20: 0 | CD20: 0 | CE20: 0 | CF20: 400000 | CG20: 500000 | CH20: 0 | CI20: 0 | CJ20: 0 | CK20: 0 | CL20: 0 | CM20: 0 | CN20: 0 | CO20: 0 | CP20: 0 | CQ20: 0 | CR20: 0 | CS20: 0 | CT20: =IF(CT2="","",[2]Receita!B220) -> 0 | CU20: =IF(CU2="","",[2]Receita!C220) -> 0 | CV20: =IF(CV2="","",[2]Receita!D220) -> 0 | CW20: =IF(CW2="","",[2]Receita!E220) -> 0 | CX20: =IF(CX2="","",[2]Receita!F220) -> 0 | CY20: =IF(CY2="","",[2]Receita!G220) -> 0 | CZ20: =IF(CZ2="","",[2]Receita!H220) -> 0 | DA20: =IF(DA2="","",[2]Receita!I220) -> 0 | ... DE20: =IF(DE2="","",[2]Receita!M220) -> 0
A21: VALOR LEGAL | CE21: ='[6]Valor Legal'!$BQ$54+'[6]Valor Legal'!$BQ$61 -> 45894.979 | CF21: ='[6]Valor Legal'!$BX$54+'[6]Valor Legal'!$BX$61 -> 6215.8882 | CG21: ='[6]Valor Legal'!$CE$54+'[6]Valor Legal'!$CE$61 -> 91797.278 | CH21: 22489.233 | CI21: 41333.128 | CJ21: 44330.35 | CK21: 30862.173 | CL21: 68647.997 | CM21: 20028.889 | CN21: 30481.665 | CO21: 50200.221 | CP21: 62569.331 | CQ21: 77234.868 | CR21: 59360.301 | CS21: 59907.791 | CT21: =IF(CT2="","",[2]Recupera!$F$176+[2]Recupera!$F$184) -> 96591.414 | CU21: =IF(CU2="","",[2]Recupera!$M$176+[2]Recupera!$M$184) -> 99851.769 | CV21: =IF(CV2="","",[2]Recupera!$T$176+[2]Recupera!$T$184) -> 158860.76 | CW21: =IF(CW2="","",[2]Recupera!$AA$176+[2]Recupera!$AA$184) -> 0 | CX21: =IF(CX2="","",[2]Recupera!$AH$176+[2]Recupera!$AH$184) -> 0 | CY21: =IF(CY2="","",[2]Recupera!$AO$176+[2]Recupera!$AO$184) -> 0 | CZ21: =IF(CZ2="","",[2]Recupera!$AV$176+[2]Recupera!$AV$184) -> 0 | DA21: =IF(DA2="","",[2]Recupera!$BC$176+[2]Recupera!$BC$184) -> 0 | DB21: =IF(DB2="","",[2]Recupera!$BJ$176+[2]Recupera!$BJ$184) -> 0 | DC21: =IF(DC2="","",[2]Recupera!$BQ$176+[2]Recupera!$BQ$184) -> 0 | DD21: =IF(DD2="","",[2]Recupera!$BX$176+[2]Recupera!$BX$184) -> 0 | DE21: =IF(DE2="","",[2]Recupera!$CE$176+[2]Recupera!$CE$184) -> 0
A22: SUCUMB LÍQUIDA | BV22: =IFERROR(BV12-BV13-BV23-BV12*0.1,"") -> 18583.375 | BW22: =IFERROR(BW12-BW13-BW23-BW12*0.1,"") -> 194132.92 | BX22: =IFERROR(BX12-BX13-BX23-BX12*0.1,"") -> 106430.63 | BY22: =IFERROR(BY12-BY13-BY23-BY12*0.1,"") -> -776.622 | BZ22: =IFERROR(BZ12-BZ13-BZ23-BZ12*0.1,"") -> 31914.882 | CA22: =IFERROR(CA12-CA13-CA23-CA12*0.1,"") -> 124939.11 | CB22: =IFERROR(CB12-CB13-CB23-CB12*0.1,"") -> 218859.36 | CC22: =IFERROR(CC12-CC13-CC23-CC12*0.1,"") -> 195272.29 | ... CG22: =IFERROR(CG12-CG13-CG23-CG12*0.1,"") -> 746460.23 | CH22: 296944.1 | CI22: 296431.26 | CJ22: 313439.61 | CK22: 228184.1 | CL22: 474354.26 | CM22: 55607.742 | CN22: 35551.042 | CO22: 477323.64 | CP22: 62001.919 | CQ22: 321352.21 | CR22: 134963.69 | CS22: 407018.19 | CT22: =IFERROR(CT12-CT13-CT23-CT12*0.1,"") -> 353651.41 | CU22: =IFERROR(CU12-CU13-CU23-CU12*0.1,"") -> 324456.72 | CV22: =IFERROR(CV12-CV13-CV23-CV12*0.1,"") -> -74268.38 | CW22: =IFERROR(CW12-CW13-CW23-CW12*0.1,"") -> 0 | CX22: =IFERROR(CX12-CX13-CX23-CX12*0.1,"") -> 0 | CY22: =IFERROR(CY12-CY13-CY23-CY12*0.1,"") -> 0 | CZ22: =IFERROR(CZ12-CZ13-CZ23-CZ12*0.1,"") -> 0 | DA22: =IFERROR(DA12-DA13-DA23-DA12*0.1,"") -> 0 | ... DE22: =IFERROR(DE12-DE13-DE23-DE12*0.1,"") -> 0
A23: VL DD | CE23: 45894.979 | CF23: 6215.8882 | CG23: 5292.2577 | CH23: 5010.1128 | CI23: 7679.8074 | CJ23: 13659.403 | CK23: 13024.136 | CL23: 13363.604 | CM23: 12984.261 | CN23: 29778.562 | CO23: 22424.199 | CP23: 34808.085 | CQ23: 31048.795 | CR23: 24300.526 | CS23: 22950.773 | CT23: =IF(CT2="","",[2]Recupera!$F$176) -> 24750.633 | CU23: =IF(CU2="","",[2]Recupera!$M$176) -> 21875.415 | CV23: =IF(CV2="","",[2]Recupera!$T$176) -> 42960.22 | CW23: =IF(CW2="","",[2]Recupera!$AA$176) -> 0 | CX23: =IF(CX2="","",[2]Recupera!$AH$176) -> 0 | CY23: =IF(CY2="","",[2]Recupera!$AO$176) -> 0 | CZ23: =IF(CZ2="","",[2]Recupera!$AV$176) -> 0 | DA23: =IF(DA2="","",[2]Recupera!$BC$176) -> 0 | DB23: =IF(DB2="","",[2]Recupera!$BJ$176) -> 0 | DC23: =IF(DC2="","",[2]Recupera!$BQ$176) -> 0 | DD23: =IF(DD2="","",[2]Recupera!$BX$176) -> 0 | DE23: =IF(DE2="","",[2]Recupera!$CE$176) -> 0
A24: SUCUMB ORÇADA | CH24: 141666.67 | CI24: 141666.67 | CJ24: 141666.67 | CK24: 141666.67 | CL24: 141666.67 | CM24: 141666.67 | CN24: 141666.67 | CO24: 141666.67 | CP24: 141666.67 | CQ24: 141666.67 | CR24: 141666.67 | CS24: 141666.67 | CT24: =[2]Recupera!$D$8 -> 150000 | CU24: =[2]Recupera!$K$8 -> 150000 | CV24: =[2]Recupera!$R$8 -> 150000 | CW24: =[2]Recupera!$Y$8 -> 150000 | CX24: =[2]Recupera!$AF$8 -> 150000 | CY24: =[2]Recupera!$AM$8 -> 150000 | CZ24: =[2]Recupera!$AT$8 -> 150000 | DA24: =[2]Recupera!$BA$8 -> 150000 | DB24: =[2]Recupera!$BH$8 -> 150000 | DC24: =[2]Recupera!$BO$8 -> 150000 | DD24: =[2]Recupera!$BV$8 -> 150000 | DE24: =[2]Recupera!$CC$8 -> 150000
A25: TOTAL ORÇADO | CH25: 4231546.7 | CI25: 4391466.7 | CJ25: 3930886.7 | CK25: 4214399.7 | CL25: 4491699.7 | CM25: 4496699.7 | CN25: 4546699.7 | CO25: 4582399.7 | CP25: 4492399.7 | CQ25: 4516599.7 | CR25: 4536599.7 | CS25: 4526599.7 | CT25: =[2]Total!$B$35 -> 3495609.3 | CU25: =[2]Total!$P$35 -> 3650042.4 | CV25: =[2]Total!$AD$35 -> 4860256.6 | CW25: =[2]Total!$AR$35 -> 4674335.2 | CX25: =[2]Total!$BF$35 -> 4763068.3 | CY25: =[2]Total!$BT$35 -> 4772526.3 | CZ25: =[2]Total!$CH$35 -> 4948793.2 | DA25: =[2]Total!$CV$35 -> 4948793.2 | DB25: =[2]Total!$DJ$35 -> 4948793.2 | DC25: =[2]Total!$DX$35 -> 4995060.2 | DD25: =[2]Total!$EL$35 -> 4948793.2 | DE25: =[2]Total!$EZ$35 -> 4948793.2
A26: CONTRATUAIS ORÇADO | CH26: 4089880 | CI26: 4249800 | CJ26: 3789220 | CK26: 4072733 | CL26: 4350033 | CM26: 4355033 | CN26: 4405033 | CO26: 4440733 | CP26: 4350733 | CQ26: 4374933 | CR26: 4394933 | CS26: 4384933 | CT26: =IF(CT2="","",CT25-CT24) -> 3345609.3 | CU26: =IF(CU2="","",CU25-CU24) -> 3500042.4 | CV26: =IF(CV2="","",CV25-CV24) -> 4710256.6 | CW26: =IF(CW2="","",CW25-CW24) -> 4524335.2 | CX26: =IF(CX2="","",CX25-CX24) -> 4613068.3 | CY26: =IF(CY2="","",CY25-CY24) -> 4622526.3 | CZ26: =IF(CZ2="","",CZ25-CZ24) -> 4798793.2 | DA26: =IF(DA2="","",DA25-DA24) -> 4798793.2 | ... DE26: =IF(DE2="","",DE25-DE24) -> 4798793.2
A27: RESULTADO SEM SUCUMBÊNCIAS LÍQUIDA | BV27: =BV9-BV22 -> 329923.1 | BW27: =BW9-BW22 -> 411830.02 | BX27: =BX9-BX22 -> -187042.34 | BY27: =BY9-BY22 -> 503539.33 | BZ27: =BZ9-BZ22 -> 774305.36 | CA27: =CA9-CA22 -> 1024319.9 | CB27: =CB9-CB22 -> 1242056.1 | CC27: =CC9-CC22 -> 226346.58 | ... CG27: =CG9-CG22 -> 590707.28 | CH27: 671751.68 | CI27: 413843.31 | CJ27: 284649.47 | CK27: 289858.21 | CL27: -365780.32 | CM27: 585633.96 | CN27: 794853.29 | CO27: 771368.52 | CP27: 349367.33 | CQ27: 328610.63 | CR27: 499391.88 | CS27: 2472715.6 | CT27: =IF(CT2="","",CT9-CT22) -> -391357.06 | CU27: =IF(CU2="","",CU9-CU22) -> -368916.46 | CV27: =IF(CV2="","",CV9-CV22) -> 866453.16 | CW27: =IF(CW2="","",CW9-CW22) -> 0 | CX27: =IF(CX2="","",CX9-CX22) -> 0 | CY27: =IF(CY2="","",CY9-CY22) -> 0 | CZ27: =IF(CZ2="","",CZ9-CZ22) -> 0 | DA27: =IF(DA2="","",DA9-DA22) -> 0 | ... DE27: =IF(DE2="","",DE9-DE22) -> 0
A28: RECEITA SEM INTERCOMPANY | B28: =B2-B20 -> 1307223.8 | C28: =C2-C20 -> 1533151.6 | D28: =D2-D20 -> 990409.83 | E28: =E2-E20 -> 1675538.8 | F28: =F2-F20 -> 1390304.1 | G28: =G2-G20 -> 1429726.9 | H28: =H2-H20 -> 1617844.9 | I28: =I2-I20 -> 1754379.8 | ... CG28: =CG2-CG20 -> 4812105.9 | CH28: 4402653.9 | CI28: 4086254.3 | CJ28: 4048194.3 | CK28: 3939627.5 | CL28: 3548210.9 | CM28: 4304516.3 | CN28: 4526009.4 | CO28: 4828600.7 | CP28: 4420476.6 | CQ28: 4300330.3 | CR28: 4681796.7 | CS28: 7347433 | CT28: =IF(CT2="","",CT2-CT20) -> 3839058 | CU28: =IF(CU2="","",CU2-CU20) -> 3623744.1 | CV28: =IF(CV2="","",CV2-CV20) -> 4695972.1 | CW28: =IF(CW2="","",CW2-CW20) -> 0 | CX28: =IF(CX2="","",CX2-CX20) -> 0 | CY28: =IF(CY2="","",CY2-CY20) -> 0 | CZ28: =IF(CZ2="","",CZ2-CZ20) -> 0 | DA28: =IF(DA2="","",DA2-DA20) -> 0 | ... DE28: =IF(DE2="","",DE2-DE20) -> 0
A29: CUSTOS E DESPESAS SEM INTERCOMPANY | B29: =B8-B20 -> 1251905.1 | C29: =C8-C20 -> 1154457.8 | D29: =D8-D20 -> 1183242.9 | E29: =E8-E20 -> 1291915.3 | F29: =F8-F20 -> 1293411 | G29: =G8-G20 -> 1306797 | H29: =H8-H20 -> 1485977.8 | I29: =I8-I20 -> 1509039.3 | ... CG29: =CG8-CG20 -> 3474938.4 | CH29: 3433958.2 | CI29: 3375979.7 | CJ29: 3450105.3 | CK29: 3421585.2 | CL29: 3439636.9 | CM29: 3663274.6 | CN29: 3695605.1 | CO29: 3579908.6 | CP29: 4009107.4 | CQ29: 3650367.4 | CR29: 4047441.1 | CS29: 4467699.2 | CT29: =IF(CT2="","",CT8-CT20) -> 3876763.6 | CU29: =IF(CU2="","",CU8-CU20) -> 3668203.8 | CV29: =IF(CV2="","",CV8-CV20) -> 3903787.4 | CW29: =IF(CW2="","",CW8-CW20) -> 0 | CX29: =IF(CX2="","",CX8-CX20) -> 0 | CY29: =IF(CY2="","",CY8-CY20) -> 0 | CZ29: =IF(CZ2="","",CZ8-CZ20) -> 0 | DA29: =IF(DA2="","",DA8-DA20) -> 0 | ... DE29: =IF(DE2="","",DE8-DE20) -> 0
A30: RESULTADO SEM INTERCOMPANY | B30: =B28-B29 -> 55318.732 | C30: =C28-C29 -> 378693.83 | D30: =D28-D29 -> -192833.08 | E30: =E28-E29 -> 383623.47 | F30: =F28-F29 -> 96893.083 | G30: =G28-G29 -> 122929.91 | H30: =H28-H29 -> 131867.03 | I30: =I28-I29 -> 245340.54 | ... CG30: =CG28-CG29 -> 1337167.5 | CH30: 968695.78 | CI30: 710274.57 | CJ30: 598089.08 | CK30: 518042.31 | CL30: 108573.95 | CM30: 641241.7 | CN30: 830404.33 | CO30: 1248692.2 | CP30: 411369.25 | CQ30: 649962.84 | CR30: 634355.57 | CS30: 2879733.8 | CT30: =IF(CT2="","",CT28-CT29) -> -37705.652 | CU30: =IF(CU2="","",CU28-CU29) -> -44459.741 | CV30: =IF(CV2="","",CV28-CV29) -> 792184.77 | CW30: =IF(CW2="","",CW28-CW29) -> 0 | CX30: =IF(CX2="","",CX28-CX29) -> 0 | CY30: =IF(CY2="","",CY28-CY29) -> 0 | CZ30: =IF(CZ2="","",CZ28-CZ29) -> 0 | DA30: =IF(DA2="","",DA28-DA29) -> 0 | ... DE30: =IF(DE2="","",DE28-DE29) -> 0

Sheet Honorários
A1: DATA | B1: TOTAL FLUXO | C1: ATOS/PREPOSTOS | D1: SUCUMBÊNCIAS | E1: GLOSAS | F1: VALORES RETROATIVOS | G1: TOTAL | H1: Hora
A2: 43466 | B2: 1467400.1 | G2: =B2+C2+D2+E2 -> 1467400.1 | H2: =NOW() -> 46134.669
A3: 43497 | B3: 1032717.8 | G3: =B3+C3+D3+E3 -> 1032717.8
A4: 43525 | B4: 1313738 | G4: =B4+C4+D4+E4 -> 1313738
A5: 43556 | B5: 1330213.9 | G5: =B5+C5+D5+E5 -> 1330213.9
A6: 43586 | B6: 1973924 | G6: =B6+C6+D6+E6 -> 1973924
A7: 43617 | B7: 2136174.2 | G7: =B7+C7+D7+E7 -> 2136174.2
A8: 43647 | B8: 1983098.6 | G8: =B8+C8+D8+E8 -> 1983098.6
A9: 43678 | B9: 2276787.9 | G9: =B9+C9+D9+E9 -> 2276787.9
A10: 43709 | B10: 1849436 | G10: =B10+C10+D10+E10 -> 1849436
A11: 43739 | B11: 1853373.7 | G11: =B11+C11+D11+E11 -> 1853373.7
A12: 43770 | B12: 2489722.6 | G12: =B12+C12+D12+E12 -> 2489722.6
A13: 43800 | B13: 1833456.7 | G13: =B13+C13+D13+E13 -> 1833456.7
A14: 43831 | B14: 2079332.4 | C14: 0 | D14: 48459.63 | E14: 1160.72 | F14: 0 | G14: =B14+C14+D14+E14 -> 2128952.8
A15: 43862 | B15: 1557158.3 | C15: 0 | D15: 15393.73 | E15: 720.08 | F15: 0 | G15: =B15+C15+D15+E15 -> 1573272.1
A16: 43891 | B16: 2446334.3 | C16: 2080.1 | D16: 9094.42 | E16: 19452.58 | F16: 0 | G16: =B16+C16+D16+E16 -> 2476961.4
A17: 43922 | B17: 2077416.3 | C17: 0 | D17: 9069.62 | E17: 0 | F17: 0 | G17: =B17+C17+D17+E17 -> 2086485.9
A18: 43952 | B18: 2012991.2 | C18: 10395 | D18: 14114.65 | E18: 608.23 | F18: 0 | G18: =B18+C18+D18+E18 -> 2038109.1
A19: 43983 | B19: 1893356 | C19: 0 | D19: 66299.88 | E19: 431.84 | F19: 0 | G19: =B19+C19+D19+E19 -> 1960087.8
A20: 44013 | B20: 2424434.8 | C20: 60 | D20: 16874.65 | E20: 8208.94 | F20: 0 | G20: =B20+C20+D20+E20 -> 2449578.4
A21: 44044 | B21: 1728524.6 | C21: 0 | D21: 22271.86 | E21: 608.23 | F21: 0 | G21: =B21+C21+D21+E21 -> 1751404.7
A22: 44075 | B22: 2622040.1 | C22: 290 | D22: 9498.26 | E22: 4276.55 | F22: 0 | G22: =B22+C22+D22+E22 -> 2636104.9
A23: 44105 | B23: 1936416.9 | C23: 580 | D23: 46340.98 | E23: 7719.49 | F23: 0 | G23: =B23+C23+D23+E23 -> 1991057.4
A24: 44136 | B24: 2820577.8 | C24: 700 | D24: 11279 | E24: 57920.46 | F24: 0 | G24: =B24+C24+D24+E24 -> 2890477.2
A25: 44166 | B25: 2630555 | C25: 1015 | D25: 35578.24 | E25: 5394.13 | F25: 0 | G25: =B25+C25+D25+E25 -> 2672542.4
... A33: 44409 | B33: 2099963.6 | C33: 0 | D33: 45636.69 | E33: 35269.8 | F33: 0 | G33: =B33+C33+D33+E33 -> 2180870.1
A34: 44440 | B34: 2200749.7 | C34: 2448.1 | D34: =[7]Receita!$J$315+[7]Receita!$J$318 -> 45175.41 | E34: 25874.19 | F34: 0 | G34: =B34+C34+D34+E34 -> 2274247.4
A35: 44470 | B35: 2525135.5 | C35: 1885 | D35: =[7]Receita!$K$315+[7]Receita!$K$318 -> 39850.58 | E35: 21889.69 | F35: 0 | G35: =B35+C35+D35+E35 -> 2588760.7
A36: 44501 | B36: 2472022.3 | C36: 0 | D36: 83465.23 | E36: 25793.59 | F36: 0 | G36: =B36+C36+D36+E36 -> 2581281.1
A37: 44531 | B37: 2899936.4 | C37: 2150 | D37: 86874.45 | E37: 13816.28 | F37: 0 | G37: =B37+C37+D37+E37 -> 3002777.1
A38: 44562 | B38: 2194991.6 | C38: 290 | D38: 29746.63 | E38: =10077.12+1670 -> 11747.12 | F38: 0 | G38: =B38+C38+D38+E38 -> 2236775.4
A39: 44593 | B39: 1407956.7 | C39: 60 | D39: 18941.76 | E39: 5696.73 | F39: 0 | G39: =B39+C39+D39+E39 -> 1432655.2
A40: 44621 | B40: 1972315.4 | C40: 435 | D40: 32915.16 | E40: 5693.35 | F40: 0 | G40: =B40+C40+D40+E40 -> 2011358.9
A41: 44652 | B41: 2545081.6 | C41: 435 | D41: 106067.72 | E41: 7446.7 | F41: 0 | G41: =B41+C41+D41+E41 -> 2659031
A42: 44682 | B42: 2927889.2 | C42: 180 | D42: 64119.41 | E42: 14391.15 | F42: 0 | G42: =B42+C42+D42+E42 -> 3006579.8
A43: 44713 | B43: 2337673.7 | C43: 1885 | D43: =[4]Receita!$G$315+[4]Receita!$G$318 -> 111006.47 | E43: 14336.19 | F43: 0 | G43: =B43+C43+D43+E43 -> 2464901.4
A44: 44743 | B44: 2487139.5 | C44: 650 | D44: 11551.85 | E44: 2040.76 | F44: 0 | G44: =B44+C44+D44+E44 -> 2501382.1
A45: 44774 | B45: 2068851.1 | C45: 530 | D45: 130378.64 | E45: 5100.35 | F45: 0 | G45: =B45+C45+D45+E45 -> 2204860.1
A46: 44805 | B46: 2481115.3 | C46: 2650 | D46: 66227.94 | E46: 6902.78 | F46: 0 | G46: =B46+C46+D46+E46 -> 2556896
A47: 44835 | B47: 2619228.2 | C47: 0 | D47: 80018.85 | E47: 8450.42 | F47: 0 | G47: =B47+C47+D47+E47 -> 2707697.4
A48: 44866 | B48: 2217274.8 | C48: 2250 | D48: 182634.19 | E48: 13723.56 | F48: 0 | G48: =B48+C48+D48+E48 -> 2415882.5
A49: 44896 | B49: 2382610.2 | C49: 0 | D49: 133376.75 | E49: 176797.66 | F49: 0 | G49: =B49+C49+D49+E49 -> 2692784.6
A50: 44927 | B50: 2824332.1 | C50: 360 | D50: 17722.4 | E50: 17170.8 | F50: 0 | G50: 2859585.3
A51: 44958 | B51: 2229804.9 | C51: 0 | D51: 37863.44 | E51: 22510 | F51: 325.29 | G51: 2290503.6
A52: 44986 | B52: 2206837.7 | C52: 0 | D52: 17778.03 | E52: 32443.95 | F52: 1704.11 | G52: 2258763.8
A53: 45017 | B53: 3171958.7 | C53: 0 | D53: 37235.69 | E53: 17170.8 | F53: 0 | G53: 3226365.2
A54: 45047 | B54: 2692285.8 | C54: 360 | D54: 38944.1 | E54: 28040.83 | F54: 0 | G54: 2759630.7
A55: 45078 | B55: 2613183.6 | C55: 0 | D55: 86275.06 | E55: 65037.66 | F55: 0 | G55: 2764496.4
A56: 45108 | B56: 2641941.2 | C56: 3750 | D56: 171883.22 | E56: 21614.62 | F56: 0 | G56: 2839189
A57: 45139 | B57: 3700449.7 | C57: 1230 | D57: 77700.86 | E57: 22194.29 | F57: 0 | G57: 3801574.9
A58: 45170 | B58: 3076295.1 | C58: 5950 | D58: 240605.86 | E58: 23943.87 | F58: 0 | G58: 3346794.8
A59: 45200 | B59: 3041310 | C59: 990 | D59: 171332.58 | E59: 32073.5 | F59: 0 | G59: 3245706.1
A60: 45231 | B60: 3272228.6 | C60: 0 | D60: 165965.22 | E60: 41254.85 | F60: 0 | G60: 3479448.7
A61: 45261 | B61: 4523403.1 | C61: 0 | D61: 339598.13 | E61: 32755.25 | F61: 27492.43 | G61: 4923248.9
... A85: 45992 | B85: 6820947.2 | C85: 3225 | D85: 501699.87 | E85: 21560.92 | F85: 0 | G85: 7347433
A86: 46023 | B86: =IFERROR(G86-C86-D86-E86-F86,"") -> 3394480.5 | C86: =VLOOKUP("ATOS/PREPOSTOS",[2]Receita!$A$370:$M$381,(MONTH($A86)+1),0) -> 0 | D86: =[5]Sucumbências!$CD$44 -> 430573.42 | E86: =IF(GLOSAS!CD$43=0,"",GLOSAS!CD$43) -> 9114.04 | F86: =VLOOKUP("HONORÁRIOS RETROATIVOS",[2]Receita!$A$370:$M$381,(MONTH($A86)+1),0)+VLOOKUP("PREPOSTOS RETROATIVOS",[2]Receita!$A$370:$M$381,(MONTH($A86)+1),0) -> 4890 | G86: ='TOTAIS 20 E 21'!CT$2 -> 3839058
A87: 46054 | B87: =IFERROR(G87-C87-D87-E87-F87,"") -> 3189212.7 | C87: =VLOOKUP("ATOS/PREPOSTOS",[2]Receita!$A$370:$M$381,(MONTH($A87)+1),0) -> 0 | D87: =[5]Sucumbências!$CE$44 -> 410980.78 | E87: =IF(GLOSAS!CE$43=0,"",GLOSAS!CE$43) -> 23550.57 | F87: =VLOOKUP("HONORÁRIOS RETROATIVOS",[2]Receita!$A$370:$M$381,(MONTH($A87)+1),0)+VLOOKUP("PREPOSTOS RETROATIVOS",[2]Receita!$A$370:$M$381,(MONTH($A87)+1),0) -> 0 | G87: ='TOTAIS 20 E 21'!CU$2 -> 3623744.1
A88: 46082 | B88: =IFERROR(G88-C88-D88-E88-F88,"") -> 4664664 | C88: =VLOOKUP("ATOS/PREPOSTOS",[2]Receita!$A$370:$M$381,(MONTH($A88)+1),0) -> 0 | D88: =[5]Sucumbências!$CF$44 -> 0 | E88: =IF(GLOSAS!CF$43=0,"",GLOSAS!CF$43) -> 31308.16 | F88: =VLOOKUP("HONORÁRIOS RETROATIVOS",[2]Receita!$A$370:$M$381,(MONTH($A88)+1),0)+VLOOKUP("PREPOSTOS RETROATIVOS",[2]Receita!$A$370:$M$381,(MONTH($A88)+1),0) -> 0 | G88: ='TOTAIS 20 E 21'!CV$2 -> 4695972.1
A89: 46113 | B89: =IFERROR(G89-C89-D89-E89-F89,"") | C89: =VLOOKUP("ATOS/PREPOSTOS",[2]Receita!$A$370:$M$381,(MONTH($A89)+1),0) -> 0 | D89: =[5]Sucumbências!$CG$44 -> 0 | E89: =IF(GLOSAS!CG$43=0,"",GLOSAS!CG$43) | F89: =VLOOKUP("HONORÁRIOS RETROATIVOS",[2]Receita!$A$370:$M$381,(MONTH($A89)+1),0)+VLOOKUP("PREPOSTOS RETROATIVOS",[2]Receita!$A$370:$M$381,(MONTH($A89)+1),0) -> 0 | G89: ='TOTAIS 20 E 21'!CW$2 -> 0
A90: 46143 | B90: =IFERROR(G90-C90-D90-E90-F90,"") | C90: =VLOOKUP("ATOS/PREPOSTOS",[2]Receita!$A$370:$M$381,(MONTH($A90)+1),0) -> 0 | D90: =[5]Sucumbências!$CH$44 -> 0 | E90: =IF(GLOSAS!CH$43=0,"",GLOSAS!CH$43) | F90: =VLOOKUP("HONORÁRIOS RETROATIVOS",[2]Receita!$A$370:$M$381,(MONTH($A90)+1),0)+VLOOKUP("PREPOSTOS RETROATIVOS",[2]Receita!$A$370:$M$381,(MONTH($A90)+1),0) -> 0 | G90: ='TOTAIS 20 E 21'!CX$2 -> 0
A91: 46174 | B91: =IFERROR(G91-C91-D91-E91-F91,"") | C91: =VLOOKUP("ATOS/PREPOSTOS",[2]Receita!$A$370:$M$381,(MONTH($A91)+1),0) -> 0 | D91: =[5]Sucumbências!$CI$44 -> 0 | E91: =IF(GLOSAS!CI$43=0,"",GLOSAS!CI$43) | F91: =VLOOKUP("HONORÁRIOS RETROATIVOS",[2]Receita!$A$370:$M$381,(MONTH($A91)+1),0)+VLOOKUP("PREPOSTOS RETROATIVOS",[2]Receita!$A$370:$M$381,(MONTH($A91)+1),0) -> 0 | G91: ='TOTAIS 20 E 21'!CY$2 -> 0
A92: 46204 | B92: =IFERROR(G92-C92-D92-E92-F92,"") | C92: =VLOOKUP("ATOS/PREPOSTOS",[2]Receita!$A$370:$M$381,(MONTH($A92)+1),0) -> 0 | D92: =[5]Sucumbências!$CJ$44 -> 0 | E92: =IF(GLOSAS!CJ$43=0,"",GLOSAS!CJ$43) | F92: =VLOOKUP("HONORÁRIOS RETROATIVOS",[2]Receita!$A$370:$M$381,(MONTH($A92)+1),0)+VLOOKUP("PREPOSTOS RETROATIVOS",[2]Receita!$A$370:$M$381,(MONTH($A92)+1),0) -> 0 | G92: ='TOTAIS 20 E 21'!CZ$2 -> 0
A93: 46235 | B93: =IFERROR(G93-C93-D93-E93-F93,"") | C93: =VLOOKUP("ATOS/PREPOSTOS",[2]Receita!$A$370:$M$381,(MONTH($A93)+1),0) -> 0 | D93: =[5]Sucumbências!$CK$44 -> 0 | E93: =IF(GLOSAS!CK$43=0,"",GLOSAS!CK$43) | F93: =VLOOKUP("HONORÁRIOS RETROATIVOS",[2]Receita!$A$370:$M$381,(MONTH($A93)+1),0)+VLOOKUP("PREPOSTOS RETROATIVOS",[2]Receita!$A$370:$M$381,(MONTH($A93)+1),0) -> 0 | G93: ='TOTAIS 20 E 21'!DA$2 -> 0
A94: 46266 | B94: =IFERROR(G94-C94-D94-E94-F94,"") | C94: =VLOOKUP("ATOS/PREPOSTOS",[2]Receita!$A$370:$M$381,(MONTH($A94)+1),0) -> 0 | D94: =[5]Sucumbências!$CL$44 -> 0 | E94: =IF(GLOSAS!CL$43=0,"",GLOSAS!CL$43) | F94: =VLOOKUP("HONORÁRIOS RETROATIVOS",[2]Receita!$A$370:$M$381,(MONTH($A94)+1),0)+VLOOKUP("PREPOSTOS RETROATIVOS",[2]Receita!$A$370:$M$381,(MONTH($A94)+1),0) -> 0 | G94: ='TOTAIS 20 E 21'!DB$2 -> 0
A95: 46296 | B95: =IFERROR(G95-C95-D95-E95-F95,"") | C95: =VLOOKUP("ATOS/PREPOSTOS",[2]Receita!$A$370:$M$381,(MONTH($A95)+1),0) -> 0 | D95: =[5]Sucumbências!$CM$44 -> 0 | E95: =IF(GLOSAS!CM$43=0,"",GLOSAS!CM$43) | F95: =VLOOKUP("HONORÁRIOS RETROATIVOS",[2]Receita!$A$370:$M$381,(MONTH($A95)+1),0)+VLOOKUP("PREPOSTOS RETROATIVOS",[2]Receita!$A$370:$M$381,(MONTH($A95)+1),0) -> 0 | G95: ='TOTAIS 20 E 21'!DC$2 -> 0
A96: 46327 | B96: =IFERROR(G96-C96-D96-E96-F96,"") | C96: =VLOOKUP("ATOS/PREPOSTOS",[2]Receita!$A$370:$M$381,(MONTH($A96)+1),0) -> 0 | D96: =[5]Sucumbências!$CN$44 -> 0 | E96: =IF(GLOSAS!CN$43=0,"",GLOSAS!CN$43) | F96: =VLOOKUP("HONORÁRIOS RETROATIVOS",[2]Receita!$A$370:$M$381,(MONTH($A96)+1),0)+VLOOKUP("PREPOSTOS RETROATIVOS",[2]Receita!$A$370:$M$381,(MONTH($A96)+1),0) -> 0 | G96: ='TOTAIS 20 E 21'!DD$2 -> 0
A97: 46357 | B97: =IFERROR(G97-C97-D97-E97-F97,"") | C97: =VLOOKUP("ATOS/PREPOSTOS",[2]Receita!$A$370:$M$381,(MONTH($A97)+1),0) -> 0 | D97: =[5]Sucumbências!$CO$44 -> 0 | E97: =IF(GLOSAS!CO$43=0,"",GLOSAS!CO$43) | F97: =VLOOKUP("HONORÁRIOS RETROATIVOS",[2]Receita!$A$370:$M$381,(MONTH($A97)+1),0)+VLOOKUP("PREPOSTOS RETROATIVOS",[2]Receita!$A$370:$M$381,(MONTH($A97)+1),0) -> 0 | G97: ='TOTAIS 20 E 21'!DE$2 -> 0

Sheet GLOSAS
A1: Grupo | B1: Data | C1: 2019 | D1: 43831 | E1: 43862 | F1: 43891 | G1: 43922 | H1: 43952 | I1: 43983 | J1: 44013 | K1: 44044 | L1: 44075 | M1: 44105 | N1: 44136 | O1: 44166 | P1: 2020 | Q1: 44197 | R1: 44228 | S1: 44256 | T1: 44287 | U1: 44317 | V1: 44348 | W1: 44378 | X1: 44409 | Y1: 44440 | Z1: 44470 | AA1: 44501 | AB1: 44531 | AC1: 2021 | AD1: 44562 | AE1: 44593 | AF1: 44621 | AG1: 44652 | AH1: 44682 | AI1: 44713 | AJ1: 44743 | AK1: 44774 | AL1: 44805 | AM1: 44835 | AN1: 44866 | AO1: 44896 | AP1: 2022 | AQ1: 44927 | AR1: 44958 | AS1: 44986 | AT1: 45017 | AU1: 45047 | AV1: 45078 | AW1: 45108 | AX1: 45139 | AY1: 45170 | AZ1: 45200 | BA1: 45231 | BB1: 45261 | BC1: 2023 | BD1: 45292 | BE1: 45323 | BF1: 45352 | BG1: 45383 | BH1: 45413 | BI1: 45444 | BJ1: 45474 | BK1: 45505 | BL1: 45536 | BM1: 45566 | BN1: 45597 | BO1: 45627 | BP1: 2024 | BQ1: 45658 | BR1: 45689 | BS1: 45717 | BT1: 45748 | BU1: 45778 | BV1: 45809 | BW1: 45839 | BX1: 45870 | BY1: 45901 | BZ1: 45931 | CA1: 45962 | CB1: 45992 | CC1: 2025 | CD1: 46023 | CE1: 46054 | CF1: 46082 | CG1: 46113 | CH1: 46143 | CI1: 46174 | CJ1: 46204 | CK1: 46235 | CL1: 46266 | CM1: 46296 | CN1: 46327 | CO1: 46357 | CP1: 2026
A2: SANEAMENTO | B2: SANEAMENTO | C2: 0 | D2: 0 | E2: 0 | F2: 0 | G2: 0 | H2: 0 | I2: 0 | J2: 0 | K2: 0 | L2: 0 | M2: 0 | N2: 0 | O2: 0 | P2: =SUM(D2:O2) -> 0 | Q2: 0 | R2: 0 | S2: 0 | T2: 0 | U2: 0 | V2: 0 | W2: 0 | X2: 0 | Y2: 578.97 | Z2: 0 | AA2: 0 | AB2: 0 | AC2: =SUM(Q2:AB2) -> 578.97 | AD2: 0 | AE2: 0 | AF2: 0 | AG2: 0 | AH2: 0 | AI2: 0 | AJ2: 0 | AK2: 0 | AL2: 700 | AM2: 2042 | AN2: 900.46 | AO2: 0 | AP2: =SUM(AD2:AO2) -> 3642.46 | AQ2: 0 | AR2: 0 | AS2: 1219.97 | AT2: 0 | AU2: 2304.14 | AV2: 0 | AW2: 1877.3 | AX2: 0 | AY2: 0 | AZ2: 0 | BA2: 0 | BB2: 0 | BC2: =SUM(AQ2:BB2) -> 5401.41 | BD2: 0 | BE2: 6279.55 | BF2: 0 | BG2: 10864.74 | BH2: 0 | BI2: 0 | BJ2: 3000 | BK2: 0 | BL2: 8000 | BM2: 2430.74 | BN2: 0 | BO2: 0 | BP2: =SUM(BD2:BO2) -> 30575.03 | BQ2: 0 | BR2: 0 | BS2: 0 | BT2: 0 | BU2: 0 | BV2: 0 | BW2: 0 | BX2: 0 | BY2: 0 | BZ2: 0 | CA2: 0 | CB2: 0 | CC2: =SUM(BQ2:CB2) -> 0 | CD2: 0 | CE2: 0 | CF2: 0 | CG2: 0 | CH2: 0 | CI2: 0 | CJ2: 0 | CK2: 0 | CL2: 0 | CM2: 0 | CN2: 0 | CO2: 0 | CP2: =SUM(CD2:CO2) -> 0
A3: SANEAMENTO | B3: SANEAMENTO - BRK | C3: 0 | D3: 0 | E3: 0 | F3: 0 | G3: 0 | H3: 0 | I3: 0 | J3: 0 | K3: 0 | L3: 0 | M3: 0 | N3: 0 | O3: 0 | P3: =SUM(D3:O3) -> 0 | Q3: 0 | R3: 0 | S3: 0 | T3: 0 | U3: 0 | V3: 0 | W3: 0 | X3: 0 | Y3: 0 | Z3: 0 | AA3: 0 | AB3: 0 | AC3: =SUM(Q3:AB3) -> 0 | AD3: 0 | AE3: 0 | AF3: 0 | AG3: 0 | AH3: 0 | AI3: 0 | AJ3: 0 | AK3: 0 | AL3: 0 | AM3: 0 | AN3: 0 | AO3: 0 | AP3: =SUM(AD3:AO3) -> 0 | AQ3: 0 | AR3: 0 | AS3: 0 | AT3: 0 | AU3: 0 | AV3: 0 | AW3: 0 | AX3: 0 | AY3: 0 | AZ3: 0 | BA3: 0 | BB3: 0 | BC3: =SUM(AQ3:BB3) -> 0 | BD3: 0 | BE3: 0 | BF3: 0 | BG3: 0 | BH3: 0 | BI3: 0 | BJ3: 0 | BK3: 0 | BL3: 0 | BM3: 0 | BN3: 0 | BO3: 0 | BP3: =SUM(BD3:BO3) -> 0 | BQ3: 0 | BR3: 6255.98 | BS3: 1172.33 | BT3: 0 | BU3: 254.94 | BV3: 77515.48 | BW3: 12847.05 | BX3: 4500 | BY3: 4385.96 | BZ3: 8501.55 | CA3: 8500 | CB3: 0 | CC3: =SUM(BQ3:CB3) -> 123933.29 | CD3: =VLOOKUP("Condenação",[2]Saneamento!$A67:$CH109,CD46,0)+VLOOKUP("Penalidades/Irregularidades",[2]Saneamento!$A67:$CH109,CD46,0) -> 0 | CE3: =VLOOKUP("Condenação",[2]Saneamento!$A67:$CH109,CE46,0)+VLOOKUP("Penalidades/Irregularidades",[2]Saneamento!$A67:$CH109,CE46,0) -> 0 | CF3: =VLOOKUP("Condenação",[2]Saneamento!$A67:$CH109,CF46,0)+VLOOKUP("Penalidades/Irregularidades",[2]Saneamento!$A67:$CH109,CF46,0) -> 0 | CG3: =VLOOKUP("Condenação",[2]Saneamento!$A67:$CH109,CG46,0)+VLOOKUP("Penalidades/Irregularidades",[2]Saneamento!$A67:$CH109,CG46,0) -> 0 | CH3: =VLOOKUP("Condenação",[2]Saneamento!$A67:$CH109,CH46,0)+VLOOKUP("Penalidades/Irregularidades",[2]Saneamento!$A67:$CH109,CH46,0) -> 0 | CI3: =VLOOKUP("Condenação",[2]Saneamento!$A67:$CH109,CI46,0)+VLOOKUP("Penalidades/Irregularidades",[2]Saneamento!$A67:$CH109,CI46,0) -> 0 | CJ3: =VLOOKUP("Condenação",[2]Saneamento!$A67:$CH109,CJ46,0)+VLOOKUP("Penalidades/Irregularidades",[2]Saneamento!$A67:$CH109,CJ46,0) -> 0 | CK3: =VLOOKUP("Condenação",[2]Saneamento!$A67:$CH109,CK46,0)+VLOOKUP("Penalidades/Irregularidades",[2]Saneamento!$A67:$CH109,CK46,0) -> 0 | ... CO3: =VLOOKUP("Condenação",[2]Saneamento!$A67:$CH109,CO46,0)+VLOOKUP("Penalidades/Irregularidades",[2]Saneamento!$A67:$CH109,CO46,0) -> 0 | CP3: =SUM(CD3:CO3) -> 0
A4: SANEAMENTO | B4: SANEAMENTO - ÁGUAS DO RIO 1 | C4: 0 | D4: 0 | E4: 0 | F4: 0 | G4: 0 | H4: 0 | I4: 0 | J4: 0 | K4: 0 | L4: 0 | M4: 0 | N4: 0 | O4: 0 | P4: =SUM(D4:O4) -> 0 | Q4: 0 | R4: 0 | S4: 0 | T4: 0 | U4: 0 | V4: 0 | W4: 0 | X4: 0 | Y4: 0 | Z4: 0 | AA4: 0 | AB4: 0 | AC4: =SUM(Q4:AB4) -> 0 | AD4: 0 | AE4: 0 | AF4: 0 | AG4: 0 | AH4: 0 | AI4: 0 | AJ4: 0 | AK4: 0 | AL4: 0 | AM4: 0 | AN4: 0 | AO4: 0 | AP4: =SUM(AD4:AO4) -> 0 | AQ4: 0 | AR4: 0 | AS4: 0 | AT4: 0 | AU4: 0 | AV4: 0 | AW4: 0 | AX4: 0 | AY4: 0 | AZ4: 0 | BA4: 0 | BB4: 0 | BC4: =SUM(AQ4:BB4) -> 0 | BD4: 0 | BE4: 0 | BF4: 0 | BG4: 0 | BH4: 0 | BI4: 0 | BJ4: 0 | BK4: 0 | BL4: 0 | BM4: 0 | BN4: 0 | BO4: 0 | BP4: =SUM(BD4:BO4) -> 0 | BQ4: 0 | BR4: 0 | BS4: 0 | BT4: 0 | BU4: 0 | BV4: 0 | BW4: 0 | BX4: 0 | BY4: 0 | BZ4: 0 | CA4: 0 | CB4: 0 | CC4: =SUM(BQ4:CB4) -> 0 | CD4: =VLOOKUP("Condenação",[2]Saneamento!$A501:$CH543,CD46,0)+VLOOKUP("Penalidades/Irregularidades",[2]Saneamento!$A501:$CH543,CD46,0) -> 0 | CE4: =VLOOKUP("Condenação",[2]Saneamento!$A501:$CH543,CE46,0)+VLOOKUP("Penalidades/Irregularidades",[2]Saneamento!$A501:$CH543,CE46,0) -> 0 | CF4: =VLOOKUP("Condenação",[2]Saneamento!$A501:$CH543,CF46,0)+VLOOKUP("Penalidades/Irregularidades",[2]Saneamento!$A501:$CH543,CF46,0) -> 0 | CG4: =VLOOKUP("Condenação",[2]Saneamento!$A501:$CH543,CG46,0)+VLOOKUP("Penalidades/Irregularidades",[2]Saneamento!$A501:$CH543,CG46,0) -> 0 | CH4: =VLOOKUP("Condenação",[2]Saneamento!$A501:$CH543,CH46,0)+VLOOKUP("Penalidades/Irregularidades",[2]Saneamento!$A501:$CH543,CH46,0) -> 0 | CI4: =VLOOKUP("Condenação",[2]Saneamento!$A501:$CH543,CI46,0)+VLOOKUP("Penalidades/Irregularidades",[2]Saneamento!$A501:$CH543,CI46,0) -> 0 | CJ4: =VLOOKUP("Condenação",[2]Saneamento!$A501:$CH543,CJ46,0)+VLOOKUP("Penalidades/Irregularidades",[2]Saneamento!$A501:$CH543,CJ46,0) -> 0 | CK4: =VLOOKUP("Condenação",[2]Saneamento!$A501:$CH543,CK46,0)+VLOOKUP("Penalidades/Irregularidades",[2]Saneamento!$A501:$CH543,CK46,0) -> 0 | ... CO4: =VLOOKUP("Condenação",[2]Saneamento!$A501:$CH543,CO46,0)+VLOOKUP("Penalidades/Irregularidades",[2]Saneamento!$A501:$CH543,CO46,0) -> 0 | CP4: =SUM(CD4:CO4) -> 0
A5: SANEAMENTO | B5: SANEAMENTO - ÁGUAS DO RIO 4 | C5: 0 | D5: 0 | E5: 0 | F5: 0 | G5: 0 | H5: 0 | I5: 0 | J5: 0 | K5: 0 | L5: 0 | M5: 0 | N5: 0 | O5: 0 | P5: =SUM(D5:O5) -> 0 | Q5: 0 | R5: 0 | S5: 0 | T5: 0 | U5: 0 | V5: 0 | W5: 0 | X5: 0 | Y5: 0 | Z5: 0 | AA5: 0 | AB5: 0 | AC5: =SUM(Q5:AB5) -> 0 | AD5: 0 | AE5: 0 | AF5: 0 | AG5: 0 | AH5: 0 | AI5: 0 | AJ5: 0 | AK5: 0 | AL5: 0 | AM5: 0 | AN5: 0 | AO5: 0 | AP5: =SUM(AD5:AO5) -> 0 | AQ5: 0 | AR5: 0 | AS5: 0 | AT5: 0 | AU5: 0 | AV5: 0 | AW5: 0 | AX5: 0 | AY5: 0 | AZ5: 0 | BA5: 0 | BB5: 0 | BC5: =SUM(AQ5:BB5) -> 0 | BD5: 0 | BE5: 0 | BF5: 0 | BG5: 0 | BH5: 0 | BI5: 0 | BJ5: 0 | BK5: 0 | BL5: 0 | BM5: 0 | BN5: 0 | BO5: 0 | BP5: =SUM(BD5:BO5) -> 0 | BQ5: 0 | BR5: 0 | BS5: 0 | BT5: 0 | BU5: 0 | BV5: 0 | BW5: 0 | BX5: 0 | BY5: 0 | BZ5: 0 | CA5: 0 | CB5: 0 | CC5: =SUM(BQ5:CB5) -> 0 | CD5: =VLOOKUP("Condenação",[2]Saneamento!$A439:$CH481,CD46,0)+VLOOKUP("Penalidades/Irregularidades",[2]Saneamento!$A439:$CH481,CD46,0) -> 0 | CE5: =VLOOKUP("Condenação",[2]Saneamento!$A439:$CH481,CE46,0)+VLOOKUP("Penalidades/Irregularidades",[2]Saneamento!$A439:$CH481,CE46,0) -> 0 | CF5: =VLOOKUP("Condenação",[2]Saneamento!$A439:$CH481,CF46,0)+VLOOKUP("Penalidades/Irregularidades",[2]Saneamento!$A439:$CH481,CF46,0) -> 0 | CG5: =VLOOKUP("Condenação",[2]Saneamento!$A439:$CH481,CG46,0)+VLOOKUP("Penalidades/Irregularidades",[2]Saneamento!$A439:$CH481,CG46,0) -> 0 | CH5: =VLOOKUP("Condenação",[2]Saneamento!$A439:$CH481,CH46,0)+VLOOKUP("Penalidades/Irregularidades",[2]Saneamento!$A439:$CH481,CH46,0) -> 0 | CI5: =VLOOKUP("Condenação",[2]Saneamento!$A439:$CH481,CI46,0)+VLOOKUP("Penalidades/Irregularidades",[2]Saneamento!$A439:$CH481,CI46,0) -> 0 | CJ5: =VLOOKUP("Condenação",[2]Saneamento!$A439:$CH481,CJ46,0)+VLOOKUP("Penalidades/Irregularidades",[2]Saneamento!$A439:$CH481,CJ46,0) -> 0 | CK5: =VLOOKUP("Condenação",[2]Saneamento!$A439:$CH481,CK46,0)+VLOOKUP("Penalidades/Irregularidades",[2]Saneamento!$A439:$CH481,CK46,0) -> 0 | ... CO5: =VLOOKUP("Condenação",[2]Saneamento!$A439:$CH481,CO46,0)+VLOOKUP("Penalidades/Irregularidades",[2]Saneamento!$A439:$CH481,CO46,0) -> 0 | CP5: =SUM(CD5:CO5) -> 0
A6: SANEAMENTO | B6: SANEAMENTO - ÁGUAS DO SERTÃO | C6: 0 | D6: 0 | E6: 0 | F6: 0 | G6: 0 | H6: 0 | I6: 0 | J6: 0 | K6: 0 | L6: 0 | M6: 0 | N6: 0 | O6: 0 | P6: =SUM(D6:O6) -> 0 | Q6: 0 | R6: 0 | S6: 0 | T6: 0 | U6: 0 | V6: 0 | W6: 0 | X6: 0 | Y6: 0 | Z6: 0 | AA6: 0 | AB6: 0 | AC6: =SUM(Q6:AB6) -> 0 | AD6: 0 | AE6: 0 | AF6: 0 | AG6: 0 | AH6: 0 | AI6: 0 | AJ6: 0 | AK6: 0 | AL6: 0 | AM6: 0 | AN6: 0 | AO6: 0 | AP6: =SUM(AD6:AO6) -> 0 | AQ6: 0 | AR6: 0 | AS6: 0 | AT6: 0 | AU6: 0 | AV6: 0 | AW6: 0 | AX6: 0 | AY6: 0 | AZ6: 0 | BA6: 0 | BB6: 0 | BC6: =SUM(AQ6:BB6) -> 0 | BD6: 0 | BE6: 0 | BF6: 0 | BG6: 0 | BH6: 0 | BI6: 0 | BJ6: 0 | BK6: 0 | BL6: 0 | BM6: 0 | BN6: 0 | BO6: 0 | BP6: =SUM(BD6:BO6) -> 0 | BQ6: 0 | BR6: 0 | BS6: 0 | BT6: 0 | BU6: 0 | BV6: 0 | BW6: 0 | BX6: 0 | BY6: 0 | BZ6: 0 | CA6: 0 | CB6: 0 | CC6: =SUM(BQ6:CB6) -> 0 | CD6: =VLOOKUP("Condenação",[2]Saneamento!$A377:$CH419,CD46,0)+VLOOKUP("Penalidades/Irregularidades",[2]Saneamento!$A377:$CH419,CD46,0) -> 0 | CE6: =VLOOKUP("Condenação",[2]Saneamento!$A377:$CH419,CE46,0)+VLOOKUP("Penalidades/Irregularidades",[2]Saneamento!$A377:$CH419,CE46,0) -> 0 | CF6: =VLOOKUP("Condenação",[2]Saneamento!$A377:$CH419,CF46,0)+VLOOKUP("Penalidades/Irregularidades",[2]Saneamento!$A377:$CH419,CF46,0) -> 0 | CG6: =VLOOKUP("Condenação",[2]Saneamento!$A377:$CH419,CG46,0)+VLOOKUP("Penalidades/Irregularidades",[2]Saneamento!$A377:$CH419,CG46,0) -> 0 | CH6: =VLOOKUP("Condenação",[2]Saneamento!$A377:$CH419,CH46,0)+VLOOKUP("Penalidades/Irregularidades",[2]Saneamento!$A377:$CH419,CH46,0) -> 0 | CI6: =VLOOKUP("Condenação",[2]Saneamento!$A377:$CH419,CI46,0)+VLOOKUP("Penalidades/Irregularidades",[2]Saneamento!$A377:$CH419,CI46,0) -> 0 | CJ6: =VLOOKUP("Condenação",[2]Saneamento!$A377:$CH419,CJ46,0)+VLOOKUP("Penalidades/Irregularidades",[2]Saneamento!$A377:$CH419,CJ46,0) -> 0 | CK6: =VLOOKUP("Condenação",[2]Saneamento!$A377:$CH419,CK46,0)+VLOOKUP("Penalidades/Irregularidades",[2]Saneamento!$A377:$CH419,CK46,0) -> 0 | ... CO6: =VLOOKUP("Condenação",[2]Saneamento!$A377:$CH419,CO46,0)+VLOOKUP("Penalidades/Irregularidades",[2]Saneamento!$A377:$CH419,CO46,0) -> 0 | CP6: =SUM(CD6:CO6) -> 0
A7: SANEAMENTO | B7: SANEAMENTO - RESOLUÇÃO DE DISPUTAS | C7: 0 | D7: 0 | E7: 0 | F7: 0 | G7: 0 | H7: 0 | I7: 0 | J7: 0 | K7: 0 | L7: 0 | M7: 0 | N7: 0 | O7: 0 | P7: =SUM(D7:O7) -> 0 | Q7: 0 | R7: 0 | S7: 0 | T7: 0 | U7: 0 | V7: 0 | W7: 0 | X7: 0 | Y7: 0 | Z7: 0 | AA7: 0 | AB7: 0 | AC7: =SUM(Q7:AB7) -> 0 | AD7: 0 | AE7: 0 | AF7: 0 | AG7: 0 | AH7: 0 | AI7: 0 | AJ7: 0 | AK7: 0 | AL7: 0 | AM7: 0 | AN7: 0 | AO7: 0 | AP7: =SUM(AD7:AO7) -> 0 | AQ7: 0 | AR7: 0 | AS7: 0 | AT7: 0 | AU7: 0 | AV7: 0 | AW7: 0 | AX7: 0 | AY7: 0 | AZ7: 0 | BA7: 0 | BB7: 0 | BC7: =SUM(AQ7:BB7) -> 0 | BD7: 0 | BE7: 0 | BF7: 0 | BG7: 0 | BH7: 0 | BI7: 0 | BJ7: 0 | BK7: 0 | BL7: 0 | BM7: 0 | BN7: 0 | BO7: 0 | BP7: =SUM(BD7:BO7) -> 0 | BQ7: 0 | BR7: 0 | BS7: 0 | BT7: 0 | BU7: 0 | BV7: 0 | BW7: 0 | BX7: 0 | BY7: 0 | BZ7: 259.08 | CA7: 0 | CB7: 0 | CC7: =SUM(BQ7:CB7) -> 259.08 | CD7: =VLOOKUP("Condenação",[2]Saneamento!$A129:$CH171,CD46,0)+VLOOKUP("Penalidades/Irregularidades",[2]Saneamento!$A129:$CH171,CD46,0) -> 0 | CE7: =VLOOKUP("Condenação",[2]Saneamento!$A129:$CH171,CE46,0)+VLOOKUP("Penalidades/Irregularidades",[2]Saneamento!$A129:$CH171,CE46,0) -> 0 | CF7: =VLOOKUP("Condenação",[2]Saneamento!$A129:$CH171,CF46,0)+VLOOKUP("Penalidades/Irregularidades",[2]Saneamento!$A129:$CH171,CF46,0) -> 0 | CG7: =VLOOKUP("Condenação",[2]Saneamento!$A129:$CH171,CG46,0)+VLOOKUP("Penalidades/Irregularidades",[2]Saneamento!$A129:$CH171,CG46,0) -> 0 | CH7: =VLOOKUP("Condenação",[2]Saneamento!$A129:$CH171,CH46,0)+VLOOKUP("Penalidades/Irregularidades",[2]Saneamento!$A129:$CH171,CH46,0) -> 0 | CI7: =VLOOKUP("Condenação",[2]Saneamento!$A129:$CH171,CI46,0)+VLOOKUP("Penalidades/Irregularidades",[2]Saneamento!$A129:$CH171,CI46,0) -> 0 | CJ7: =VLOOKUP("Condenação",[2]Saneamento!$A129:$CH171,CJ46,0)+VLOOKUP("Penalidades/Irregularidades",[2]Saneamento!$A129:$CH171,CJ46,0) -> 0 | CK7: =VLOOKUP("Condenação",[2]Saneamento!$A129:$CH171,CK46,0)+VLOOKUP("Penalidades/Irregularidades",[2]Saneamento!$A129:$CH171,CK46,0) -> 0 | ... CO7: =VLOOKUP("Condenação",[2]Saneamento!$A129:$CH171,CO46,0)+VLOOKUP("Penalidades/Irregularidades",[2]Saneamento!$A129:$CH171,CO46,0) -> 0 | CP7: =SUM(CD7:CO7) -> 0
A8: SANEAMENTO | B8: SANEAMENTO - FAB | C8: 0 | D8: 0 | E8: 0 | F8: 0 | G8: 0 | H8: 0 | I8: 0 | J8: 0 | K8: 0 | L8: 0 | M8: 0 | N8: 0 | O8: 0 | P8: =SUM(D8:O8) -> 0 | Q8: 0 | R8: 0 | S8: 0 | T8: 0 | U8: 0 | V8: 0 | W8: 0 | X8: 0 | Y8: 0 | Z8: 0 | AA8: 0 | AB8: 0 | AC8: =SUM(Q8:AB8) -> 0 | AD8: 0 | AE8: 0 | AF8: 0 | AG8: 0 | AH8: 0 | AI8: 0 | AJ8: 0 | AK8: 0 | AL8: 0 | AM8: 0 | AN8: 0 | AO8: 0 | AP8: =SUM(AD8:AO8) -> 0 | AQ8: 0 | AR8: 0 | AS8: 0 | AT8: 0 | AU8: 0 | AV8: 0 | AW8: 0 | AX8: 0 | AY8: 0 | AZ8: 0 | BA8: 0 | BB8: 0 | BC8: =SUM(AQ8:BB8) -> 0 | BD8: 0 | BE8: 0 | BF8: 0 | BG8: 0 | BH8: 0 | BI8: 0 | BJ8: 0 | BK8: 0 | BL8: 0 | BM8: 0 | BN8: 0 | BO8: 0 | BP8: =SUM(BD8:BO8) -> 0 | BQ8: 0 | BR8: 0 | BS8: 0 | BT8: 0 | BU8: 0 | BV8: 0 | BW8: 0 | BX8: 0 | BY8: 0 | BZ8: 0 | CA8: 0 | CB8: 0 | CC8: =SUM(BQ8:CB8) -> 0 | CD8: =VLOOKUP("Condenação",[2]Saneamento!$A253:$CH295,CD46,0)+VLOOKUP("Penalidades/Irregularidades",[2]Saneamento!$A253:$CH295,CD46,0) -> 0 | CE8: =VLOOKUP("Condenação",[2]Saneamento!$A253:$CH295,CE46,0)+VLOOKUP("Penalidades/Irregularidades",[2]Saneamento!$A253:$CH295,CE46,0) -> 0 | CF8: =VLOOKUP("Condenação",[2]Saneamento!$A253:$CH295,CF46,0)+VLOOKUP("Penalidades/Irregularidades",[2]Saneamento!$A253:$CH295,CF46,0) -> 0 | CG8: =VLOOKUP("Condenação",[2]Saneamento!$A253:$CH295,CG46,0)+VLOOKUP("Penalidades/Irregularidades",[2]Saneamento!$A253:$CH295,CG46,0) -> 0 | CH8: =VLOOKUP("Condenação",[2]Saneamento!$A253:$CH295,CH46,0)+VLOOKUP("Penalidades/Irregularidades",[2]Saneamento!$A253:$CH295,CH46,0) -> 0 | CI8: =VLOOKUP("Condenação",[2]Saneamento!$A253:$CH295,CI46,0)+VLOOKUP("Penalidades/Irregularidades",[2]Saneamento!$A253:$CH295,CI46,0) -> 0 | CJ8: =VLOOKUP("Condenação",[2]Saneamento!$A253:$CH295,CJ46,0)+VLOOKUP("Penalidades/Irregularidades",[2]Saneamento!$A253:$CH295,CJ46,0) -> 0 | CK8: =VLOOKUP("Condenação",[2]Saneamento!$A253:$CH295,CK46,0)+VLOOKUP("Penalidades/Irregularidades",[2]Saneamento!$A253:$CH295,CK46,0) -> 0 | ... CO8: =VLOOKUP("Condenação",[2]Saneamento!$A253:$CH295,CO46,0)+VLOOKUP("Penalidades/Irregularidades",[2]Saneamento!$A253:$CH295,CO46,0) -> 0 | CP8: =SUM(CD8:CO8) -> 0
A9: SANEAMENTO | B9: SANEAMENTO - PROLAGOS | C9: 0 | D9: 0 | E9: 0 | F9: 0 | G9: 0 | H9: 0 | I9: 0 | J9: 0 | K9: 0 | L9: 0 | M9: 0 | N9: 0 | O9: 0 | P9: =SUM(D9:O9) -> 0 | Q9: 0 | R9: 0 | S9: 0 | T9: 0 | U9: 0 | V9: 0 | W9: 0 | X9: 0 | Y9: 0 | Z9: 0 | AA9: 0 | AB9: 0 | AC9: =SUM(Q9:AB9) -> 0 | AD9: 0 | AE9: 0 | AF9: 0 | AG9: 0 | AH9: 0 | AI9: 0 | AJ9: 0 | AK9: 0 | AL9: 0 | AM9: 0 | AN9: 0 | AO9: 0 | AP9: =SUM(AD9:AO9) -> 0 | AQ9: 0 | AR9: 0 | AS9: 0 | AT9: 0 | AU9: 0 | AV9: 0 | AW9: 0 | AX9: 0 | AY9: 0 | AZ9: 0 | BA9: 0 | BB9: 0 | BC9: =SUM(AQ9:BB9) -> 0 | BD9: 0 | BE9: 0 | BF9: 0 | BG9: 0 | BH9: 0 | BI9: 0 | BJ9: 0 | BK9: 0 | BL9: 0 | BM9: 0 | BN9: 0 | BO9: 0 | BP9: =SUM(BD9:BO9) -> 0 | BQ9: 0 | BR9: 0 | BS9: 0 | BT9: 0 | BU9: 0 | BV9: 0 | BW9: 0 | BX9: 0 | BY9: 0 | BZ9: 0 | CA9: 16020.4 | CB9: 0 | CC9: =SUM(BQ9:CB9) -> 16020.4 | CD9: =VLOOKUP("Condenação",[2]Saneamento!$A563:$CH605,CD46,0)+VLOOKUP("Penalidades/Irregularidades",[2]Saneamento!$A563:$CH605,CD46,0) -> 0 | CE9: =VLOOKUP("Condenação",[2]Saneamento!$A563:$CH605,CE46,0)+VLOOKUP("Penalidades/Irregularidades",[2]Saneamento!$A563:$CH605,CE46,0) -> 0 | CF9: =VLOOKUP("Condenação",[2]Saneamento!$A563:$CH605,CF46,0)+VLOOKUP("Penalidades/Irregularidades",[2]Saneamento!$A563:$CH605,CF46,0) -> 0 | CG9: =VLOOKUP("Condenação",[2]Saneamento!$A563:$CH605,CG46,0)+VLOOKUP("Penalidades/Irregularidades",[2]Saneamento!$A563:$CH605,CG46,0) -> 0 | CH9: =VLOOKUP("Condenação",[2]Saneamento!$A563:$CH605,CH46,0)+VLOOKUP("Penalidades/Irregularidades",[2]Saneamento!$A563:$CH605,CH46,0) -> 0 | CI9: =VLOOKUP("Condenação",[2]Saneamento!$A563:$CH605,CI46,0)+VLOOKUP("Penalidades/Irregularidades",[2]Saneamento!$A563:$CH605,CI46,0) -> 0 | CJ9: =VLOOKUP("Condenação",[2]Saneamento!$A563:$CH605,CJ46,0)+VLOOKUP("Penalidades/Irregularidades",[2]Saneamento!$A563:$CH605,CJ46,0) -> 0 | CK9: =VLOOKUP("Condenação",[2]Saneamento!$A563:$CH605,CK46,0)+VLOOKUP("Penalidades/Irregularidades",[2]Saneamento!$A563:$CH605,CK46,0) -> 0 | ... CO9: =VLOOKUP("Condenação",[2]Saneamento!$A563:$CH605,CO46,0)+VLOOKUP("Penalidades/Irregularidades",[2]Saneamento!$A563:$CH605,CO46,0) -> 0 | CP9: =SUM(CD9:CO9) -> 0
A10: SANEAMENTO | B10: SANEAMENTO - RIO+ | C10: 0 | D10: 0 | E10: 0 | F10: 0 | G10: 0 | H10: 0 | I10: 0 | J10: 0 | K10: 0 | L10: 0 | M10: 0 | N10: 0 | O10: 0 | P10: =SUM(D10:O10) -> 0 | Q10: 0 | R10: 0 | S10: 0 | T10: 0 | U10: 0 | V10: 0 | W10: 0 | X10: 0 | Y10: 0 | Z10: 0 | AA10: 0 | AB10: 0 | AC10: =SUM(Q10:AB10) -> 0 | AD10: 0 | AE10: 0 | AF10: 0 | AG10: 0 | AH10: 0 | AI10: 0 | AJ10: 0 | AK10: 0 | AL10: 0 | AM10: 0 | AN10: 0 | AO10: 0 | AP10: =SUM(AD10:AO10) -> 0 | AQ10: 0 | AR10: 0 | AS10: 0 | AT10: 0 | AU10: 0 | AV10: 0 | AW10: 0 | AX10: 0 | AY10: 0 | AZ10: 0 | BA10: 0 | BB10: 0 | BC10: =SUM(AQ10:BB10) -> 0 | BD10: 0 | BE10: 0 | BF10: 0 | BG10: 0 | BH10: 0 | BI10: 0 | BJ10: 0 | BK10: 0 | BL10: 0 | BM10: 0 | BN10: 0 | BO10: 0 | BP10: =SUM(BD10:BO10) -> 0 | BQ10: 0 | BR10: 0 | BS10: 0 | BT10: 0 | BU10: 0 | BV10: 0 | BW10: 0 | BX10: 0 | BY10: 0 | BZ10: 0 | CA10: 0 | CB10: 0 | CC10: =SUM(BQ10:CB10) -> 0 | CD10: =VLOOKUP("Condenação",[2]Saneamento!$A191:$CH233,CD46,0)+VLOOKUP("Penalidades/Irregularidades",[2]Saneamento!$A191:$CH233,CD46,0) -> 0 | CE10: =VLOOKUP("Condenação",[2]Saneamento!$A191:$CH233,CE46,0)+VLOOKUP("Penalidades/Irregularidades",[2]Saneamento!$A191:$CH233,CE46,0) -> 0 | CF10: =VLOOKUP("Condenação",[2]Saneamento!$A191:$CH233,CF46,0)+VLOOKUP("Penalidades/Irregularidades",[2]Saneamento!$A191:$CH233,CF46,0) -> 0 | CG10: =VLOOKUP("Condenação",[2]Saneamento!$A191:$CH233,CG46,0)+VLOOKUP("Penalidades/Irregularidades",[2]Saneamento!$A191:$CH233,CG46,0) -> 0 | CH10: =VLOOKUP("Condenação",[2]Saneamento!$A191:$CH233,CH46,0)+VLOOKUP("Penalidades/Irregularidades",[2]Saneamento!$A191:$CH233,CH46,0) -> 0 | CI10: =VLOOKUP("Condenação",[2]Saneamento!$A191:$CH233,CI46,0)+VLOOKUP("Penalidades/Irregularidades",[2]Saneamento!$A191:$CH233,CI46,0) -> 0 | CJ10: =VLOOKUP("Condenação",[2]Saneamento!$A191:$CH233,CJ46,0)+VLOOKUP("Penalidades/Irregularidades",[2]Saneamento!$A191:$CH233,CJ46,0) -> 0 | CK10: =VLOOKUP("Condenação",[2]Saneamento!$A191:$CH233,CK46,0)+VLOOKUP("Penalidades/Irregularidades",[2]Saneamento!$A191:$CH233,CK46,0) -> 0 | ... CO10: =VLOOKUP("Condenação",[2]Saneamento!$A191:$CH233,CO46,0)+VLOOKUP("Penalidades/Irregularidades",[2]Saneamento!$A191:$CH233,CO46,0) -> 0 | CP10: =SUM(CD10:CO10) -> 0
A11: SANEAMENTO | B11: SANEAMENTO - VERDE ALAGOAS | C11: 0 | D11: 0 | E11: 0 | F11: 0 | G11: 0 | H11: 0 | I11: 0 | J11: 0 | K11: 0 | L11: 0 | M11: 0 | N11: 0 | O11: 0 | P11: =SUM(D11:O11) -> 0 | Q11: 0 | R11: 0 | S11: 0 | T11: 0 | U11: 0 | V11: 0 | W11: 0 | X11: 0 | Y11: 0 | Z11: 0 | AA11: 0 | AB11: 0 | AC11: =SUM(Q11:AB11) -> 0 | AD11: 0 | AE11: 0 | AF11: 0 | AG11: 0 | AH11: 0 | AI11: 0 | AJ11: 0 | AK11: 0 | AL11: 0 | AM11: 0 | AN11: 0 | AO11: 0 | AP11: =SUM(AD11:AO11) -> 0 | AQ11: 0 | AR11: 0 | AS11: 0 | AT11: 0 | AU11: 0 | AV11: 0 | AW11: 0 | AX11: 0 | AY11: 0 | AZ11: 0 | BA11: 0 | BB11: 0 | BC11: =SUM(AQ11:BB11) -> 0 | BD11: 0 | BE11: 0 | BF11: 0 | BG11: 0 | BH11: 0 | BI11: 0 | BJ11: 0 | BK11: 0 | BL11: 0 | BM11: 0 | BN11: 0 | BO11: 0 | BP11: =SUM(BD11:BO11) -> 0 | BQ11: 0 | BR11: 0 | BS11: 0 | BT11: 0 | BU11: 0 | BV11: 0 | BW11: 0 | BX11: 0 | BY11: 0 | BZ11: 0 | CA11: 0 | CB11: 0 | CC11: =SUM(BQ11:CB11) -> 0 | CD11: =VLOOKUP("Condenação",[2]Saneamento!$A315:$CH357,CD46,0)+VLOOKUP("Penalidades/Irregularidades",[2]Saneamento!$A315:$CH357,CD46,0) -> 0 | CE11: =VLOOKUP("Condenação",[2]Saneamento!$A315:$CH357,CE46,0)+VLOOKUP("Penalidades/Irregularidades",[2]Saneamento!$A315:$CH357,CE46,0) -> 0 | CF11: =VLOOKUP("Condenação",[2]Saneamento!$A315:$CH357,CF46,0)+VLOOKUP("Penalidades/Irregularidades",[2]Saneamento!$A315:$CH357,CF46,0) -> 0 | CG11: =VLOOKUP("Condenação",[2]Saneamento!$A315:$CH357,CG46,0)+VLOOKUP("Penalidades/Irregularidades",[2]Saneamento!$A315:$CH357,CG46,0) -> 0 | CH11: =VLOOKUP("Condenação",[2]Saneamento!$A315:$CH357,CH46,0)+VLOOKUP("Penalidades/Irregularidades",[2]Saneamento!$A315:$CH357,CH46,0) -> 0 | CI11: =VLOOKUP("Condenação",[2]Saneamento!$A315:$CH357,CI46,0)+VLOOKUP("Penalidades/Irregularidades",[2]Saneamento!$A315:$CH357,CI46,0) -> 0 | CJ11: =VLOOKUP("Condenação",[2]Saneamento!$A315:$CH357,CJ46,0)+VLOOKUP("Penalidades/Irregularidades",[2]Saneamento!$A315:$CH357,CJ46,0) -> 0 | CK11: =VLOOKUP("Condenação",[2]Saneamento!$A315:$CH357,CK46,0)+VLOOKUP("Penalidades/Irregularidades",[2]Saneamento!$A315:$CH357,CK46,0) -> 0 | ... CO11: =VLOOKUP("Condenação",[2]Saneamento!$A315:$CH357,CO46,0)+VLOOKUP("Penalidades/Irregularidades",[2]Saneamento!$A315:$CH357,CO46,0) -> 0 | CP11: =SUM(CD11:CO11) -> 0
A12: BRADESCO | B12: BRADESCO | C12: 0 | D12: 0 | E12: 0 | F12: 0 | G12: 0 | H12: 0 | I12: 0 | J12: 0 | K12: 0 | L12: 0 | M12: 0 | N12: 0 | O12: 0 | P12: =SUM(D12:O12) -> 0 | Q12: 0 | R12: 0 | S12: 0 | T12: 0 | U12: 0 | V12: 0 | W12: 0 | X12: 0 | Y12: 0 | Z12: 0 | AA12: 0 | AB12: 0 | AC12: =SUM(Q12:AB12) -> 0 | AD12: 0 | AE12: 0 | AF12: 0 | AG12: 0 | AH12: 0 | AI12: 9764.59 | AJ12: 0 | AK12: 0 | AL12: 5021.98 | AM12: 0 | AN12: 0 | AO12: 0 | AP12: =SUM(AD12:AO12) -> 14786.57 | AQ12: 0 | AR12: 0 | AS12: 0 | AT12: 0 | AU12: 0 | AV12: 0 | AW12: 0 | AX12: 0 | AY12: 0 | AZ12: 0 | BA12: 0 | BB12: 0 | BC12: =SUM(AQ12:BB12) -> 0 | BD12: 0 | BE12: 0 | BF12: 0 | BG12: 0 | BH12: 0 | BI12: 0 | BJ12: 0 | BK12: 0 | BL12: 0 | BM12: 20861.13 | BN12: 864.1 | BO12: 841.11 | BP12: =SUM(BD12:BO12) -> 22566.34 | BQ12: 7756.08 | BR12: 16889.71 | BS12: 362.85 | BT12: 1187.04 | BU12: 0 | BV12: 210.25 | BW12: 0 | BX12: 2036.12 | BY12: 0 | BZ12: 0 | CA12: 1341.73 | CB12: 2417 | CC12: =SUM(BQ12:CB12) -> 32200.78 | CD12: =VLOOKUP("Condenação",[2]Bradesco!$A$11:$CH$80,CD46,0)+VLOOKUP("Penalidades/Irregularidades",[2]Bradesco!$A$11:$CH$80,CD46,0) -> 2195.83 | CE12: =VLOOKUP("Condenação",[2]Bradesco!$A$11:$CH$80,CE46,0)+VLOOKUP("Penalidades/Irregularidades",[2]Bradesco!$A$11:$CH$80,CE46,0) -> 0 | CF12: =VLOOKUP("Condenação",[2]Bradesco!$A$11:$CH$80,CF46,0)+VLOOKUP("Penalidades/Irregularidades",[2]Bradesco!$A$11:$CH$80,CF46,0) -> 0 | CG12: =VLOOKUP("Condenação",[2]Bradesco!$A$11:$CH$80,CG46,0)+VLOOKUP("Penalidades/Irregularidades",[2]Bradesco!$A$11:$CH$80,CG46,0) -> 0 | CH12: =VLOOKUP("Condenação",[2]Bradesco!$A$11:$CH$80,CH46,0)+VLOOKUP("Penalidades/Irregularidades",[2]Bradesco!$A$11:$CH$80,CH46,0) -> 0 | CI12: =VLOOKUP("Condenação",[2]Bradesco!$A$11:$CH$80,CI46,0)+VLOOKUP("Penalidades/Irregularidades",[2]Bradesco!$A$11:$CH$80,CI46,0) -> 0 | CJ12: =VLOOKUP("Condenação",[2]Bradesco!$A$11:$CH$80,CJ46,0)+VLOOKUP("Penalidades/Irregularidades",[2]Bradesco!$A$11:$CH$80,CJ46,0) -> 0 | CK12: =VLOOKUP("Condenação",[2]Bradesco!$A$11:$CH$80,CK46,0)+VLOOKUP("Penalidades/Irregularidades",[2]Bradesco!$A$11:$CH$80,CK46,0) -> 0 | ... CO12: =VLOOKUP("Condenação",[2]Bradesco!$A$11:$CH$80,CO46,0)+VLOOKUP("Penalidades/Irregularidades",[2]Bradesco!$A$11:$CH$80,CO46,0) -> 0 | CP12: =SUM(CD12:CO12) -> 2195.83
A13: BS2 | B13: BS2 | C13: 8798.38 | D13: 0 | E13: 6874.78 | F13: 0 | G13: 0 | H13: 0 | I13: 0 | J13: 0 | K13: 0 | L13: 0 | M13: 0 | N13: 0 | O13: 0 | P13: =SUM(D13:O13) -> 6874.78 | Q13: 0 | R13: 0 | S13: 0 | T13: 0 | U13: 0 | V13: 0 | W13: 513.4 | X13: 0 | Y13: 0 | Z13: 0 | AA13: 0 | AB13: 0 | AC13: =SUM(Q13:AB13) -> 513.4 | AD13: 0 | AE13: 0 | AF13: 0 | AG13: 0 | AH13: 0 | AI13: 0 | AJ13: 0 | AK13: 1937.5 | AL13: 0 | AM13: 0 | AN13: 0 | AO13: 0 | AP13: =SUM(AD13:AO13) -> 1937.5 | AQ13: 0 | AR13: 0 | AS13: 0 | AT13: 0 | AU13: 0 | AV13: 9500 | AW13: 0 | AX13: 0 | AY13: 1665.88 | AZ13: 0 | BA13: 0 | BB13: 0 | BC13: =SUM(AQ13:BB13) -> 11165.88 | BD13: 0 | BE13: 0 | BF13: 0 | BG13: 0 | BH13: 0 | BI13: 0 | BJ13: 1379.96 | BK13: 0 | BL13: 0 | BM13: 560 | BN13: 8445 | BO13: 0 | BP13: =SUM(BD13:BO13) -> 10384.96 | BQ13: 0 | BR13: 0 | BS13: 0 | BT13: 0 | BU13: 0 | BV13: 0 | BW13: 0 | BX13: 0 | BY13: 0 | BZ13: 0 | CA13: 0 | CB13: 0 | CC13: =SUM(BQ13:CB13) -> 0 | CD13: =VLOOKUP("Condenação",[2]BS2!$A$11:$CH$80,CD46,0)+VLOOKUP("Penalidades/Irregularidades",[2]BS2!$A$11:$CH$80,CD46,0) -> 0 | CE13: =VLOOKUP("Condenação",[2]BS2!$A$11:$CH$80,CE46,0)+VLOOKUP("Penalidades/Irregularidades",[2]BS2!$A$11:$CH$80,CE46,0) -> 0 | CF13: =VLOOKUP("Condenação",[2]BS2!$A$11:$CH$80,CF46,0)+VLOOKUP("Penalidades/Irregularidades",[2]BS2!$A$11:$CH$80,CF46,0) -> 0 | CG13: =VLOOKUP("Condenação",[2]BS2!$A$11:$CH$80,CG46,0)+VLOOKUP("Penalidades/Irregularidades",[2]BS2!$A$11:$CH$80,CG46,0) -> 0 | CH13: =VLOOKUP("Condenação",[2]BS2!$A$11:$CH$80,CH46,0)+VLOOKUP("Penalidades/Irregularidades",[2]BS2!$A$11:$CH$80,CH46,0) -> 0 | CI13: =VLOOKUP("Condenação",[2]BS2!$A$11:$CH$80,CI46,0)+VLOOKUP("Penalidades/Irregularidades",[2]BS2!$A$11:$CH$80,CI46,0) -> 0 | CJ13: =VLOOKUP("Condenação",[2]BS2!$A$11:$CH$80,CJ46,0)+VLOOKUP("Penalidades/Irregularidades",[2]BS2!$A$11:$CH$80,CJ46,0) -> 0 | CK13: =VLOOKUP("Condenação",[2]BS2!$A$11:$CH$80,CK46,0)+VLOOKUP("Penalidades/Irregularidades",[2]BS2!$A$11:$CH$80,CK46,0) -> 0 | ... CO13: =VLOOKUP("Condenação",[2]BS2!$A$11:$CH$80,CO46,0)+VLOOKUP("Penalidades/Irregularidades",[2]BS2!$A$11:$CH$80,CO46,0) -> 0 | CP13: =SUM(CD13:CO13) -> 0
A14: BV | B14: BV | C14: 6637.68 | D14: 777.02 | E14: 0 | F14: 0 | G14: 300 | H14: 2500.01 | I14: 1044.82 | J14: 0 | K14: 0 | L14: 0 | M14: 0 | N14: 0 | O14: 300 | P14: =SUM(D14:O14) -> 4921.85 | Q14: 0 | R14: 0 | S14: 0 | T14: 3331.13 | U14: 0 | V14: 300 | W14: =900+300 -> 1200 | X14: 300 | Y14: 0 | Z14: 0 | AA14: 0 | AB14: 0 | AC14: =SUM(Q14:AB14) -> 5131.13 | AD14: 0 | AE14: 0 | AF14: 0 | AG14: 0 | AH14: 0 | AI14: 0 | AJ14: 0 | AK14: 0 | AL14: 0 | AM14: 0 | AN14: 0 | AO14: 0 | AP14: =SUM(AD14:AO14) -> 0 | AQ14: 0 | AR14: 0 | AS14: 0 | AT14: 0 | AU14: 0 | AV14: 0 | AW14: 0 | AX14: 0 | AY14: 0 | AZ14: 0 | BA14: 0 | BB14: 0 | BC14: =SUM(AQ14:BB14) -> 0 | BD14: 0 | BE14: 0 | BF14: 0 | BG14: 0 | BH14: 0 | BI14: 0 | BJ14: 0 | BK14: 0 | BL14: 0 | BM14: 0 | BN14: 0 | BO14: 0 | BP14: =SUM(BD14:BO14) -> 0 | BQ14: 0 | BR14: 0 | BS14: 0 | BT14: 0 | BU14: 0 | BV14: 0 | BW14: 0 | BX14: 0 | BY14: 0 | BZ14: 0 | CA14: 0 | CB14: 0 | CC14: =SUM(BQ14:CB14) -> 0 | CD14: 0 | CE14: 0 | CF14: 0 | CG14: 0 | CH14: 0 | CI14: 0 | CJ14: 0 | CK14: 0 | CL14: 0 | CM14: 0 | CN14: 0 | CO14: 0 | CP14: =SUM(CD14:CO14) -> 0
A15: IMOBILIÁRIO | B15: IMOBILIÁRIO | C15: 236.63 | D15: 0 | E15: 0 | F15: 0 | G15: 0 | H15: 0 | I15: 0 | J15: 0 | K15: 0 | L15: 0 | M15: 0 | N15: 0 | O15: 0 | P15: =SUM(D15:O15) -> 0 | Q15: 0 | R15: 0 | S15: 0 | T15: 0 | U15: 0 | V15: 0 | W15: 0 | X15: 0 | Y15: 0 | Z15: 0 | AA15: 0 | AB15: 0 | AC15: =SUM(Q15:AB15) -> 0 | AD15: 0 | AE15: 0 | AF15: 0 | AG15: 0 | AH15: 0 | AI15: 0 | AJ15: 0 | AK15: 0 | AL15: 0 | AM15: 0 | AN15: 0 | AO15: 170000 | AP15: =SUM(AD15:AO15) -> 170000 | AQ15: 6666.67 | AR15: 6666.67 | AS15: 6666.67 | AT15: 6666.67 | AU15: 6666.67 | AV15: 6666.67 | AW15: 6666.67 | AX15: 6666.67 | AY15: 6666.67 | AZ15: 6666.67 | BA15: 16206.67 | BB15: 6666.67 | BC15: =SUM(AQ15:BB15) -> 89540.04 | BD15: 7007.51 | BE15: 7007.51 | BF15: 7007.51 | BG15: 7007.51 | BH15: 7007.51 | BI15: 7007.51 | BJ15: 7007.51 | BK15: 7007.51 | BL15: 7007.51 | BM15: 7007.51 | BN15: 7007.51 | BO15: 7007.51 | BP15: =SUM(BD15:BO15) -> 84090.12 | BQ15: 7007.51 | BR15: 7725.85 | BS15: 7366.68 | BT15: 8697.83 | BU15: 7366.68 | BV15: 7366.68 | BW15: 0 | BX15: 0 | BY15: 0 | BZ15: 0 | CA15: 0 | CB15: 0 | CC15: =SUM(BQ15:CB15) -> 45531.23 | CD15: =VLOOKUP("Condenação",[2]Patrimônio!$A$11:$CH$80,CD46,0)+VLOOKUP("Penalidades/Irregularidades",[2]Patrimônio!$A$11:$CH$80,CD46,0) -> 0 | CE15: =VLOOKUP("Condenação",[2]Patrimônio!$A$11:$CH$80,CE46,0)+VLOOKUP("Penalidades/Irregularidades",[2]Patrimônio!$A$11:$CH$80,CE46,0) -> 18000 | CF15: =VLOOKUP("Condenação",[2]Patrimônio!$A$11:$CH$80,CF46,0)+VLOOKUP("Penalidades/Irregularidades",[2]Patrimônio!$A$11:$CH$80,CF46,0) -> 0 | CG15: =VLOOKUP("Condenação",[2]Patrimônio!$A$11:$CH$80,CG46,0)+VLOOKUP("Penalidades/Irregularidades",[2]Patrimônio!$A$11:$CH$80,CG46,0) -> 0 | CH15: =VLOOKUP("Condenação",[2]Patrimônio!$A$11:$CH$80,CH46,0)+VLOOKUP("Penalidades/Irregularidades",[2]Patrimônio!$A$11:$CH$80,CH46,0) -> 0 | CI15: =VLOOKUP("Condenação",[2]Patrimônio!$A$11:$CH$80,CI46,0)+VLOOKUP("Penalidades/Irregularidades",[2]Patrimônio!$A$11:$CH$80,CI46,0) -> 0 | CJ15: =VLOOKUP("Condenação",[2]Patrimônio!$A$11:$CH$80,CJ46,0)+VLOOKUP("Penalidades/Irregularidades",[2]Patrimônio!$A$11:$CH$80,CJ46,0) -> 0 | CK15: =VLOOKUP("Condenação",[2]Patrimônio!$A$11:$CH$80,CK46,0)+VLOOKUP("Penalidades/Irregularidades",[2]Patrimônio!$A$11:$CH$80,CK46,0) -> 0 | ... CO15: =VLOOKUP("Condenação",[2]Patrimônio!$A$11:$CH$80,CO46,0)+VLOOKUP("Penalidades/Irregularidades",[2]Patrimônio!$A$11:$CH$80,CO46,0) -> 0 | CP15: =SUM(CD15:CO15) -> 18000
A16: AMERICANAS | B16: AMERICANAS | C16: 17897.31 | D16: 760.72 | E16: 720.08 | F16: 0 | G16: 0 | H16: 2196.56 | I16: 40.64 | J16: 0 | K16: 0 | L16: 0 | M16: 7719.49 | N16: 0 | O16: 0 | P16: =SUM(D16:O16) -> 11437.49 | Q16: 0 | R16: 0 | S16: 0 | T16: 0 | U16: 0 | V16: 0 | W16: 0 | X16: 0 | Y16: 0 | Z16: 0 | AA16: 0 | AB16: 0 | AC16: =SUM(Q16:AB16) -> 0 | AD16: 0 | AE16: 0 | AF16: 0 | AG16: 0 | AH16: 0 | AI16: 0 | AJ16: 0 | AK16: 0 | AL16: 0 | AM16: 0 | AN16: 0 | AO16: 0 | AP16: =SUM(AD16:AO16) -> 0 | AQ16: 0 | AR16: 0 | AS16: 0 | AT16: 0 | AU16: 0 | AV16: 0 | AW16: 0 | AX16: 0 | AY16: 0 | AZ16: 0 | BA16: 0 | BB16: 0 | BC16: =SUM(AQ16:BB16) -> 0 | BD16: 0 | BE16: 0 | BF16: 0 | BG16: 0 | BH16: 0 | BI16: 0 | BJ16: 0 | BK16: 0 | BL16: 0 | BM16: 0 | BN16: 0 | BO16: 0 | BP16: =SUM(BD16:BO16) -> 0 | BQ16: 0 | BR16: 0 | BS16: 0 | BT16: 0 | BU16: 0 | BV16: 0 | BW16: 0 | BX16: 0 | BY16: 0 | BZ16: 0 | CA16: 0 | CB16: 0 | CC16: =SUM(BQ16:CB16) -> 0 | CD16: 0 | CE16: 0 | CF16: 0 | CG16: 0 | CH16: 0 | CI16: 0 | CJ16: 0 | CK16: 0 | CL16: 0 | CM16: 0 | CN16: 0 | CO16: 0 | CP16: =SUM(CD16:CO16) -> 0
A17: MERCADO LIVRE | B17: MERCADO LIVRE | C17: 58706.88 | D17: 13880.93 | E17: 12261.56 | F17: 27171.63 | G17: 0 | H17: 608.23 | I17: 0 | J17: 0 | K17: 608.23 | L17: 3556.55 | M17: 0 | N17: 52314.59 | O17: 11000 | P17: =SUM(D17:O17) -> 121401.72 | Q17: 0 | R17: 0 | S17: 0 | T17: 0 | U17: 0 | V17: 5031.42 | W17: 0 | X17: 0 | Y17: 0 | Z17: 0 | AA17: 0 | AB17: 576 | AC17: =SUM(Q17:AB17) -> 5607.42 | AD17: 0 | AE17: 3776.8 | AF17: 1970 | AG17: 0 | AH17: 3450 | AI17: 0 | AJ17: 2040.76 | AK17: 587.61 | AL17: 0 | AM17: 768.2 | AN17: 0 | AO17: -1700 | AP17: =SUM(AD17:AO17) -> 10893.37 | AQ17: 0 | AR17: 1860.35 | AS17: 12759.76 | AT17: 0 | AU17: 3833.27 | AV17: 11013.97 | AW17: 2211 | AX17: 0 | AY17: 0 | AZ17: 6572.03 | BA17: 0 | BB17: 4548.34 | BC17: =SUM(AQ17:BB17) -> 42798.72 | BD17: 4548.34 | BE17: 8089.7 | BF17: 0 | BG17: 13294.18 | BH17: 54012.77 | BI17: 35918.15 | BJ17: 139309.38 | BK17: 71149.53 | BL17: 29647.42 | BM17: 34566.85 | BN17: 16839.2 | BO17: 23375.53 | BP17: =SUM(BD17:BO17) -> 430751.05 | BQ17: 0 | BR17: 3289.71 | BS17: 10942 | BT17: 10098.88 | BU17: -43341.51 | BV17: 35823.64 | BW17: 9190.19 | BX17: 9547.07 | BY17: 6900 | BZ17: 0 | CA17: 0 | CB17: 0 | CC17: =SUM(BQ17:CB17) -> 42449.98 | CD17: =VLOOKUP("Condenação",'[2]Mercado Livre'!$A$11:$CH$80,CD46,0)+VLOOKUP("Penalidades/Irregularidades",'[2]Mercado Livre'!$A$11:$CH$80,CD46,0) -> 0 | CE17: =VLOOKUP("Condenação",'[2]Mercado Livre'!$A$11:$CH$80,CE46,0)+VLOOKUP("Penalidades/Irregularidades",'[2]Mercado Livre'!$A$11:$CH$80,CE46,0) -> 0 | CF17: =VLOOKUP("Condenação",'[2]Mercado Livre'!$A$11:$CH$80,CF46,0)+VLOOKUP("Penalidades/Irregularidades",'[2]Mercado Livre'!$A$11:$CH$80,CF46,0) -> 0 | CG17: =VLOOKUP("Condenação",'[2]Mercado Livre'!$A$11:$CH$80,CG46,0)+VLOOKUP("Penalidades/Irregularidades",'[2]Mercado Livre'!$A$11:$CH$80,CG46,0) -> 0 | CH17: =VLOOKUP("Condenação",'[2]Mercado Livre'!$A$11:$CH$80,CH46,0)+VLOOKUP("Penalidades/Irregularidades",'[2]Mercado Livre'!$A$11:$CH$80,CH46,0) -> 0 | CI17: =VLOOKUP("Condenação",'[2]Mercado Livre'!$A$11:$CH$80,CI46,0)+VLOOKUP("Penalidades/Irregularidades",'[2]Mercado Livre'!$A$11:$CH$80,CI46,0) -> 0 | CJ17: =VLOOKUP("Condenação",'[2]Mercado Livre'!$A$11:$CH$80,CJ46,0)+VLOOKUP("Penalidades/Irregularidades",'[2]Mercado Livre'!$A$11:$CH$80,CJ46,0) -> 0 | CK17: =VLOOKUP("Condenação",'[2]Mercado Livre'!$A$11:$CH$80,CK46,0)+VLOOKUP("Penalidades/Irregularidades",'[2]Mercado Livre'!$A$11:$CH$80,CK46,0) -> 0 | ... CO17: =VLOOKUP("Condenação",'[2]Mercado Livre'!$A$11:$CH$80,CO46,0)+VLOOKUP("Penalidades/Irregularidades",'[2]Mercado Livre'!$A$11:$CH$80,CO46,0) -> 0 | CP17: =SUM(CD17:CO17) -> 0
A18: CLARO | B18: CLARO | C18: 1016.98 | D18: 400 | E18: 0 | F18: 0 | G18: 0 | H18: 0 | I18: 0 | J18: 8208.94 | K18: 0 | L18: 0 | M18: 0 | N18: 0 | O18: 0 | P18: =SUM(D18:O18) -> 8608.94 | Q18: 0 | R18: 0 | S18: 0 | T18: 0 | U18: 2300 | V18: 1181.47 | W18: =483.52+801.96+150 -> 1435.48 | X18: 13689.01 | Y18: 2402.6 | Z18: 830 | AA18: 1940 | AB18: 13240.28 | AC18: =SUM(Q18:AB18) -> 37018.84 | AD18: 6353.77 | AE18: 1919.93 | AF18: 0 | AG18: 0 | AH18: 948.03 | AI18: 0 | AJ18: 0 | AK18: 0 | AL18: 861 | AM18: 320 | AN18: 0 | AO18: 0 | AP18: =SUM(AD18:AO18) -> 10402.73 | AQ18: 0 | AR18: 0 | AS18: 0 | AT18: 0 | AU18: 0 | AV18: 0 | AW18: 0 | AX18: 0 | AY18: 3793.63 | AZ18: 6853.36 | BA18: 9811.43 | BB18: 500 | BC18: =SUM(AQ18:BB18) -> 20958.42 | BD18: 7888.55 | BE18: 16450.96 | BF18: 6755 | BG18: 0 | BH18: 4035.24 | BI18: 787.54 | BJ18: 0 | BK18: 0 | BL18: 0 | BM18: 85.52 | BN18: 4189.25 | BO18: 6119.01 | BP18: =SUM(BD18:BO18) -> 46311.07 | BQ18: 0 | BR18: 0 | BS18: 690.29 | BT18: 0 | BU18: 0 | BV18: 4130.33 | BW18: 36.19 | BX18: 208.05 | BY18: 0 | BZ18: 1000 | CA18: 12183.06 | CB18: 3588.69 | CC18: =SUM(BQ18:CB18) -> 21836.61 | CD18: =VLOOKUP("Condenação",[2]Claro!$A$11:$CH$53,CD46,0)+VLOOKUP("Penalidades/Irregularidades",[2]Claro!$A$11:$CH$53,CD46,0)+VLOOKUP("Condenação",[2]Claro!$A$67:$CH$109,CD46,0)+VLOOKUP("Penalidades/Irregularidades",[2]Claro!$A$67:$CH$109,CD46,0) -> 2597.48 | CE18: =VLOOKUP("Condenação",[2]Claro!$A$11:$CH$53,CE46,0)+VLOOKUP("Penalidades/Irregularidades",[2]Claro!$A$11:$CH$53,CE46,0)+VLOOKUP("Condenação",[2]Claro!$A$67:$CH$109,CE46,0)+VLOOKUP("Penalidades/Irregularidades",[2]Claro!$A$67:$CH$109,CE46,0) -> 238.52 | CF18: =VLOOKUP("Condenação",[2]Claro!$A$11:$CH$53,CF46,0)+VLOOKUP("Penalidades/Irregularidades",[2]Claro!$A$11:$CH$53,CF46,0)+VLOOKUP("Condenação",[2]Claro!$A$67:$CH$109,CF46,0)+VLOOKUP("Penalidades/Irregularidades",[2]Claro!$A$67:$CH$109,CF46,0) -> 0 | CG18: =VLOOKUP("Condenação",[2]Claro!$A$11:$CH$53,CG46,0)+VLOOKUP("Penalidades/Irregularidades",[2]Claro!$A$11:$CH$53,CG46,0)+VLOOKUP("Condenação",[2]Claro!$A$67:$CH$109,CG46,0)+VLOOKUP("Penalidades/Irregularidades",[2]Claro!$A$67:$CH$109,CG46,0) -> 0 | CH18: =VLOOKUP("Condenação",[2]Claro!$A$11:$CH$53,CH46,0)+VLOOKUP("Penalidades/Irregularidades",[2]Claro!$A$11:$CH$53,CH46,0)+VLOOKUP("Condenação",[2]Claro!$A$67:$CH$109,CH46,0)+VLOOKUP("Penalidades/Irregularidades",[2]Claro!$A$67:$CH$109,CH46,0) -> 0 | CI18: =VLOOKUP("Condenação",[2]Claro!$A$11:$CH$53,CI46,0)+VLOOKUP("Penalidades/Irregularidades",[2]Claro!$A$11:$CH$53,CI46,0)+VLOOKUP("Condenação",[2]Claro!$A$67:$CH$109,CI46,0)+VLOOKUP("Penalidades/Irregularidades",[2]Claro!$A$67:$CH$109,CI46,0) -> 0 | CJ18: =VLOOKUP("Condenação",[2]Claro!$A$11:$CH$53,CJ46,0)+VLOOKUP("Penalidades/Irregularidades",[2]Claro!$A$11:$CH$53,CJ46,0)+VLOOKUP("Condenação",[2]Claro!$A$67:$CH$109,CJ46,0)+VLOOKUP("Penalidades/Irregularidades",[2]Claro!$A$67:$CH$109,CJ46,0) -> 0 | CK18: =VLOOKUP("Condenação",[2]Claro!$A$11:$CH$53,CK46,0)+VLOOKUP("Penalidades/Irregularidades",[2]Claro!$A$11:$CH$53,CK46,0)+VLOOKUP("Condenação",[2]Claro!$A$67:$CH$109,CK46,0)+VLOOKUP("Penalidades/Irregularidades",[2]Claro!$A$67:$CH$109,CK46,0) -> 0 | ... CO18: =VLOOKUP("Condenação",[2]Claro!$A$11:$CH$53,CO46,0)+VLOOKUP("Penalidades/Irregularidades",[2]Claro!$A$11:$CH$53,CO46,0)+VLOOKUP("Condenação",[2]Claro!$A$67:$CH$109,CO46,0)+VLOOKUP("Penalidades/Irregularidades",[2]Claro!$A$67:$CH$109,CO46,0) -> 0 | CP18: =SUM(CD18:CO18) -> 2836
A19: CASA E VÍDEO | B19: CASA E VÍDEO | C19: 0 | D19: 0 | E19: 0 | F19: 0 | G19: 0 | H19: 0 | I19: 0 | J19: 0 | K19: 0 | L19: 0 | M19: 0 | N19: 0 | O19: 0 | P19: =SUM(D19:O19) -> 0 | Q19: 0 | R19: 0 | S19: 0 | T19: 0 | U19: 0 | V19: 0 | W19: 0 | Y19: 2039.03 | Z19: 0 | AA19: 0 | AB19: 0 | AC19: =SUM(Q19:AB19) -> 2039.03 | AD19: 0 | AE19: 0 | AF19: 0 | AG19: 0 | AH19: 0 | AI19: 0 | AJ19: 0 | AK19: 0 | AL19: 0 | AM19: 0 | AN19: 0 | AO19: 0 | AP19: =SUM(AD19:AO19) -> 0 | AQ19: 0 | AR19: 0 | AS19: 0 | AT19: 0 | AU19: 0 | AV19: 0 | AW19: 0 | AX19: 0 | AY19: 0 | AZ19: 0 | BA19: 0 | BB19: 0 | BC19: =SUM(AQ19:BB19) -> 0 | BD19: 0 | BE19: 0 | BF19: 0 | BG19: 0 | BH19: 0 | BI19: 0 | BJ19: 0 | BK19: 0 | BL19: 0 | BM19: 0 | BN19: 0 | BO19: 0 | BP19: =SUM(BD19:BO19) -> 0 | BQ19: 0 | BR19: 0 | BS19: 0 | BT19: 0 | BU19: 0 | BV19: 0 | BW19: 0 | BX19: 0 | BY19: 0 | BZ19: 0 | CA19: 0 | CB19: 0 | CC19: =SUM(BQ19:CB19) -> 0 | CD19: 0 | CE19: 0 | CF19: 0 | CG19: 0 | CH19: 0 | CI19: 0 | CJ19: 0 | CK19: 0 | CL19: 0 | CM19: 0 | CN19: 0 | CO19: 0 | CP19: =SUM(CD19:CO19) -> 0
A20: SANTANDER | B20: SANTANDER | C20: 15009.85 | D20: 0 | E20: 0 | F20: 0 | G20: 0 | H20: 0 | I20: 391.2 | J20: 0 | K20: 0 | L20: 720 | M20: 0 | N20: 0 | O20: 0 | P20: =SUM(D20:O20) -> 1111.2 | Q20: 0 | R20: 0 | S20: 0 | T20: 0 | U20: 3011.54 | V20: 0 | W20: 631 | X20: 20853.59 | Y20: 20853.59 | Z20: 20853.59 | AA20: 20853.59 | AB20: 0 | AC20: =SUM(Q20:AB20) -> 87056.9 | AD20: 3723.35 | AE20: 0 | AF20: 3723.35 | AG20: 7446.7 | AH20: 0 | AI20: 0 | AJ20: 0 | AK20: 0 | AL20: 0 | AM20: 0 | AN20: 0 | AO20: 0 | AP20: =SUM(AD20:AO20) -> 14893.4 | AQ20: 10504.13 | AR20: 10504.13 | AS20: 11797.55 | AT20: 10504.13 | AU20: 10504.13 | AV20: 10504.13 | AW20: 10504.13 | AX20: 10504.13 | AY20: 10504.13 | AZ20: 11399.23 | BA20: 10504.13 | BB20: 10504.13 | BC20: =SUM(AQ20:BB20) -> 128238.08 | BD20: 0 | BE20: 0 | BF20: 0 | BG20: 0 | BH20: 0 | BI20: 0 | BJ20: 0 | BK20: 0 | BL20: 0 | BM20: 3098 | BN20: 3098 | BO20: 3098 | BP20: =SUM(BD20:BO20) -> 9294 | BQ20: 3098 | BR20: 3098 | BS20: 3098 | BT20: 3098 | BU20: 3098 | BV20: 11121.65 | BW20: 8023.65 | BX20: 4925.65 | BY20: 6600.27 | BZ20: 6600.27 | CA20: 7131.94 | CB20: 6600.27 | CC20: =SUM(BQ20:CB20) -> 66493.7 | CD20: =VLOOKUP("Condenação",[2]Santander!$A$11:$CH$80,CD46,0)+VLOOKUP("Penalidades/Irregularidades",[2]Santander!$A$11:$CH$80,CD46,0) -> 538.69 | CE20: =VLOOKUP("Condenação",[2]Santander!$A$11:$CH$80,CE46,0)+VLOOKUP("Penalidades/Irregularidades",[2]Santander!$A$11:$CH$80,CE46,0) -> 0 | CF20: =VLOOKUP("Condenação",[2]Santander!$A$11:$CH$80,CF46,0)+VLOOKUP("Penalidades/Irregularidades",[2]Santander!$A$11:$CH$80,CF46,0) -> 0 | CG20: =VLOOKUP("Condenação",[2]Santander!$A$11:$CH$80,CG46,0)+VLOOKUP("Penalidades/Irregularidades",[2]Santander!$A$11:$CH$80,CG46,0) -> 0 | CH20: =VLOOKUP("Condenação",[2]Santander!$A$11:$CH$80,CH46,0)+VLOOKUP("Penalidades/Irregularidades",[2]Santander!$A$11:$CH$80,CH46,0) -> 0 | CI20: =VLOOKUP("Condenação",[2]Santander!$A$11:$CH$80,CI46,0)+VLOOKUP("Penalidades/Irregularidades",[2]Santander!$A$11:$CH$80,CI46,0) -> 0 | CJ20: =VLOOKUP("Condenação",[2]Santander!$A$11:$CH$80,CJ46,0)+VLOOKUP("Penalidades/Irregularidades",[2]Santander!$A$11:$CH$80,CJ46,0) -> 0 | CK20: =VLOOKUP("Condenação",[2]Santander!$A$11:$CH$80,CK46,0)+VLOOKUP("Penalidades/Irregularidades",[2]Santander!$A$11:$CH$80,CK46,0) -> 0 | ... CO20: =VLOOKUP("Condenação",[2]Santander!$A$11:$CH$80,CO46,0)+VLOOKUP("Penalidades/Irregularidades",[2]Santander!$A$11:$CH$80,CO46,0) -> 0 | CP20: =SUM(CD20:CO20) -> 538.69
A21: UOL PAGSEGURO | B21: UOL PAGSEGURO | C21: 244.4 | D21: 0 | E21: 0 | F21: 0 | G21: 0 | H21: 0 | I21: 0 | J21: 0 | K21: 0 | L21: 0 | M21: 0 | N21: 0 | O21: 0 | P21: =SUM(D21:O21) -> 0 | Q21: 0 | R21: 0 | S21: 0 | T21: 0 | U21: 0 | V21: 0 | W21: 0 | X21: 427.2 | Y21: 0 | Z21: 0 | AA21: 3000 | AB21: 0 | AC21: =SUM(Q21:AB21) -> 3427.2 | AD21: 0 | AE21: 0 | AF21: 0 | AG21: 0 | AH21: 0 | AI21: 0 | AJ21: 0 | AK21: 0 | AL21: 0 | AM21: 0 | AN21: 0 | AO21: 0 | AP21: =SUM(AD21:AO21) -> 0 | AQ21: 0 | AR21: 0 | AS21: 0 | AT21: 0 | AU21: 0 | AV21: 0 | AW21: 355.52 | AX21: 0 | AY21: 0 | AZ21: 0 | BA21: 0 | BB21: 0 | BC21: =SUM(AQ21:BB21) -> 355.52 | BD21: 0 | BE21: 0 | BF21: 0 | BG21: 3500 | BH21: 0 | BI21: 0 | BJ21: 0 | BK21: 0 | BL21: 0 | BM21: 0 | BN21: 0 | BO21: 0 | BP21: =SUM(BD21:BO21) -> 3500 | BQ21: 0 | BR21: 0 | BS21: 0 | BT21: 0 | BU21: 0 | BV21: 0 | BW21: 0 | BX21: 0 | BY21: 0 | BZ21: 0 | CA21: 0 | CB21: 0 | CC21: =SUM(BQ21:CB21) -> 0 | CD21: =VLOOKUP("Condenação",[2]UOL!$A$11:$CH$53,CD46,0)+VLOOKUP("Penalidades/Irregularidades",[2]UOL!$A$11:$CH$53,CD46,0)+VLOOKUP("Condenação",[2]UOL!$A$67:$CH$109,CD46,0)+VLOOKUP("Penalidades/Irregularidades",[2]UOL!$A$67:$CH$109,CD46,0)+VLOOKUP("Condenação",[2]UOL!$A$123:$CH$165,CD46,0)+VLOOKUP("Penalidades/Irregularidades",[2]UOL!$A$123:$CH$165,CD46,0) -> 0 | CE21: =VLOOKUP("Condenação",[2]UOL!$A$11:$CH$53,CE46,0)+VLOOKUP("Penalidades/Irregularidades",[2]UOL!$A$11:$CH$53,CE46,0)+VLOOKUP("Condenação",[2]UOL!$A$67:$CH$109,CE46,0)+VLOOKUP("Penalidades/Irregularidades",[2]UOL!$A$67:$CH$109,CE46,0)+VLOOKUP("Condenação",[2]UOL!$A$123:$CH$165,CE46,0)+VLOOKUP("Penalidades/Irregularidades",[2]UOL!$A$123:$CH$165,CE46,0) -> 0 | CF21: =VLOOKUP("Condenação",[2]UOL!$A$11:$CH$53,CF46,0)+VLOOKUP("Penalidades/Irregularidades",[2]UOL!$A$11:$CH$53,CF46,0)+VLOOKUP("Condenação",[2]UOL!$A$67:$CH$109,CF46,0)+VLOOKUP("Penalidades/Irregularidades",[2]UOL!$A$67:$CH$109,CF46,0)+VLOOKUP("Condenação",[2]UOL!$A$123:$CH$165,CF46,0)+VLOOKUP("Penalidades/Irregularidades",[2]UOL!$A$123:$CH$165,CF46,0) -> 0 | CG21: =VLOOKUP("Condenação",[2]UOL!$A$11:$CH$53,CG46,0)+VLOOKUP("Penalidades/Irregularidades",[2]UOL!$A$11:$CH$53,CG46,0)+VLOOKUP("Condenação",[2]UOL!$A$67:$CH$109,CG46,0)+VLOOKUP("Penalidades/Irregularidades",[2]UOL!$A$67:$CH$109,CG46,0)+VLOOKUP("Condenação",[2]UOL!$A$123:$CH$165,CG46,0)+VLOOKUP("Penalidades/Irregularidades",[2]UOL!$A$123:$CH$165,CG46,0) -> 0 | CH21: =VLOOKUP("Condenação",[2]UOL!$A$11:$CH$53,CH46,0)+VLOOKUP("Penalidades/Irregularidades",[2]UOL!$A$11:$CH$53,CH46,0)+VLOOKUP("Condenação",[2]UOL!$A$67:$CH$109,CH46,0)+VLOOKUP("Penalidades/Irregularidades",[2]UOL!$A$67:$CH$109,CH46,0)+VLOOKUP("Condenação",[2]UOL!$A$123:$CH$165,CH46,0)+VLOOKUP("Penalidades/Irregularidades",[2]UOL!$A$123:$CH$165,CH46,0) -> 0 | CI21: =VLOOKUP("Condenação",[2]UOL!$A$11:$CH$53,CI46,0)+VLOOKUP("Penalidades/Irregularidades",[2]UOL!$A$11:$CH$53,CI46,0)+VLOOKUP("Condenação",[2]UOL!$A$67:$CH$109,CI46,0)+VLOOKUP("Penalidades/Irregularidades",[2]UOL!$A$67:$CH$109,CI46,0)+VLOOKUP("Condenação",[2]UOL!$A$123:$CH$165,CI46,0)+VLOOKUP("Penalidades/Irregularidades",[2]UOL!$A$123:$CH$165,CI46,0) -> 0 | CJ21: =VLOOKUP("Condenação",[2]UOL!$A$11:$CH$53,CJ46,0)+VLOOKUP("Penalidades/Irregularidades",[2]UOL!$A$11:$CH$53,CJ46,0)+VLOOKUP("Condenação",[2]UOL!$A$67:$CH$109,CJ46,0)+VLOOKUP("Penalidades/Irregularidades",[2]UOL!$A$67:$CH$109,CJ46,0)+VLOOKUP("Condenação",[2]UOL!$A$123:$CH$165,CJ46,0)+VLOOKUP("Penalidades/Irregularidades",[2]UOL!$A$123:$CH$165,CJ46,0) -> 0 | CK21: =VLOOKUP("Condenação",[2]UOL!$A$11:$CH$53,CK46,0)+VLOOKUP("Penalidades/Irregularidades",[2]UOL!$A$11:$CH$53,CK46,0)+VLOOKUP("Condenação",[2]UOL!$A$67:$CH$109,CK46,0)+VLOOKUP("Penalidades/Irregularidades",[2]UOL!$A$67:$CH$109,CK46,0)+VLOOKUP("Condenação",[2]UOL!$A$123:$CH$165,CK46,0)+VLOOKUP("Penalidades/Irregularidades",[2]UOL!$A$123:$CH$165,CK46,0) -> 0 | ... CO21: =VLOOKUP("Condenação",[2]UOL!$A$11:$CH$53,CO46,0)+VLOOKUP("Penalidades/Irregularidades",[2]UOL!$A$11:$CH$53,CO46,0)+VLOOKUP("Condenação",[2]UOL!$A$67:$CH$109,CO46,0)+VLOOKUP("Penalidades/Irregularidades",[2]UOL!$A$67:$CH$109,CO46,0)+VLOOKUP("Condenação",[2]UOL!$A$123:$CH$165,CO46,0)+VLOOKUP("Penalidades/Irregularidades",[2]UOL!$A$123:$CH$165,CO46,0) -> 0 | CP21: =SUM(CD21:CO21) -> 0
A22: RESOLUÇÃO DE DISPUTAS | B22: RESOLUÇÃO DE DISPUTAS | C22: 0 | D22: 0 | E22: 0 | F22: 0 | G22: 0 | H22: 0 | I22: 0 | J22: 0 | K22: 0 | L22: 0 | M22: 0 | N22: 4000 | O22: 0 | P22: =SUM(D22:O22) -> 4000 | Q22: 0 | R22: 0 | S22: 0 | T22: 0 | U22: 0 | V22: 0 | W22: 0 | X22: 0 | Y22: 0 | Z22: 0 | AA22: 0 | AB22: 0 | AC22: =SUM(Q22:AB22) -> 0 | AD22: 0 | AE22: 0 | AF22: 0 | AG22: 0 | AH22: 0 | AI22: 4571.6 | AJ22: 0 | AK22: 2575.24 | AL22: 319.8 | AM22: 5268.96 | AN22: 0 | AO22: 8497.66 | AP22: =SUM(AD22:AO22) -> 21233.26 | AQ22: 0 | AR22: 3478.85 | AS22: 0 | AT22: 0 | AU22: 0 | AV22: 27352.89 | AW22: 0 | AX22: 3425.2 | AY22: 0 | AZ22: 0 | BA22: 0 | BB22: 0 | BC22: =SUM(AQ22:BB22) -> 34256.94 | BD22: 0 | BE22: 0 | BF22: 0 | BG22: 0 | BH22: 0 | BI22: 0 | BJ22: 0 | BK22: 0 | BL22: 0 | BM22: 8122.59 | BN22: 0 | BO22: -42.86 | BP22: =SUM(BD22:BO22) -> 8079.73 | BQ22: 0 | BR22: 0 | BS22: 0 | BT22: 1034.88 | BU22: 0 | BV22: 0 | BW22: 1094.31 | BX22: 0 | BY22: 2631.81 | BZ22: 0 | CA22: 0 | CB22: 0 | CC22: =SUM(BQ22:CB22) -> 4761 | CD22: =VLOOKUP("Condenação",'[2]Resolução de Disputas'!$A$11:$CI$53,CD46,0)+VLOOKUP("Penalidades/Irregularidades",'[2]Resolução de Disputas'!$A$11:$CI$53,CD46,0) -> 0 | CE22: =VLOOKUP("Condenação",'[2]Resolução de Disputas'!$A$11:$CI$53,CE46,0)+VLOOKUP("Penalidades/Irregularidades",'[2]Resolução de Disputas'!$A$11:$CI$53,CE46,0) -> 0 | CF22: =VLOOKUP("Condenação",'[2]Resolução de Disputas'!$A$11:$CI$53,CF46,0)+VLOOKUP("Penalidades/Irregularidades",'[2]Resolução de Disputas'!$A$11:$CI$53,CF46,0) -> 0 | CG22: =VLOOKUP("Condenação",'[2]Resolução de Disputas'!$A$11:$CI$53,CG46,0)+VLOOKUP("Penalidades/Irregularidades",'[2]Resolução de Disputas'!$A$11:$CI$53,CG46,0) -> 0 | CH22: =VLOOKUP("Condenação",'[2]Resolução de Disputas'!$A$11:$CI$53,CH46,0)+VLOOKUP("Penalidades/Irregularidades",'[2]Resolução de Disputas'!$A$11:$CI$53,CH46,0) -> 0 | CI22: =VLOOKUP("Condenação",'[2]Resolução de Disputas'!$A$11:$CI$53,CI46,0)+VLOOKUP("Penalidades/Irregularidades",'[2]Resolução de Disputas'!$A$11:$CI$53,CI46,0) -> 0 | CJ22: =VLOOKUP("Condenação",'[2]Resolução de Disputas'!$A$11:$CI$53,CJ46,0)+VLOOKUP("Penalidades/Irregularidades",'[2]Resolução de Disputas'!$A$11:$CI$53,CJ46,0) -> 0 | CK22: =VLOOKUP("Condenação",'[2]Resolução de Disputas'!$A$11:$CI$53,CK46,0)+VLOOKUP("Penalidades/Irregularidades",'[2]Resolução de Disputas'!$A$11:$CI$53,CK46,0) -> 0 | ... CO22: =VLOOKUP("Condenação",'[2]Resolução de Disputas'!$A$11:$CI$53,CO46,0)+VLOOKUP("Penalidades/Irregularidades",'[2]Resolução de Disputas'!$A$11:$CI$53,CO46,0) -> 0 | CP22: =SUM(CD22:CO22) -> 0
A23: WALMART | B23: WALMART | C23: 1452.23 | D23: 0 | E23: 0 | F23: 0 | G23: 0 | H23: 0 | I23: 0 | J23: 0 | K23: 0 | L23: 0 | M23: 0 | N23: 0 | O23: 0 | P23: =SUM(D23:O23) -> 0 | Q23: 0 | R23: 0 | S23: 0 | T23: 0 | U23: 0 | V23: 0 | W23: 0 | X23: 0 | Y23: 0 | Z23: 0 | AA23: 0 | AB23: 0 | AC23: =SUM(Q23:AB23) -> 0 | AD23: 0 | AE23: 0 | AF23: 0 | AG23: 0 | AH23: 0 | AI23: 0 | AJ23: 0 | AK23: 0 | AL23: 0 | AM23: 0 | AN23: 0 | AO23: 0 | AP23: =SUM(AD23:AO23) -> 0 | AQ23: 0 | AR23: 0 | AS23: 0 | AT23: 0 | AU23: 0 | AV23: 0 | AW23: 0 | AX23: 0 | AY23: 0 | AZ23: 0 | BA23: 0 | BB23: 0 | BC23: =SUM(AQ23:BB23) -> 0 | BD23: 0 | BE23: 0 | BF23: 0 | BG23: 0 | BH23: 0 | BI23: 0 | BJ23: 0 | BK23: 0 | BL23: 0 | BM23: 0 | BN23: 0 | BO23: 0 | BP23: =SUM(BD23:BO23) -> 0 | BQ23: 0 | BR23: 0 | BS23: 0 | BT23: 0 | BU23: 0 | BV23: 0 | BW23: 0 | BX23: 0 | BY23: 0 | BZ23: 0 | CA23: 0 | CB23: 0 | CC23: =SUM(BQ23:CB23) -> 0 | CD23: 0 | CE23: 0 | CF23: 0 | CG23: 0 | CH23: 0 | CI23: 0 | CJ23: 0 | CK23: 0 | CL23: 0 | CM23: 0 | CN23: 0 | CO23: 0 | CP23: =SUM(CD23:CO23) -> 0
A24: TRABALHISTA - C&V | B24: TRABALHISTA - C&V | C24: 1120 | D24: 0 | E24: 0 | F24: 0 | G24: 0 | H24: 0 | I24: 0 | J24: 0 | K24: 0 | L24: 0 | M24: 0 | N24: 0 | O24: 0 | P24: =SUM(D24:O24) -> 0 | Q24: 0 | R24: 0 | S24: 0 | T24: 0 | U24: 0 | V24: 0 | W24: 0 | X24: 0 | Y24: 0 | Z24: 0 | AA24: 0 | AB24: 0 | AC24: =SUM(Q24:AB24) -> 0 | AD24: 0 | AE24: 0 | AF24: 0 | AG24: 0 | AH24: 0 | AI24: 0 | AJ24: 0 | AK24: 0 | AL24: 0 | AM24: 0 | AN24: 0 | AO24: 0 | AP24: =SUM(AD24:AO24) -> 0 | AQ24: 0 | AR24: 0 | AS24: 0 | AT24: 0 | AU24: 0 | AV24: 0 | AW24: 0 | AX24: 0 | AY24: 0 | AZ24: 0 | BA24: 0 | BB24: 0 | BC24: =SUM(AQ24:BB24) -> 0 | BD24: 0 | BE24: 0 | BF24: 0 | BG24: 0 | BH24: 0 | BI24: 0 | BJ24: 0 | BK24: 0 | BL24: 0 | BM24: 0 | BN24: 0 | BO24: 0 | BP24: =SUM(BD24:BO24) -> 0 | BQ24: 0 | BR24: 0 | BS24: 0 | BT24: 0 | BU24: 0 | BV24: 0 | BW24: 0 | BX24: 0 | BY24: 0 | BZ24: 0 | CA24: 0 | CB24: 0 | CC24: =SUM(BQ24:CB24) -> 0 | CD24: 0 | CE24: 0 | CF24: 0 | CG24: 0 | CH24: 0 | CI24: 0 | CJ24: 0 | CK24: 0 | CL24: 0 | CM24: 0 | CN24: 0 | CO24: 0 | CP24: =SUM(CD24:CO24) -> 0
A25: ENEL | B25: ENEL | C25: 0 | D25: 0 | E25: 0 | F25: 0 | G25: 0 | H25: 0 | I25: 0 | J25: 0 | K25: 0 | L25: 0 | M25: 0 | N25: 0 | O25: 0 | P25: =SUM(D25:O25) -> 0 | Q25: 0 | R25: 0 | S25: 0 | T25: 0 | U25: 0 | V25: 0 | W25: 0 | X25: 0 | Y25: 0 | Z25: 0 | AA25: 0 | AB25: 0 | AC25: =SUM(Q25:AB25) -> 0 | AD25: 1670 | AE25: 0 | AF25: 0 | AG25: 0 | AH25: 0 | AI25: 0 | AJ25: 0 | AK25: 0 | AL25: 0 | AM25: 0 | AN25: 0 | AO25: 0 | AP25: =SUM(AD25:AO25) -> 1670 | AQ25: 0 | AR25: 0 | AS25: 0 | AT25: 0 | AU25: 0 | AV25: 0 | AW25: 0 | AX25: 0 | AY25: 0 | AZ25: 0 | BA25: 0 | BB25: 0 | BC25: =SUM(AQ25:BB25) -> 0 | BD25: 0 | BE25: 0 | BF25: 0 | BG25: 0 | BH25: 0 | BI25: 0 | BJ25: 0 | BK25: 0 | BL25: 0 | BM25: 0 | BN25: 0 | BO25: 0 | BP25: =SUM(BD25:BO25) -> 0 | BQ25: 0 | BR25: 4000 | BS25: -444 | BT25: -444 | BU25: -444 | BV25: -444 | BW25: -444 | BX25: -444 | BY25: -444 | BZ25: -444 | CA25: 0 | CB25: 0 | CC25: =SUM(BQ25:CB25) -> 448 | CD25: =VLOOKUP("Condenação",[2]Enel!$A$12:$CH$54,CD46,0)+VLOOKUP("Penalidades/Irregularidades",[2]Enel!$A$12:$CH$54,CD46,0) -> 0 | CE25: =VLOOKUP("Condenação",[2]Enel!$A$12:$CH$54,CE46,0)+VLOOKUP("Penalidades/Irregularidades",[2]Enel!$A$12:$CH$54,CE46,0) -> 0 | CF25: =VLOOKUP("Condenação",[2]Enel!$A$12:$CH$54,CF46,0)+VLOOKUP("Penalidades/Irregularidades",[2]Enel!$A$12:$CH$54,CF46,0) -> 0 | CG25: =VLOOKUP("Condenação",[2]Enel!$A$12:$CH$54,CG46,0)+VLOOKUP("Penalidades/Irregularidades",[2]Enel!$A$12:$CH$54,CG46,0) -> 0 | CH25: =VLOOKUP("Condenação",[2]Enel!$A$12:$CH$54,CH46,0)+VLOOKUP("Penalidades/Irregularidades",[2]Enel!$A$12:$CH$54,CH46,0) -> 0 | CI25: =VLOOKUP("Condenação",[2]Enel!$A$12:$CH$54,CI46,0)+VLOOKUP("Penalidades/Irregularidades",[2]Enel!$A$12:$CH$54,CI46,0) -> 0 | CJ25: =VLOOKUP("Condenação",[2]Enel!$A$12:$CH$54,CJ46,0)+VLOOKUP("Penalidades/Irregularidades",[2]Enel!$A$12:$CH$54,CJ46,0) -> 0 | CK25: =VLOOKUP("Condenação",[2]Enel!$A$12:$CH$54,CK46,0)+VLOOKUP("Penalidades/Irregularidades",[2]Enel!$A$12:$CH$54,CK46,0) -> 0 | ... CO25: =VLOOKUP("Condenação",[2]Enel!$A$12:$CH$54,CO46,0)+VLOOKUP("Penalidades/Irregularidades",[2]Enel!$A$12:$CH$54,CO46,0) -> 0 | CP25: =SUM(CD25:CO25) -> 0
A26: ITAÚ | B26: ITAÚ | C26: 0 | D26: 0 | E26: 0 | F26: 0 | G26: 0 | H26: 0 | I26: 0 | J26: 0 | K26: 0 | L26: 0 | M26: 0 | N26: 0 | O26: 0 | P26: =SUM(D26:O26) -> 0 | Q26: 0 | R26: 0 | S26: 0 | T26: 0 | U26: 0 | V26: 0 | W26: 0 | X26: 0 | Y26: 0 | Z26: 0 | AA26: 0 | AB26: 0 | AC26: =SUM(Q26:AB26) -> 0 | AD26: 0 | AE26: 0 | AF26: 0 | AG26: 0 | AH26: 9993.12 | AI26: 0 | AJ26: 0 | AK26: 0 | AL26: 0 | AM26: 0 | AN26: 12823.1 | AO26: 0 | AP26: =SUM(AD26:AO26) -> 22816.22 | AQ26: 0 | AR26: 0 | AS26: 0 | AT26: 0 | AU26: 0 | AV26: 0 | AW26: 0 | AX26: 0 | AY26: 0 | AZ26: 0 | BA26: 0 | BB26: 0 | BC26: =SUM(AQ26:BB26) -> 0 | BD26: 0 | BE26: 0 | BF26: 0 | BG26: 0 | BH26: 0 | BI26: 0 | BJ26: 0 | BK26: 0 | BL26: 0 | BM26: 0 | BN26: 0 | BO26: 0 | BP26: =SUM(BD26:BO26) -> 0 | BQ26: 675.71 | BR26: 222.52 | BS26: 0 | BT26: 0 | BU26: 0 | BV26: 0 | BW26: 82.59 | BX26: 548.64 | BY26: 0 | BZ26: 0 | CA26: 0 | CB26: 0 | CC26: =SUM(BQ26:CB26) -> 1529.46 | CD26: =VLOOKUP("Condenação",[2]Itaú!$A$11:$CH$49,CD46,0)+VLOOKUP("Penalidades/Irregularidades",[2]Itaú!$A$11:$CH$49,CD46,0)+VLOOKUP("Condenação",[2]Itaú!$A$65:$CH$101,CD46,0)+VLOOKUP("Penalidades/Irregularidades",[2]Itaú!$A$65:$CH$101,CD46,0)+VLOOKUP("Condenação",[2]Itaú!$A$117:$CH$153,CD46,0)+VLOOKUP("Penalidades/Irregularidades",[2]Itaú!$A$117:$CH$153,CD46,0) -> 0 | CE26: =VLOOKUP("Condenação",[2]Itaú!$A$11:$CH$49,CE46,0)+VLOOKUP("Penalidades/Irregularidades",[2]Itaú!$A$11:$CH$49,CE46,0)+VLOOKUP("Condenação",[2]Itaú!$A$65:$CH$101,CE46,0)+VLOOKUP("Penalidades/Irregularidades",[2]Itaú!$A$65:$CH$101,CE46,0)+VLOOKUP("Condenação",[2]Itaú!$A$117:$CH$153,CE46,0)+VLOOKUP("Penalidades/Irregularidades",[2]Itaú!$A$117:$CH$153,CE46,0) -> 0 | CF26: =VLOOKUP("Condenação",[2]Itaú!$A$11:$CH$49,CF46,0)+VLOOKUP("Penalidades/Irregularidades",[2]Itaú!$A$11:$CH$49,CF46,0)+VLOOKUP("Condenação",[2]Itaú!$A$65:$CH$101,CF46,0)+VLOOKUP("Penalidades/Irregularidades",[2]Itaú!$A$65:$CH$101,CF46,0)+VLOOKUP("Condenação",[2]Itaú!$A$117:$CH$153,CF46,0)+VLOOKUP("Penalidades/Irregularidades",[2]Itaú!$A$117:$CH$153,CF46,0) -> 0 | CG26: =VLOOKUP("Condenação",[2]Itaú!$A$11:$CH$49,CG46,0)+VLOOKUP("Penalidades/Irregularidades",[2]Itaú!$A$11:$CH$49,CG46,0)+VLOOKUP("Condenação",[2]Itaú!$A$65:$CH$101,CG46,0)+VLOOKUP("Penalidades/Irregularidades",[2]Itaú!$A$65:$CH$101,CG46,0)+VLOOKUP("Condenação",[2]Itaú!$A$117:$CH$153,CG46,0)+VLOOKUP("Penalidades/Irregularidades",[2]Itaú!$A$117:$CH$153,CG46,0) -> 0 | CH26: =VLOOKUP("Condenação",[2]Itaú!$A$11:$CH$49,CH46,0)+VLOOKUP("Penalidades/Irregularidades",[2]Itaú!$A$11:$CH$49,CH46,0)+VLOOKUP("Condenação",[2]Itaú!$A$65:$CH$101,CH46,0)+VLOOKUP("Penalidades/Irregularidades",[2]Itaú!$A$65:$CH$101,CH46,0)+VLOOKUP("Condenação",[2]Itaú!$A$117:$CH$153,CH46,0)+VLOOKUP("Penalidades/Irregularidades",[2]Itaú!$A$117:$CH$153,CH46,0) -> 0 | CI26: =VLOOKUP("Condenação",[2]Itaú!$A$11:$CH$49,CI46,0)+VLOOKUP("Penalidades/Irregularidades",[2]Itaú!$A$11:$CH$49,CI46,0)+VLOOKUP("Condenação",[2]Itaú!$A$65:$CH$101,CI46,0)+VLOOKUP("Penalidades/Irregularidades",[2]Itaú!$A$65:$CH$101,CI46,0)+VLOOKUP("Condenação",[2]Itaú!$A$117:$CH$153,CI46,0)+VLOOKUP("Penalidades/Irregularidades",[2]Itaú!$A$117:$CH$153,CI46,0) -> 0 | CJ26: =VLOOKUP("Condenação",[2]Itaú!$A$11:$CH$49,CJ46,0)+VLOOKUP("Penalidades/Irregularidades",[2]Itaú!$A$11:$CH$49,CJ46,0)+VLOOKUP("Condenação",[2]Itaú!$A$65:$CH$101,CJ46,0)+VLOOKUP("Penalidades/Irregularidades",[2]Itaú!$A$65:$CH$101,CJ46,0)+VLOOKUP("Condenação",[2]Itaú!$A$117:$CH$153,CJ46,0)+VLOOKUP("Penalidades/Irregularidades",[2]Itaú!$A$117:$CH$153,CJ46,0) -> 0 | CK26: =VLOOKUP("Condenação",[2]Itaú!$A$11:$CH$49,CK46,0)+VLOOKUP("Penalidades/Irregularidades",[2]Itaú!$A$11:$CH$49,CK46,0)+VLOOKUP("Condenação",[2]Itaú!$A$65:$CH$101,CK46,0)+VLOOKUP("Penalidades/Irregularidades",[2]Itaú!$A$65:$CH$101,CK46,0)+VLOOKUP("Condenação",[2]Itaú!$A$117:$CH$153,CK46,0)+VLOOKUP("Penalidades/Irregularidades",[2]Itaú!$A$117:$CH$153,CK46,0) -> 0 | ... CO26: =VLOOKUP("Condenação",[2]Itaú!$A$11:$CH$49,CO46,0)+VLOOKUP("Penalidades/Irregularidades",[2]Itaú!$A$11:$CH$49,CO46,0)+VLOOKUP("Condenação",[2]Itaú!$A$65:$CH$101,CO46,0)+VLOOKUP("Penalidades/Irregularidades",[2]Itaú!$A$65:$CH$101,CO46,0)+VLOOKUP("Condenação",[2]Itaú!$A$117:$CH$153,CO46,0)+VLOOKUP("Penalidades/Irregularidades",[2]Itaú!$A$117:$CH$153,CO46,0) -> 0 | CP26: =SUM(CD26:CO26) -> 0
A27: MADEIRA MADEIRA | B27: MADEIRA MADEIRA | C27: 0 | D27: 0 | E27: 0 | F27: 0 | G27: 0 | H27: 0 | I27: 0 | J27: 0 | K27: 0 | L27: 0 | M27: 0 | N27: 0 | O27: 0 | P27: =SUM(D27:O27) -> 0 | Q27: 0 | R27: 0 | S27: 0 | T27: 0 | U27: 0 | V27: 0 | W27: 0 | X27: 0 | Y27: 0 | Z27: 0 | AA27: 0 | AB27: 0 | AC27: =SUM(Q27:AB27) -> 0 | AD27: 0 | AE27: 0 | AF27: 0 | AG27: 0 | AH27: 0 | AI27: 0 | AJ27: 0 | AK27: 0 | AL27: 0 | AM27: 0 | AN27: 0 | AO27: 0 | AP27: =SUM(AD27:AO27) -> 0 | AQ27: 0 | AR27: 0 | AS27: 0 | AT27: 0 | AU27: 0 | AV27: 0 | AW27: 0 | AX27: 0 | AY27: 0 | AZ27: 0 | BA27: 0 | BB27: 0 | BC27: =SUM(AQ27:BB27) -> 0 | BD27: 0 | BE27: 0 | BF27: 0 | BG27: 0 | BH27: 0 | BI27: 0 | BJ27: 0 | BK27: 0 | BL27: 0 | BM27: 21281.66 | BN27: 0 | BO27: 0 | BP27: =SUM(BD27:BO27) -> 21281.66 | BQ27: 0 | BR27: 0 | BS27: 0 | BT27: 0 | BU27: 0 | BV27: 0 | BW27: 0 | BX27: 0 | BY27: 0 | BZ27: 0 | CA27: 0 | CB27: 0 | CC27: =SUM(BQ27:CB27) -> 0 | CD27: =VLOOKUP("Condenação",[2]MadeiraMadeira!$A$11:$CH$80,CD46,0)+VLOOKUP("Penalidades/Irregularidades",[2]MadeiraMadeira!$A$11:$CH$80,CD46,0) -> 0 | CE27: =VLOOKUP("Condenação",[2]MadeiraMadeira!$A$11:$CH$80,CE46,0)+VLOOKUP("Penalidades/Irregularidades",[2]MadeiraMadeira!$A$11:$CH$80,CE46,0) -> 0 | CF27: =VLOOKUP("Condenação",[2]MadeiraMadeira!$A$11:$CH$80,CF46,0)+VLOOKUP("Penalidades/Irregularidades",[2]MadeiraMadeira!$A$11:$CH$80,CF46,0) -> 0 | CG27: =VLOOKUP("Condenação",[2]MadeiraMadeira!$A$11:$CH$80,CG46,0)+VLOOKUP("Penalidades/Irregularidades",[2]MadeiraMadeira!$A$11:$CH$80,CG46,0) -> 0 | CH27: =VLOOKUP("Condenação",[2]MadeiraMadeira!$A$11:$CH$80,CH46,0)+VLOOKUP("Penalidades/Irregularidades",[2]MadeiraMadeira!$A$11:$CH$80,CH46,0) -> 0 | CI27: =VLOOKUP("Condenação",[2]MadeiraMadeira!$A$11:$CH$80,CI46,0)+VLOOKUP("Penalidades/Irregularidades",[2]MadeiraMadeira!$A$11:$CH$80,CI46,0) -> 0 | CJ27: =VLOOKUP("Condenação",[2]MadeiraMadeira!$A$11:$CH$80,CJ46,0)+VLOOKUP("Penalidades/Irregularidades",[2]MadeiraMadeira!$A$11:$CH$80,CJ46,0) -> 0 | CK27: =VLOOKUP("Condenação",[2]MadeiraMadeira!$A$11:$CH$80,CK46,0)+VLOOKUP("Penalidades/Irregularidades",[2]MadeiraMadeira!$A$11:$CH$80,CK46,0) -> 0 | ... CO27: =VLOOKUP("Condenação",[2]MadeiraMadeira!$A$11:$CH$80,CO46,0)+VLOOKUP("Penalidades/Irregularidades",[2]MadeiraMadeira!$A$11:$CH$80,CO46,0) -> 0 | CP27: =SUM(CD27:CO27) -> 0
A28: NATURGY | B28: NATURGY | C28: 0 | D28: 0 | E28: 0 | F28: 0 | G28: 0 | H28: 0 | I28: 0 | J28: 0 | K28: 0 | L28: 0 | M28: 0 | N28: 0 | O28: 0 | P28: =SUM(D28:O28) -> 0 | Q28: 0 | R28: 0 | S28: 0 | T28: 0 | U28: 0 | V28: 0 | W28: 0 | X28: 0 | Y28: 0 | Z28: 0 | AA28: 0 | AB28: 0 | AC28: =SUM(Q28:AB28) -> 0 | AD28: 0 | AE28: 0 | AF28: 0 | AG28: 0 | AH28: 0 | AI28: 0 | AJ28: 0 | AK28: 0 | AL28: 0 | AM28: 0 | AN28: 0 | AO28: 0 | AP28: =SUM(AD28:AO28) -> 0 | AQ28: 0 | AR28: 0 | AS28: 0 | AT28: 0 | AU28: 0 | AV28: 0 | AW28: 0 | AX28: 0 | AY28: 0 | AZ28: 0 | BA28: 0 | BB28: 0 | BC28: =SUM(AQ28:BB28) -> 0 | BD28: 0 | BE28: 0 | BF28: 0 | BG28: 0 | BH28: 0 | BI28: 0 | BJ28: 0 | BK28: 0 | BL28: 0 | BM28: 0 | BN28: 0 | BO28: 0 | BP28: =SUM(BD28:BO28) -> 0 | BQ28: 0 | BR28: 0 | BS28: 0 | BT28: 0 | BU28: 0 | BV28: 0 | BW28: 0 | BX28: 0 | BY28: 0 | BZ28: 0 | CA28: 0 | CB28: 0 | CC28: =SUM(BQ28:CB28) -> 0 | CD28: =VLOOKUP("Condenação",[2]Naturgy!$A$11:$CH$80,CD46,0)+VLOOKUP("Penalidades/Irregularidades",[2]Naturgy!$A$11:$CH$80,CD46,0) -> 0 | CE28: =VLOOKUP("Condenação",[2]Naturgy!$A$11:$CH$80,CE46,0)+VLOOKUP("Penalidades/Irregularidades",[2]Naturgy!$A$11:$CH$80,CE46,0) -> 0 | CF28: =VLOOKUP("Condenação",[2]Naturgy!$A$11:$CH$80,CF46,0)+VLOOKUP("Penalidades/Irregularidades",[2]Naturgy!$A$11:$CH$80,CF46,0) -> 0 | CG28: =VLOOKUP("Condenação",[2]Naturgy!$A$11:$CH$80,CG46,0)+VLOOKUP("Penalidades/Irregularidades",[2]Naturgy!$A$11:$CH$80,CG46,0) -> 0 | CH28: =VLOOKUP("Condenação",[2]Naturgy!$A$11:$CH$80,CH46,0)+VLOOKUP("Penalidades/Irregularidades",[2]Naturgy!$A$11:$CH$80,CH46,0) -> 0 | CI28: =VLOOKUP("Condenação",[2]Naturgy!$A$11:$CH$80,CI46,0)+VLOOKUP("Penalidades/Irregularidades",[2]Naturgy!$A$11:$CH$80,CI46,0) -> 0 | CJ28: =VLOOKUP("Condenação",[2]Naturgy!$A$11:$CH$80,CJ46,0)+VLOOKUP("Penalidades/Irregularidades",[2]Naturgy!$A$11:$CH$80,CJ46,0) -> 0 | CK28: =VLOOKUP("Condenação",[2]Naturgy!$A$11:$CH$80,CK46,0)+VLOOKUP("Penalidades/Irregularidades",[2]Naturgy!$A$11:$CH$80,CK46,0) -> 0 | ... CO28: =VLOOKUP("Condenação",[2]Naturgy!$A$11:$CH$80,CO46,0)+VLOOKUP("Penalidades/Irregularidades",[2]Naturgy!$A$11:$CH$80,CO46,0) -> 0 | CP28: =SUM(CD28:CO28) -> 0
A29: LEADER | B29: LEADER | C29: 0 | D29: 0 | E29: 0 | F29: 0 | G29: 0 | H29: 0 | I29: 0 | J29: 0 | K29: 0 | L29: 0 | M29: 0 | N29: 0 | O29: 0 | P29: =SUM(D29:O29) -> 0 | Q29: 0 | R29: 0 | S29: 0 | T29: 0 | U29: 0 | V29: 0 | W29: 0 | X29: 0 | Y29: 0 | Z29: 0 | AA29: 0 | AB29: 0 | AC29: =SUM(Q29:AB29) -> 0 | AD29: 0 | AE29: 0 | AF29: 0 | AG29: 0 | AH29: 0 | AI29: 0 | AJ29: 0 | AK29: 0 | AL29: 0 | AM29: 0 | AN29: 0 | AO29: 0 | AP29: =SUM(AD29:AO29) -> 0 | AQ29: 0 | AR29: 0 | AS29: 0 | AT29: 0 | AU29: 0 | AV29: 0 | AW29: 0 | AX29: 0 | AY29: 0 | AZ29: 0 | BA29: 0 | BB29: 0 | BC29: =SUM(AQ29:BB29) -> 0 | BD29: 0 | BE29: 0 | BF29: 0 | BG29: 0 | BH29: 0 | BI29: 0 | BJ29: 0 | BK29: 0 | BL29: 0 | BM29: 0 | BN29: 0 | BO29: 0 | BP29: =SUM(BD29:BO29) -> 0 | BQ29: 0 | BR29: 0 | BS29: 0 | BT29: 0 | BU29: 0 | BV29: 0 | BW29: 0 | BX29: 0 | BY29: 0 | BZ29: 0 | CA29: 0 | CB29: 0 | CC29: =SUM(BQ29:CB29) -> 0 | CD29: 0 | CE29: 0 | CF29: 0 | CG29: 0 | CH29: 0 | CI29: 0 | CJ29: 0 | CK29: 0 | CL29: 0 | CM29: 0 | CN29: 0 | CO29: 0 | CP29: =SUM(CD29:CO29) -> 0
A30: MRS | B30: MRS | C30: 0 | D30: 0 | E30: 0 | F30: 0 | G30: 0 | H30: 0 | I30: 0 | J30: 0 | K30: 0 | L30: 0 | M30: 0 | N30: 0 | O30: 0 | P30: =SUM(D30:O30) -> 0 | Q30: 0 | R30: 0 | S30: 0 | T30: 0 | U30: 0 | V30: 0 | W30: 0 | X30: 0 | Y30: 0 | Z30: 0 | AA30: 0 | AB30: 0 | AC30: =SUM(Q30:AB30) -> 0 | AD30: 0 | AE30: 0 | AF30: 0 | AG30: 0 | AH30: 0 | AI30: 0 | AJ30: 0 | AK30: 0 | AL30: 0 | AM30: 0 | AN30: 0 | AO30: 0 | AP30: =SUM(AD30:AO30) -> 0 | AQ30: 0 | AR30: 0 | AS30: 0 | AT30: 0 | AU30: 0 | AV30: 0 | AW30: 0 | AX30: 0 | AY30: 0 | AZ30: 0 | BA30: 0 | BB30: 0 | BC30: =SUM(AQ30:BB30) -> 0 | BD30: 0 | BE30: 0 | BF30: 0 | BG30: 0 | BH30: 0 | BI30: 0 | BJ30: 0 | BK30: 0 | BL30: 0 | BM30: 0 | BN30: 0 | BO30: 0 | BP30: =SUM(BD30:BO30) -> 0 | BQ30: 0 | BR30: 0 | BS30: 0 | BT30: 0 | BU30: 0 | BV30: 0 | BW30: 0 | BX30: 0 | BY30: 0 | BZ30: 0 | CA30: 0 | CB30: 0 | CC30: =SUM(BQ30:CB30) -> 0 | CD30: =VLOOKUP("Condenação",[2]MRS!$A$11:$CH$80,CD46,0)+VLOOKUP("Penalidades/Irregularidades",[2]MRS!$A$11:$CH$80,CD46,0) -> 0 | CE30: =VLOOKUP("Condenação",[2]MRS!$A$11:$CH$80,CE46,0)+VLOOKUP("Penalidades/Irregularidades",[2]MRS!$A$11:$CH$80,CE46,0) -> 0 | CF30: =VLOOKUP("Condenação",[2]MRS!$A$11:$CH$80,CF46,0)+VLOOKUP("Penalidades/Irregularidades",[2]MRS!$A$11:$CH$80,CF46,0) -> 0 | CG30: =VLOOKUP("Condenação",[2]MRS!$A$11:$CH$80,CG46,0)+VLOOKUP("Penalidades/Irregularidades",[2]MRS!$A$11:$CH$80,CG46,0) -> 0 | CH30: =VLOOKUP("Condenação",[2]MRS!$A$11:$CH$80,CH46,0)+VLOOKUP("Penalidades/Irregularidades",[2]MRS!$A$11:$CH$80,CH46,0) -> 0 | CI30: =VLOOKUP("Condenação",[2]MRS!$A$11:$CH$80,CI46,0)+VLOOKUP("Penalidades/Irregularidades",[2]MRS!$A$11:$CH$80,CI46,0) -> 0 | CJ30: =VLOOKUP("Condenação",[2]MRS!$A$11:$CH$80,CJ46,0)+VLOOKUP("Penalidades/Irregularidades",[2]MRS!$A$11:$CH$80,CJ46,0) -> 0 | CK30: =VLOOKUP("Condenação",[2]MRS!$A$11:$CH$80,CK46,0)+VLOOKUP("Penalidades/Irregularidades",[2]MRS!$A$11:$CH$80,CK46,0) -> 0 | ... CO30: =VLOOKUP("Condenação",[2]MRS!$A$11:$CH$80,CO46,0)+VLOOKUP("Penalidades/Irregularidades",[2]MRS!$A$11:$CH$80,CO46,0) -> 0 | CP30: =SUM(CD30:CO30) -> 0
A31: CAIXA CAPITALIZAÇÃO | B31: CAIXA CAPITALIZAÇÃO | C31: 0 | D31: 0 | E31: 0 | F31: 0 | G31: 0 | H31: 0 | I31: 0 | J31: 0 | K31: 0 | L31: 0 | M31: 0 | N31: 0 | O31: 0 | P31: =SUM(D31:O31) -> 0 | Q31: 0 | R31: 0 | S31: 0 | T31: 0 | U31: 0 | V31: 0 | W31: 0 | X31: 0 | Y31: 0 | Z31: 0 | AA31: 0 | AB31: 0 | AC31: =SUM(Q31:AB31) -> 0 | AD31: 0 | AE31: 0 | AF31: 0 | AG31: 0 | AH31: 0 | AI31: 0 | AJ31: 0 | AK31: 0 | AL31: 0 | AM31: 0 | AN31: 0 | AO31: 0 | AP31: =SUM(AD31:AO31) -> 0 | AQ31: 0 | AR31: 0 | AS31: 0 | AT31: 0 | AU31: 0 | AV31: 0 | AW31: 0 | AX31: 0 | AY31: 0 | AZ31: 0 | BA31: 0 | BB31: 0 | BC31: =SUM(AQ31:BB31) -> 0 | BD31: 0 | BE31: 0 | BF31: 0 | BG31: 0 | BH31: 0 | BI31: 0 | BJ31: 0 | BK31: 0 | BL31: 0 | BM31: 0 | BN31: 0 | BO31: 0 | BP31: =SUM(BD31:BO31) -> 0 | BQ31: 0 | BR31: 0 | BS31: 0 | BT31: 0 | BU31: 0 | BV31: 0 | BW31: 0 | BX31: 0 | BY31: 0 | BZ31: 0 | CA31: 0 | CB31: 0 | CC31: =SUM(BQ31:CB31) -> 0 | CD31: =VLOOKUP("Condenação",[2]XS4!$A$11:$CH$80,CD46,0)+VLOOKUP("Penalidades/Irregularidades",[2]XS4!$A$11:$CH$80,CD46,0) -> 0 | CE31: =VLOOKUP("Condenação",[2]XS4!$A$11:$CH$80,CE46,0)+VLOOKUP("Penalidades/Irregularidades",[2]XS4!$A$11:$CH$80,CE46,0) -> 0 | CF31: =VLOOKUP("Condenação",[2]XS4!$A$11:$CH$80,CF46,0)+VLOOKUP("Penalidades/Irregularidades",[2]XS4!$A$11:$CH$80,CF46,0) -> 0 | CG31: =VLOOKUP("Condenação",[2]XS4!$A$11:$CH$80,CG46,0)+VLOOKUP("Penalidades/Irregularidades",[2]XS4!$A$11:$CH$80,CG46,0) -> 0 | CH31: =VLOOKUP("Condenação",[2]XS4!$A$11:$CH$80,CH46,0)+VLOOKUP("Penalidades/Irregularidades",[2]XS4!$A$11:$CH$80,CH46,0) -> 0 | CI31: =VLOOKUP("Condenação",[2]XS4!$A$11:$CH$80,CI46,0)+VLOOKUP("Penalidades/Irregularidades",[2]XS4!$A$11:$CH$80,CI46,0) -> 0 | CJ31: =VLOOKUP("Condenação",[2]XS4!$A$11:$CH$80,CJ46,0)+VLOOKUP("Penalidades/Irregularidades",[2]XS4!$A$11:$CH$80,CJ46,0) -> 0 | CK31: =VLOOKUP("Condenação",[2]XS4!$A$11:$CH$80,CK46,0)+VLOOKUP("Penalidades/Irregularidades",[2]XS4!$A$11:$CH$80,CK46,0) -> 0 | ... CO31: =VLOOKUP("Condenação",[2]XS4!$A$11:$CH$80,CO46,0)+VLOOKUP("Penalidades/Irregularidades",[2]XS4!$A$11:$CH$80,CO46,0) -> 0 | CP31: =SUM(CD31:CO31) -> 0
A32: BANCO PAN | B32: BANCO PAN | C32: 0 | D32: 0 | E32: 0 | F32: 0 | G32: 0 | H32: 0 | I32: 0 | J32: 0 | K32: 0 | L32: 0 | M32: 0 | N32: 0 | O32: 0 | P32: =SUM(D32:O32) -> 0 | Q32: 0 | R32: 0 | S32: 0 | T32: 0 | U32: 0 | V32: 0 | W32: 0 | X32: 0 | Y32: 0 | Z32: 0 | AA32: 0 | AB32: 0 | AC32: =SUM(Q32:AB32) -> 0 | AD32: 0 | AE32: 0 | AF32: 0 | AG32: 0 | AH32: 0 | AI32: 0 | AJ32: 0 | AK32: 0 | AL32: 0 | AM32: 0 | AN32: 0 | AO32: 0 | AP32: =SUM(AD32:AO32) -> 0 | AQ32: 0 | AR32: 0 | AS32: 0 | AT32: 0 | AU32: 0 | AV32: 0 | AW32: 0 | AX32: 0 | AY32: 0 | AZ32: 0 | BA32: 0 | BB32: 0 | BC32: =SUM(AQ32:BB32) -> 0 | BD32: 0 | BE32: 0 | BF32: 0 | BG32: 0 | BH32: 0 | BI32: 0 | BJ32: 0 | BK32: 0 | BL32: 0 | BM32: 0 | BN32: 0 | BO32: 0 | BP32: =SUM(BD32:BO32) -> 0 | BQ32: 0 | BR32: 0 | BS32: 0 | BT32: 0 | BU32: 0 | BV32: 0 | BW32: 0 | BX32: 0 | BY32: 0 | BZ32: 0 | CA32: 0 | CB32: 0 | CC32: =SUM(BQ32:CB32) -> 0 | CD32: =VLOOKUP("Condenação",'[2]Banco PAN'!$A$11:$CH$80,CD46,0)+VLOOKUP("Penalidades/Irregularidades",'[2]Banco PAN'!$A$11:$CH$80,CD46,0) -> 0 | CE32: =VLOOKUP("Condenação",'[2]Banco PAN'!$A$11:$CH$80,CE46,0)+VLOOKUP("Penalidades/Irregularidades",'[2]Banco PAN'!$A$11:$CH$80,CE46,0) -> 0 | CF32: =VLOOKUP("Condenação",'[2]Banco PAN'!$A$11:$CH$80,CF46,0)+VLOOKUP("Penalidades/Irregularidades",'[2]Banco PAN'!$A$11:$CH$80,CF46,0) -> 0 | CG32: =VLOOKUP("Condenação",'[2]Banco PAN'!$A$11:$CH$80,CG46,0)+VLOOKUP("Penalidades/Irregularidades",'[2]Banco PAN'!$A$11:$CH$80,CG46,0) -> 0 | CH32: =VLOOKUP("Condenação",'[2]Banco PAN'!$A$11:$CH$80,CH46,0)+VLOOKUP("Penalidades/Irregularidades",'[2]Banco PAN'!$A$11:$CH$80,CH46,0) -> 0 | CI32: =VLOOKUP("Condenação",'[2]Banco PAN'!$A$11:$CH$80,CI46,0)+VLOOKUP("Penalidades/Irregularidades",'[2]Banco PAN'!$A$11:$CH$80,CI46,0) -> 0 | CJ32: =VLOOKUP("Condenação",'[2]Banco PAN'!$A$11:$CH$80,CJ46,0)+VLOOKUP("Penalidades/Irregularidades",'[2]Banco PAN'!$A$11:$CH$80,CJ46,0) -> 0 | CK32: =VLOOKUP("Condenação",'[2]Banco PAN'!$A$11:$CH$80,CK46,0)+VLOOKUP("Penalidades/Irregularidades",'[2]Banco PAN'!$A$11:$CH$80,CK46,0) -> 0 | ... CO32: =VLOOKUP("Condenação",'[2]Banco PAN'!$A$11:$CH$80,CO46,0)+VLOOKUP("Penalidades/Irregularidades",'[2]Banco PAN'!$A$11:$CH$80,CO46,0) -> 0 | CP32: =SUM(CD32:CO32) -> 0
A33: NIO | B33: NIO | C33: 0 | D33: 0 | E33: 0 | F33: 0 | G33: 0 | H33: 0 | I33: 0 | J33: 0 | K33: 0 | L33: 0 | M33: 0 | N33: 0 | O33: 0 | P33: =SUM(D33:O33) -> 0 | Q33: 0 | R33: 0 | S33: 0 | T33: 0 | U33: 0 | V33: 0 | W33: 0 | X33: 0 | Y33: 0 | Z33: 0 | AA33: 0 | AB33: 0 | AC33: =SUM(Q33:AB33) -> 0 | AD33: 0 | AE33: 0 | AF33: 0 | AG33: 0 | AH33: 0 | AI33: 0 | AJ33: 0 | AK33: 0 | AL33: 0 | AM33: 0 | AN33: 0 | AO33: 0 | AP33: =SUM(AD33:AO33) -> 0 | AQ33: 0 | AR33: 0 | AS33: 0 | AT33: 0 | AU33: 0 | AV33: 0 | AW33: 0 | AX33: 0 | AY33: 0 | AZ33: 0 | BA33: 0 | BB33: 0 | BC33: =SUM(AQ33:BB33) -> 0 | BD33: 0 | BE33: 0 | BF33: 0 | BG33: 0 | BH33: 0 | BI33: 0 | BJ33: 0 | BK33: 0 | BL33: 0 | BM33: 0 | BN33: 0 | BO33: 0 | BP33: =SUM(BD33:BO33) -> 0 | BQ33: 0 | BR33: 0 | BS33: 0 | BT33: 0 | BU33: 0 | BV33: 0 | BW33: 0 | BX33: 0 | BY33: 0 | BZ33: 0 | CA33: 0 | CB33: 0 | CC33: =SUM(BQ33:CB33) -> 0 | CD33: =VLOOKUP("Condenação",[2]NIO!$A$11:$CH$80,CD46,0)+VLOOKUP("Penalidades/Irregularidades",[2]NIO!$A$11:$CH$80,CD46,0) -> 0 | CE33: =VLOOKUP("Condenação",[2]NIO!$A$11:$CH$80,CE46,0)+VLOOKUP("Penalidades/Irregularidades",[2]NIO!$A$11:$CH$80,CE46,0) -> 0 | CF33: =VLOOKUP("Condenação",[2]NIO!$A$11:$CH$80,CF46,0)+VLOOKUP("Penalidades/Irregularidades",[2]NIO!$A$11:$CH$80,CF46,0) -> 0 | CG33: =VLOOKUP("Condenação",[2]NIO!$A$11:$CH$80,CG46,0)+VLOOKUP("Penalidades/Irregularidades",[2]NIO!$A$11:$CH$80,CG46,0) -> 0 | CH33: =VLOOKUP("Condenação",[2]NIO!$A$11:$CH$80,CH46,0)+VLOOKUP("Penalidades/Irregularidades",[2]NIO!$A$11:$CH$80,CH46,0) -> 0 | CI33: =VLOOKUP("Condenação",[2]NIO!$A$11:$CH$80,CI46,0)+VLOOKUP("Penalidades/Irregularidades",[2]NIO!$A$11:$CH$80,CI46,0) -> 0 | CJ33: =VLOOKUP("Condenação",[2]NIO!$A$11:$CH$80,CJ46,0)+VLOOKUP("Penalidades/Irregularidades",[2]NIO!$A$11:$CH$80,CJ46,0) -> 0 | CK33: =VLOOKUP("Condenação",[2]NIO!$A$11:$CH$80,CK46,0)+VLOOKUP("Penalidades/Irregularidades",[2]NIO!$A$11:$CH$80,CK46,0) -> 0 | ... CO33: =VLOOKUP("Condenação",[2]NIO!$A$11:$CH$80,CO46,0)+VLOOKUP("Penalidades/Irregularidades",[2]NIO!$A$11:$CH$80,CO46,0) -> 0 | CP33: =SUM(CD33:CO33) -> 0
A34: VIVO | B34: VIVO | C34: 0 | D34: 0 | E34: 0 | F34: 0 | G34: 0 | H34: 0 | I34: 0 | J34: 0 | K34: 0 | L34: 0 | M34: 0 | N34: 0 | O34: 0 | P34: =SUM(D34:O34) -> 0 | Q34: 0 | R34: 0 | S34: 0 | T34: 0 | U34: 0 | V34: 0 | W34: 0 | X34: 0 | Y34: 0 | Z34: 0 | AA34: 0 | AB34: 0 | AC34: =SUM(Q34:AB34) -> 0 | AD34: 0 | AE34: 0 | AF34: 0 | AG34: 0 | AH34: 0 | AI34: 0 | AJ34: 0 | AK34: 0 | AL34: 0 | AM34: 0 | AN34: 0 | AO34: 0 | AP34: =SUM(AD34:AO34) -> 0 | AQ34: 0 | AR34: 0 | AS34: 0 | AT34: 0 | AU34: 0 | AV34: 0 | AW34: 0 | AX34: 0 | AY34: 1313.56 | AZ34: 494.38 | BA34: 0 | BB34: 10536.11 | BC34: =SUM(AQ34:BB34) -> 12344.05 | BD34: 535.18 | BE34: 0 | BF34: 0 | BG34: 0 | BH34: 3944.87 | BI34: 0 | BJ34: 0 | BK34: 0 | BL34: 390 | BM34: 0 | BN34: 480 | BO34: 0 | BP34: =SUM(BD34:BO34) -> 5350.05 | BQ34: 387.8 | BR34: 1841.91 | BS34: 1700 | BT34: 5767.92 | BU34: 0 | BV34: 0 | BW34: 220 | BX34: 400 | BY34: 0 | BZ34: 0 | CA34: 0 | CB34: 2066.51 | CC34: =SUM(BQ34:CB34) -> 12384.14 | CD34: =VLOOKUP("Condenação",[2]Vivo!$A$11:$CH$80,CD46,0)+VLOOKUP("Penalidades/Irregularidades",[2]Vivo!$A$11:$CH$80,CD46,0) -> 0 | CE34: =VLOOKUP("Condenação",[2]Vivo!$A$11:$CH$80,CE46,0)+VLOOKUP("Penalidades/Irregularidades",[2]Vivo!$A$11:$CH$80,CE46,0) -> 1530 | CF34: =VLOOKUP("Condenação",[2]Vivo!$A$11:$CH$80,CF46,0)+VLOOKUP("Penalidades/Irregularidades",[2]Vivo!$A$11:$CH$80,CF46,0) -> 0 | CG34: =VLOOKUP("Condenação",[2]Vivo!$A$11:$CH$80,CG46,0)+VLOOKUP("Penalidades/Irregularidades",[2]Vivo!$A$11:$CH$80,CG46,0) -> 0 | CH34: =VLOOKUP("Condenação",[2]Vivo!$A$11:$CH$80,CH46,0)+VLOOKUP("Penalidades/Irregularidades",[2]Vivo!$A$11:$CH$80,CH46,0) -> 0 | CI34: =VLOOKUP("Condenação",[2]Vivo!$A$11:$CH$80,CI46,0)+VLOOKUP("Penalidades/Irregularidades",[2]Vivo!$A$11:$CH$80,CI46,0) -> 0 | CJ34: =VLOOKUP("Condenação",[2]Vivo!$A$11:$CH$80,CJ46,0)+VLOOKUP("Penalidades/Irregularidades",[2]Vivo!$A$11:$CH$80,CJ46,0) -> 0 | CK34: =VLOOKUP("Condenação",[2]Vivo!$A$11:$CH$80,CK46,0)+VLOOKUP("Penalidades/Irregularidades",[2]Vivo!$A$11:$CH$80,CK46,0) -> 0 | ... CO34: =VLOOKUP("Condenação",[2]Vivo!$A$11:$CH$80,CO46,0)+VLOOKUP("Penalidades/Irregularidades",[2]Vivo!$A$11:$CH$80,CO46,0) -> 0 | CP34: =SUM(CD34:CO34) -> 1530
A35: OUTROS CLIENTES | B35: OUTROS CLIENTES | C35: 0 | D35: 0 | E35: 0 | F35: 0 | G35: 0 | H35: 0 | I35: 0 | J35: 0 | K35: 0 | L35: 0 | M35: 0 | N35: 0 | O35: 0 | P35: 0 | Q35: 0 | R35: 0 | S35: 0 | T35: 0 | U35: 0 | V35: 0 | W35: 0 | X35: 0 | Y35: 0 | Z35: 0 | AA35: 0 | AB35: 0 | AC35: 0 | AD35: 0 | AE35: 0 | AF35: 0 | AG35: 0 | AH35: 0 | AI35: 0 | AJ35: 0 | AK35: 0 | AL35: 0 | AM35: 0 | AN35: 0 | AO35: 0 | AP35: 0 | AQ35: 0 | AR35: 0 | AS35: 0 | AT35: 0 | AU35: 0 | AV35: 0 | AW35: 0 | AX35: 0 | AY35: 0 | AZ35: 0 | BA35: 0 | BB35: 0 | BC35: 0 | BD35: 0 | BE35: 0 | BF35: 0 | BG35: 0 | BH35: 0 | BI35: 0 | BJ35: 0 | BK35: 0 | BL35: 0 | BM35: 0 | BN35: 0 | BO35: 0 | BP35: 0 | BQ35: 0 | BR35: 0 | BS35: 0 | BT35: 0 | BU35: 0 | BV35: 0 | BW35: 0 | BX35: 0 | BY35: 0 | BZ35: 0 | CA35: 0 | CB35: 0 | CC35: =SUM(BQ35:CB35) -> 0 | CD35: =VLOOKUP("Condenação",'[2]Outros Clientes'!$A$11:$CH$51,CD46,0)+VLOOKUP("Penalidades/Irregularidades",'[2]Outros Clientes'!$A$11:$CH$51,CD46,0) -> 0 | CE35: =VLOOKUP("Condenação",'[2]Outros Clientes'!$A$11:$CH$51,CE46,0)+VLOOKUP("Penalidades/Irregularidades",'[2]Outros Clientes'!$A$11:$CH$51,CE46,0) -> 0 | CF35: =VLOOKUP("Condenação",'[2]Outros Clientes'!$A$11:$CH$51,CF46,0)+VLOOKUP("Penalidades/Irregularidades",'[2]Outros Clientes'!$A$11:$CH$51,CF46,0) -> 0 | CG35: =VLOOKUP("Condenação",'[2]Outros Clientes'!$A$11:$CH$51,CG46,0)+VLOOKUP("Penalidades/Irregularidades",'[2]Outros Clientes'!$A$11:$CH$51,CG46,0) -> 0 | CH35: =VLOOKUP("Condenação",'[2]Outros Clientes'!$A$11:$CH$51,CH46,0)+VLOOKUP("Penalidades/Irregularidades",'[2]Outros Clientes'!$A$11:$CH$51,CH46,0) -> 0 | CI35: =VLOOKUP("Condenação",'[2]Outros Clientes'!$A$11:$CH$51,CI46,0)+VLOOKUP("Penalidades/Irregularidades",'[2]Outros Clientes'!$A$11:$CH$51,CI46,0) -> 0 | CJ35: =VLOOKUP("Condenação",'[2]Outros Clientes'!$A$11:$CH$51,CJ46,0)+VLOOKUP("Penalidades/Irregularidades",'[2]Outros Clientes'!$A$11:$CH$51,CJ46,0) -> 0 | CK35: =VLOOKUP("Condenação",'[2]Outros Clientes'!$A$11:$CH$51,CK46,0)+VLOOKUP("Penalidades/Irregularidades",'[2]Outros Clientes'!$A$11:$CH$51,CK46,0) -> 0 | ... CO35: =VLOOKUP("Condenação",'[2]Outros Clientes'!$A$11:$CH$51,CO46,0)+VLOOKUP("Penalidades/Irregularidades",'[2]Outros Clientes'!$A$11:$CH$51,CO46,0) -> 0 | CP35: =SUM(CD35:CO35) -> 0
A36: RECUPERA | B36: RECUPERA | C36: 0 | D36: 0 | E36: 0 | F36: 0 | G36: 0 | H36: 0 | I36: 0 | J36: 0 | K36: 0 | L36: 0 | M36: 0 | N36: 0 | O36: 0 | P36: 0 | Q36: 0 | R36: 0 | S36: 0 | T36: 0 | U36: 0 | V36: 0 | W36: 0 | X36: 0 | Y36: 0 | Z36: 0 | AA36: 0 | AB36: 0 | AC36: 0 | AD36: 0 | AE36: 0 | AF36: 0 | AG36: 0 | AH36: 0 | AI36: 0 | AJ36: 0 | AK36: 0 | AL36: 0 | AM36: 0 | AN36: 0 | AO36: 0 | AP36: 0 | AQ36: 0 | AR36: 0 | AS36: 0 | AT36: 0 | AU36: 0 | AV36: 0 | AW36: 0 | AX36: 0 | AY36: 0 | AZ36: 0 | BA36: 0 | BB36: 0 | BC36: 0 | BD36: 0 | BE36: 0 | BF36: 0 | BG36: 0 | BH36: 0 | BI36: 0 | BJ36: 0 | BK36: 0 | BL36: 0 | BM36: 42.86 | BN36: 0 | BO36: -42.86 | BP36: =SUM(BD36:BO36) -> 0 | BQ36: 0 | BR36: 0 | BS36: 0 | BT36: 0 | BU36: 0 | BV36: 0 | BW36: 0 | BX36: 0 | BY36: 0 | BZ36: 0 | CA36: 0 | CB36: 0 | CC36: =SUM(BQ36:CB36) -> 0 | CD36: =VLOOKUP("Condenação",[2]Recupera!$A$11:$CI$53,CD46,0)+VLOOKUP("Penalidades/Irregularidades",[2]Recupera!$A$11:$CI$53,CD46,0)+VLOOKUP("Condenação",[2]Recupera!$A$67:$CI$109,CD46,0)+VLOOKUP("Penalidades/Irregularidades",[2]Recupera!$A$67:$CI$109,CD46,0)+VLOOKUP("Condenação",[2]Recupera!$A$123:$CI$165,CD46,0)+VLOOKUP("Penalidades/Irregularidades",[2]Recupera!$A$123:$CI$165,CD46,0) -> 0 | CE36: =VLOOKUP("Condenação",[2]Recupera!$A$11:$CI$53,CE46,0)+VLOOKUP("Penalidades/Irregularidades",[2]Recupera!$A$11:$CI$53,CE46,0)+VLOOKUP("Condenação",[2]Recupera!$A$67:$CI$109,CE46,0)+VLOOKUP("Penalidades/Irregularidades",[2]Recupera!$A$67:$CI$109,CE46,0)+VLOOKUP("Condenação",[2]Recupera!$A$123:$CI$165,CE46,0)+VLOOKUP("Penalidades/Irregularidades",[2]Recupera!$A$123:$CI$165,CE46,0) -> 0 | CF36: =VLOOKUP("Condenação",[2]Recupera!$A$11:$CI$53,CF46,0)+VLOOKUP("Penalidades/Irregularidades",[2]Recupera!$A$11:$CI$53,CF46,0)+VLOOKUP("Condenação",[2]Recupera!$A$67:$CI$109,CF46,0)+VLOOKUP("Penalidades/Irregularidades",[2]Recupera!$A$67:$CI$109,CF46,0)+VLOOKUP("Condenação",[2]Recupera!$A$123:$CI$165,CF46,0)+VLOOKUP("Penalidades/Irregularidades",[2]Recupera!$A$123:$CI$165,CF46,0) -> 31308.16 | CG36: =VLOOKUP("Condenação",[2]Recupera!$A$11:$CI$53,CG46,0)+VLOOKUP("Penalidades/Irregularidades",[2]Recupera!$A$11:$CI$53,CG46,0)+VLOOKUP("Condenação",[2]Recupera!$A$67:$CI$109,CG46,0)+VLOOKUP("Penalidades/Irregularidades",[2]Recupera!$A$67:$CI$109,CG46,0)+VLOOKUP("Condenação",[2]Recupera!$A$123:$CI$165,CG46,0)+VLOOKUP("Penalidades/Irregularidades",[2]Recupera!$A$123:$CI$165,CG46,0) -> 0 | CH36: =VLOOKUP("Condenação",[2]Recupera!$A$11:$CI$53,CH46,0)+VLOOKUP("Penalidades/Irregularidades",[2]Recupera!$A$11:$CI$53,CH46,0)+VLOOKUP("Condenação",[2]Recupera!$A$67:$CI$109,CH46,0)+VLOOKUP("Penalidades/Irregularidades",[2]Recupera!$A$67:$CI$109,CH46,0)+VLOOKUP("Condenação",[2]Recupera!$A$123:$CI$165,CH46,0)+VLOOKUP("Penalidades/Irregularidades",[2]Recupera!$A$123:$CI$165,CH46,0) -> 0 | CI36: =VLOOKUP("Condenação",[2]Recupera!$A$11:$CI$53,CI46,0)+VLOOKUP("Penalidades/Irregularidades",[2]Recupera!$A$11:$CI$53,CI46,0)+VLOOKUP("Condenação",[2]Recupera!$A$67:$CI$109,CI46,0)+VLOOKUP("Penalidades/Irregularidades",[2]Recupera!$A$67:$CI$109,CI46,0)+VLOOKUP("Condenação",[2]Recupera!$A$123:$CI$165,CI46,0)+VLOOKUP("Penalidades/Irregularidades",[2]Recupera!$A$123:$CI$165,CI46,0) -> 0 | CJ36: =VLOOKUP("Condenação",[2]Recupera!$A$11:$CI$53,CJ46,0)+VLOOKUP("Penalidades/Irregularidades",[2]Recupera!$A$11:$CI$53,CJ46,0)+VLOOKUP("Condenação",[2]Recupera!$A$67:$CI$109,CJ46,0)+VLOOKUP("Penalidades/Irregularidades",[2]Recupera!$A$67:$CI$109,CJ46,0)+VLOOKUP("Condenação",[2]Recupera!$A$123:$CI$165,CJ46,0)+VLOOKUP("Penalidades/Irregularidades",[2]Recupera!$A$123:$CI$165,CJ46,0) -> 0 | CK36: =VLOOKUP("Condenação",[2]Recupera!$A$11:$CI$53,CK46,0)+VLOOKUP("Penalidades/Irregularidades",[2]Recupera!$A$11:$CI$53,CK46,0)+VLOOKUP("Condenação",[2]Recupera!$A$67:$CI$109,CK46,0)+VLOOKUP("Penalidades/Irregularidades",[2]Recupera!$A$67:$CI$109,CK46,0)+VLOOKUP("Condenação",[2]Recupera!$A$123:$CI$165,CK46,0)+VLOOKUP("Penalidades/Irregularidades",[2]Recupera!$A$123:$CI$165,CK46,0) -> 0 | ... CO36: =VLOOKUP("Condenação",[2]Recupera!$A$11:$CI$53,CO46,0)+VLOOKUP("Penalidades/Irregularidades",[2]Recupera!$A$11:$CI$53,CO46,0)+VLOOKUP("Condenação",[2]Recupera!$A$67:$CI$109,CO46,0)+VLOOKUP("Penalidades/Irregularidades",[2]Recupera!$A$67:$CI$109,CO46,0)+VLOOKUP("Condenação",[2]Recupera!$A$123:$CI$165,CO46,0)+VLOOKUP("Penalidades/Irregularidades",[2]Recupera!$A$123:$CI$165,CO46,0) -> 0 | CP36: =SUM(CD36:CO36) -> 31308.16
A37: DIRETORIA | B37: DIRETORIA | C37: 0 | D37: 0 | E37: 0 | F37: 0 | G37: 0 | H37: 0 | I37: 0 | J37: 0 | K37: 0 | L37: 0 | M37: 0 | N37: 0 | O37: 0 | P37: =SUM(D37:O37) -> 0 | Q37: 0 | R37: 0 | S37: 0 | T37: 0 | U37: 0 | V37: 0 | W37: 0 | X37: 0 | Y37: 0 | Z37: 0 | AA37: 0 | AB37: 0 | AC37: =SUM(Q37:AB37) -> 0 | AD37: 0 | AE37: 0 | AF37: 0 | AG37: 0 | AH37: 0 | AI37: 0 | AJ37: 0 | AK37: 0 | AL37: 0 | AM37: 6520.5 | AN37: 0 | AO37: 0 | AP37: =SUM(AD37:AO37) -> 6520.5 | AQ37: 0 | AR37: 0 | AS37: 0 | AT37: 0 | AU37: 0 | AV37: 0 | AW37: 0 | AX37: 0 | AY37: 0 | AZ37: 0 | BA37: 0 | BB37: 0 | BC37: =SUM(AQ37:BB37) -> 0 | BD37: 0 | BE37: 0 | BF37: 0 | BG37: 0 | BH37: 0 | BI37: 0 | BJ37: 0 | BK37: 0 | BL37: 0 | BM37: 0 | BN37: 0 | BO37: 0 | BP37: =SUM(BD37:BO37) -> 0 | BQ37: 0 | BR37: 0 | BS37: 0 | BT37: 0 | BU37: 0 | BV37: 0 | BW37: 0 | BX37: 0 | BY37: 0 | BZ37: 0 | CA37: 0 | CB37: 0 | CC37: =SUM(BQ37:CB37) -> 0 | CD37: 0 | CE37: 0 | CF37: 0 | CG37: 0 | CH37: 0 | CI37: 0 | CJ37: 0 | CK37: 0 | CL37: 0 | CM37: 0 | CN37: 0 | CO37: 0 | CP37: =SUM(CD37:CO37) -> 0
A38: CRIMINAL | B38: CRIMINAL | C38: 0 | D38: 0 | E38: 0 | F38: 0 | G38: 0 | H38: 0 | I38: 0 | J38: 0 | K38: 0 | L38: 0 | M38: 0 | N38: 0 | O38: 0 | P38: 0 | Q38: 0 | R38: 0 | S38: 0 | T38: 0 | U38: 0 | V38: 0 | W38: 0 | X38: 0 | Y38: 0 | Z38: 0 | AA38: 0 | AB38: 0 | AC38: 0 | AD38: 0 | AE38: 0 | AF38: 0 | AG38: 0 | AH38: 0 | AI38: 0 | AJ38: 0 | AK38: 0 | AL38: 0 | AM38: 0 | AN38: 0 | AO38: 0 | AP38: 0 | AQ38: 0 | AR38: 0 | AS38: 0 | AT38: 0 | AU38: 0 | AV38: 0 | AW38: 0 | AX38: 0 | AY38: 0 | AZ38: 0 | BA38: 0 | BB38: 0 | BC38: 0 | BD38: 0 | BE38: 0 | BF38: 0 | BG38: 0 | BH38: 0 | BI38: 0 | BJ38: 0 | BK38: 0 | BL38: 0 | BM38: 0 | BN38: 0 | BO38: 0 | BP38: 0 | BQ38: 0 | BR38: 0 | BS38: 0 | BT38: 0 | BU38: 0 | BV38: 0 | BW38: 0 | BX38: 0 | BY38: 0 | BZ38: 0 | CA38: 0 | CB38: 0 | CC38: 0 | CD38: =VLOOKUP("Condenação",[2]Criminal!$A$11:$CE$53,CD46,0)+VLOOKUP("Penalidades/Irregularidades",[2]Criminal!$A$21:$CE$53,CD46,0) -> 0 | CE38: =VLOOKUP("Condenação",[2]Criminal!$A$11:$CE$53,CE46,0)+VLOOKUP("Penalidades/Irregularidades",[2]Criminal!$A$21:$CE$53,CE46,0) -> 0 | CF38: =VLOOKUP("Condenação",[2]Criminal!$A$11:$CE$53,CF46,0)+VLOOKUP("Penalidades/Irregularidades",[2]Criminal!$A$21:$CE$53,CF46,0) -> 0 | CG38: =VLOOKUP("Condenação",[2]Criminal!$A$11:$CE$53,CG46,0)+VLOOKUP("Penalidades/Irregularidades",[2]Criminal!$A$21:$CE$53,CG46,0) -> 0 | CH38: =VLOOKUP("Condenação",[2]Criminal!$A$11:$CE$53,CH46,0)+VLOOKUP("Penalidades/Irregularidades",[2]Criminal!$A$21:$CE$53,CH46,0) -> 0 | CI38: =VLOOKUP("Condenação",[2]Criminal!$A$11:$CE$53,CI46,0)+VLOOKUP("Penalidades/Irregularidades",[2]Criminal!$A$21:$CE$53,CI46,0) -> 0 | CJ38: =VLOOKUP("Condenação",[2]Criminal!$A$11:$CE$53,CJ46,0)+VLOOKUP("Penalidades/Irregularidades",[2]Criminal!$A$21:$CE$53,CJ46,0) -> 0 | CK38: =VLOOKUP("Condenação",[2]Criminal!$A$11:$CE$53,CK46,0)+VLOOKUP("Penalidades/Irregularidades",[2]Criminal!$A$21:$CE$53,CK46,0) -> 0 | ... CO38: =VLOOKUP("Condenação",[2]Criminal!$A$11:$CE$53,CO46,0)+VLOOKUP("Penalidades/Irregularidades",[2]Criminal!$A$21:$CE$53,CO46,0) -> 0
A39: VERO | B39: VERO | C39: 0 | D39: 0 | E39: 0 | F39: 0 | G39: 0 | H39: 0 | I39: 0 | J39: 0 | K39: 0 | L39: 0 | M39: 0 | N39: 0 | O39: 0 | P39: 0 | Q39: 0 | R39: 0 | S39: 0 | T39: 0 | U39: 0 | V39: 0 | W39: 0 | X39: 0 | Y39: 0 | Z39: 0 | AA39: 0 | AB39: 0 | AC39: 0 | AD39: 0 | AE39: 0 | AF39: 0 | AG39: 0 | AH39: 0 | AI39: 0 | AJ39: 0 | AK39: 0 | AL39: 0 | AM39: 0 | AN39: 0 | AO39: 0 | AP39: 0 | AQ39: 0 | AR39: 0 | AS39: 0 | AT39: 0 | AU39: 0 | AV39: 0 | AW39: 0 | AX39: 0 | AY39: 0 | AZ39: 0 | BA39: 0 | BB39: 0 | BC39: 0 | BD39: 0 | BE39: 0 | BF39: 0 | BG39: 0 | BH39: 0 | BI39: 0 | BJ39: 0 | BK39: 0 | BL39: 0 | BM39: 0 | BN39: 0 | BO39: 0 | BP39: 0 | BQ39: 0 | BR39: 0 | BS39: 0 | BT39: 0 | BU39: 0 | BV39: 0 | BW39: 0 | BX39: 0 | BY39: 0 | BZ39: 0 | CA39: 0 | CB39: 0 | CC39: 0 | CD39: =VLOOKUP("Condenação",[2]Vero!$A$11:$CE$53,CD46,0)+VLOOKUP("Penalidades/Irregularidades",[2]Vero!$A$21:$CE$53,CD46,0) -> 0 | CE39: =VLOOKUP("Condenação",[2]Vero!$A$11:$CE$53,CE46,0)+VLOOKUP("Penalidades/Irregularidades",[2]Vero!$A$21:$CE$53,CE46,0) -> 0 | CF39: =VLOOKUP("Condenação",[2]Vero!$A$11:$CE$53,CF46,0)+VLOOKUP("Penalidades/Irregularidades",[2]Vero!$A$21:$CE$53,CF46,0) -> 0 | CG39: =VLOOKUP("Condenação",[2]Vero!$A$11:$CE$53,CG46,0)+VLOOKUP("Penalidades/Irregularidades",[2]Vero!$A$21:$CE$53,CG46,0) -> 0 | CH39: =VLOOKUP("Condenação",[2]Vero!$A$11:$CE$53,CH46,0)+VLOOKUP("Penalidades/Irregularidades",[2]Vero!$A$21:$CE$53,CH46,0) -> 0 | CI39: =VLOOKUP("Condenação",[2]Vero!$A$11:$CE$53,CI46,0)+VLOOKUP("Penalidades/Irregularidades",[2]Vero!$A$21:$CE$53,CI46,0) -> 0 | CJ39: =VLOOKUP("Condenação",[2]Vero!$A$11:$CE$53,CJ46,0)+VLOOKUP("Penalidades/Irregularidades",[2]Vero!$A$21:$CE$53,CJ46,0) -> 0 | CK39: =VLOOKUP("Condenação",[2]Vero!$A$11:$CE$53,CK46,0)+VLOOKUP("Penalidades/Irregularidades",[2]Vero!$A$21:$CE$53,CK46,0) -> 0 | ... CO39: =VLOOKUP("Condenação",[2]Vero!$A$11:$CE$53,CO46,0)+VLOOKUP("Penalidades/Irregularidades",[2]Vero!$A$21:$CE$53,CO46,0) -> 0
A40: QUINTO ANDAR | B40: QUINTO ANDAR | C40: 0 | D40: 0 | E40: 0 | F40: 0 | G40: 0 | H40: 0 | I40: 0 | J40: 0 | K40: 0 | L40: 0 | M40: 0 | N40: 0 | O40: 0 | P40: =SUM(D40:O40) -> 0 | Q40: 0 | R40: 0 | S40: 0 | T40: 0 | U40: 0 | V40: 0 | W40: 0 | X40: 0 | Y40: 0 | Z40: 0 | AA40: 0 | AB40: 0 | AC40: =SUM(Q40:AB40) -> 0 | AD40: 0 | AE40: 0 | AF40: 0 | AG40: 0 | AH40: 0 | AI40: 0 | AJ40: 0 | AK40: 0 | AL40: 0 | AM40: 0 | AN40: 0 | AO40: 0 | AP40: =SUM(AD40:AO40) -> 0 | AQ40: 0 | AR40: 0 | AS40: 0 | AT40: 0 | AU40: 0 | AV40: 0 | AW40: 0 | AX40: 0 | AY40: 0 | AZ40: 0 | BA40: 0 | BB40: 0 | BC40: =SUM(AQ40:BB40) -> 0 | BD40: 0 | BE40: 0 | BF40: 0 | BG40: 0 | BH40: 0 | BI40: 0 | BJ40: 0 | BK40: 0 | BL40: 0 | BM40: 0 | BN40: 0 | BO40: 0 | BP40: =SUM(BD40:BO40) -> 0 | BQ40: 0 | BR40: 0 | BS40: 0 | BT40: 0 | BU40: 0 | BV40: 0 | BW40: 0 | BX40: 0 | BY40: 0 | BZ40: 0 | CA40: 0 | CB40: 0 | CD40: =VLOOKUP("Condenação",'[2]Quinto Andar'!$A$11:$CH$53,CD46,0)+VLOOKUP("Penalidades/Irregularidades",'[2]Quinto Andar'!$A$11:$CH$53,CD46,0) -> 0 | CE40: =VLOOKUP("Condenação",'[2]Quinto Andar'!$A$11:$CH$53,CE46,0)+VLOOKUP("Penalidades/Irregularidades",'[2]Quinto Andar'!$A$11:$CH$53,CE46,0) -> 0 | CF40: =VLOOKUP("Condenação",'[2]Quinto Andar'!$A$11:$CH$53,CF46,0)+VLOOKUP("Penalidades/Irregularidades",'[2]Quinto Andar'!$A$11:$CH$53,CF46,0) -> 0 | CG40: =VLOOKUP("Condenação",'[2]Quinto Andar'!$A$11:$CH$53,CG46,0)+VLOOKUP("Penalidades/Irregularidades",'[2]Quinto Andar'!$A$11:$CH$53,CG46,0) -> 0 | CH40: =VLOOKUP("Condenação",'[2]Quinto Andar'!$A$11:$CH$53,CH46,0)+VLOOKUP("Penalidades/Irregularidades",'[2]Quinto Andar'!$A$11:$CH$53,CH46,0) -> 0 | CI40: =VLOOKUP("Condenação",'[2]Quinto Andar'!$A$11:$CH$53,CI46,0)+VLOOKUP("Penalidades/Irregularidades",'[2]Quinto Andar'!$A$11:$CH$53,CI46,0) -> 0 | CJ40: =VLOOKUP("Condenação",'[2]Quinto Andar'!$A$11:$CH$53,CJ46,0)+VLOOKUP("Penalidades/Irregularidades",'[2]Quinto Andar'!$A$11:$CH$53,CJ46,0) -> 0 | CK40: =VLOOKUP("Condenação",'[2]Quinto Andar'!$A$11:$CH$53,CK46,0)+VLOOKUP("Penalidades/Irregularidades",'[2]Quinto Andar'!$A$11:$CH$53,CK46,0) -> 0 | ... CO40: =VLOOKUP("Condenação",'[2]Quinto Andar'!$A$11:$CH$53,CO46,0)+VLOOKUP("Penalidades/Irregularidades",'[2]Quinto Andar'!$A$11:$CH$53,CO46,0) -> 0 | CP40: =SUM(CD40:CO40) -> 0
A41: DAYCOVAL | B41: DAYCOVAL | C41: 0 | D41: 0 | E41: 0 | F41: 0 | G41: 0 | H41: 0 | I41: 0 | J41: 0 | K41: 0 | L41: 0 | M41: 0 | N41: 0 | O41: 0 | P41: =SUM(D41:O41) -> 0 | Q41: 0 | R41: 0 | S41: 0 | T41: 0 | U41: 0 | V41: 0 | W41: 0 | X41: 0 | Y41: 0 | Z41: 206.1 | AA41: 0 | AB41: 0 | AC41: =SUM(Q41:AB41) -> 206.1 | AD41: 0 | AE41: 0 | AF41: 0 | AG41: 0 | AH41: 0 | AI41: 0 | AJ41: 0 | AK41: 0 | AL41: 0 | AM41: 51.26 | AN41: 0 | AO41: 0 | AP41: =SUM(AD41:AO41) -> 51.26 | AQ41: 0 | AR41: 0 | AS41: 0 | AT41: 0 | AU41: 4732.62 | AV41: 0 | AW41: 0 | AX41: 1598.29 | AY41: 0 | AZ41: 87.83 | BA41: 4732.62 | BB41: 0 | BC41: =SUM(AQ41:BB41) -> 11151.36 | BD41: 2457.2 | BE41: 0 | BF41: 0 | BG41: 1382.47 | BH41: 0 | BI41: 0 | BJ41: 0 | BK41: 0 | BL41: 0 | BM41: 3510.42 | BN41: 0 | BO41: 8321.17 | BP41: =SUM(BD41:BO41) -> 15671.26 | BQ41: 9455.15 | BR41: 2999.99 | BS41: 5578.97 | BT41: 18374.26 | BU41: 7444.01 | BV41: 5121.74 | BW41: 5121.75 | BX41: 0 | BY41: 232219.08 | BZ41: 15692.86 | CA41: 18316.92 | CB41: 6888.45 | CC41: =SUM(BQ41:CB41) -> 327213.18 | CD41: =VLOOKUP("Condenação",[2]Daycoval!$A$11:$CH$80,CD46,0)+VLOOKUP("Penalidades/Irregularidades",[2]Daycoval!$A$11:$CH$80,CD46,0) -> 3782.04 | CE41: =VLOOKUP("Condenação",[2]Daycoval!$A$11:$CH$80,CE46,0)+VLOOKUP("Penalidades/Irregularidades",[2]Daycoval!$A$11:$CH$80,CE46,0) -> 3782.05 | CF41: =VLOOKUP("Condenação",[2]Daycoval!$A$11:$CH$80,CF46,0)+VLOOKUP("Penalidades/Irregularidades",[2]Daycoval!$A$11:$CH$80,CF46,0) -> 0 | CG41: =VLOOKUP("Condenação",[2]Daycoval!$A$11:$CH$80,CG46,0)+VLOOKUP("Penalidades/Irregularidades",[2]Daycoval!$A$11:$CH$80,CG46,0) -> 0 | CH41: =VLOOKUP("Condenação",[2]Daycoval!$A$11:$CH$80,CH46,0)+VLOOKUP("Penalidades/Irregularidades",[2]Daycoval!$A$11:$CH$80,CH46,0) -> 0 | CI41: =VLOOKUP("Condenação",[2]Daycoval!$A$11:$CH$80,CI46,0)+VLOOKUP("Penalidades/Irregularidades",[2]Daycoval!$A$11:$CH$80,CI46,0) -> 0 | CJ41: =VLOOKUP("Condenação",[2]Daycoval!$A$11:$CH$80,CJ46,0)+VLOOKUP("Penalidades/Irregularidades",[2]Daycoval!$A$11:$CH$80,CJ46,0) -> 0 | CK41: =VLOOKUP("Condenação",[2]Daycoval!$A$11:$CH$80,CK46,0)+VLOOKUP("Penalidades/Irregularidades",[2]Daycoval!$A$11:$CH$80,CK46,0) -> 0 | ... CO41: =VLOOKUP("Condenação",[2]Daycoval!$A$11:$CH$80,CO46,0)+VLOOKUP("Penalidades/Irregularidades",[2]Daycoval!$A$11:$CH$80,CO46,0) -> 0 | CP41: =SUM(CD41:CO41) -> 7564.09
C43: =SUM(C2:C42) -> 111120.34 | D43: =SUM(D2:D42) -> 15818.67 | E43: =SUM(E2:E42) -> 19856.42 | F43: =SUM(F2:F42) -> 27171.63 | G43: =SUM(G2:G42) -> 300 | H43: =SUM(H2:H42) -> 5304.8 | I43: =SUM(I2:I42) -> 1476.66 | J43: =SUM(J2:J42) -> 8208.94 | ... AO43: =SUM(AO2:AO42) -> 176797.66 | AQ43: =SUM(AQ2:AQ42) -> 17170.8 | AR43: =SUM(AR2:AR42) -> 22510 | AS43: =SUM(AS2:AS42) -> 32443.95 | AT43: =SUM(AT2:AT42) -> 17170.8 | AU43: =SUM(AU2:AU42) -> 28040.83 | AV43: =SUM(AV2:AV42) -> 65037.66 | AW43: =SUM(AW2:AW42) -> 21614.62 | AX43: =SUM(AX2:AX42) -> 22194.29 | ... BB43: =SUM(BB2:BB42) -> 32755.25 | BD43: =SUM(BD2:BD42) -> 22436.78 | BE43: =SUM(BE2:BE42) -> 37827.72 | BF43: =SUM(BF2:BF42) -> 13762.51 | BG43: =SUM(BG2:BG42) -> 36048.9 | BH43: =SUM(BH2:BH42) -> 69000.39 | BI43: =SUM(BI2:BI42) -> 43713.2 | BJ43: =SUM(BJ2:BJ42) -> 150696.85 | BK43: =SUM(BK2:BK42) -> 78157.04 | ... BO43: =SUM(BO2:BO42) -> 48676.61 | BQ43: =SUM(BQ2:BQ42) -> 28380.25 | BR43: =SUM(BR2:BR42) -> 46323.67 | BS43: =SUM(BS2:BS42) -> 30467.12 | BT43: =SUM(BT2:BT42) -> 47814.81 | BU43: =SUM(BU2:BU42) -> -25621.88 | BV43: =SUM(BV2:BV42) -> 140845.77 | BW43: =SUM(BW2:BW42) -> 36171.73 | BX43: =SUM(BX2:BX42) -> 21721.53 | ... CB43: =SUM(CB2:CB42) -> 21560.92 | CD43: =SUM(CD2:CD42) -> 9114.04 | CE43: =SUM(CE2:CE42) -> 23550.57 | CF43: =SUM(CF2:CF42) -> 31308.16 | CG43: =SUM(CG2:CG42) -> 0 | CH43: =SUM(CH2:CH42) -> 0 | CI43: =SUM(CI2:CI42) -> 0 | CJ43: =SUM(CJ2:CJ42) -> 0 | CK43: =SUM(CK2:CK42) -> 0 | ... CO43: =SUM(CO2:CO42) -> 0
AQ46: 6 | AR46: =AQ46+7 -> 13 | AS46: =AR46+7 -> 20 | AT46: =AS46+7 -> 27 | AU46: =AT46+7 -> 34 | AV46: =AU46+7 -> 41 | AW46: =AV46+7 -> 48 | AX46: =AW46+7 -> 55 | AY46: =AX46+7 -> 62 | ... BB46: =BA46+7 -> 83 | BD46: 6 | BE46: =BD46+7 -> 13 | BF46: =BE46+7 -> 20 | BG46: =BF46+7 -> 27 | BH46: =BG46+7 -> 34 | BI46: =BH46+7 -> 41 | BJ46: =BI46+7 -> 48 | BK46: =BJ46+7 -> 55 | BL46: =BK46+7 -> 62 | ... BO46: =BN46+7 -> 83 | BQ46: 6 | BR46: =BQ46+7 -> 13 | BS46: =BR46+7 -> 20 | BT46: =BS46+7 -> 27 | BU46: =BT46+7 -> 34 | BV46: =BU46+7 -> 41 | BW46: =BV46+7 -> 48 | BX46: =BW46+7 -> 55 | BY46: =BX46+7 -> 62 | ... CB46: =CA46+7 -> 83 | CD46: 6 | CE46: =CD46+7 -> 13 | CF46: =CE46+7 -> 20 | CG46: =CF46+7 -> 27 | CH46: =CG46+7 -> 34 | CI46: =CH46+7 -> 41 | CJ46: =CI46+7 -> 48 | CK46: =CJ46+7 -> 55 | CL46: =CK46+7 -> 62 | ... CO46: =CN46+7 -> 83

Sheet Impostos
A1: Imposto | B1: 43466 | C1: 43497 | D1: 43525 | E1: 43556 | F1: 43586 | G1: 43617 | H1: 43647 | I1: 43678 | J1: 43709 | K1: 43739 | L1: 43770 | M1: 43800 | N1: 43831 | O1: 43862 | P1: 43891 | Q1: 43922 | R1: 43952 | S1: 43983 | T1: 44013 | U1: 44044 | V1: 44075 | W1: 44105 | X1: 44136 | Y1: 44166 | Z1: 44197 | AA1: 44228 | AB1: 44256 | AC1: 44287 | AD1: 44317 | AE1: 44348 | AF1: 44378 | AG1: 44409 | AH1: 44440 | AI1: 44470 | AJ1: 44501 | AK1: 44531 | AL1: 44562 | AM1: 44593 | AN1: 44621 | AO1: 44652 | AP1: 44682 | AQ1: 44713 | AR1: 44743 | AS1: 44774 | AT1: 44805 | AU1: 44835 | AV1: 44866 | AW1: 44896 | AX1: 44927 | AY1: 44958 | AZ1: 44986 | BA1: 45017 | BB1: 45047 | BC1: 45078 | BD1: 45108 | BE1: 45139 | BF1: 45170 | BG1: 45200 | BH1: 45231 | BI1: 45261 | BJ1: 45292 | BK1: 45323 | BL1: 45352 | BM1: 45383 | BN1: 45413 | BO1: 45444 | BP1: 45474 | BQ1: 45505 | BR1: 45536 | BS1: 45566 | BT1: 45597 | BU1: 45627 | BV1: 45658 | BW1: 45689 | BX1: 45717 | BY1: 45748 | BZ1: 45778 | CA1: 45809 | CB1: 45839 | CC1: 45870 | CD1: 45901 | CE1: 45931 | CF1: 45962 | CG1: 45992 | CH1: 46023 | CI1: 46054 | CJ1: 46082 | CK1: 46113 | CL1: 46143 | CM1: 46174 | CN1: 46204 | CO1: 46235 | CP1: 46266 | CQ1: 46296 | CR1: 46327 | CS1: 46357
A2: COFINS Recolhido | B2: 0 | C2: 90.05 | D2: 0 | E2: 0 | F2: 0 | G2: 0 | H2: 0 | I2: 0 | J2: 0 | K2: 0 | L2: 0 | M2: 0 | N2: 0 | O2: 31.68 | P2: 30.18 | Q2: 0 | R2: 183.16 | S2: 205.01 | T2: 473.11 | U2: 0 | V2: 66.35 | W2: 224.98 | X2: 520.59 | Y2: 483.49 | Z2: 0 | AA2: 0 | AB2: 1751.61 | AC2: 815.93 | AD2: 1389.37 | AE2: 648.61 | AF2: 60.31 | AG2: 1882.23 | AH2: 953.14 | AI2: 2004.78 | AJ2: 880.27 | AK2: 612.5 | AL2: 0 | AM2: 4714.99 | AN2: 786.11 | AO2: 1435.71 | AP2: 2808.71 | AQ2: 0 | AR2: 3407.85 | AS2: 652.19 | AT2: 4019.58 | AU2: 1774.8 | AV2: 2220.62 | AW2: 5257.37 | AX2: 5802.58 | AY2: 0 | AZ2: 1169.1 | BA2: 577.66 | BB2: 1117.39 | BC2: 488.32 | BD2: 2522.78 | BE2: 2563.69 | BF2: 4028.37 | BG2: 7879.5 | BH2: 4100.37 | BI2: 1392.42 | BJ2: 7930.23 | BK2: 1996.89 | BL2: 0 | BM2: 157.5 | BN2: 0 | BO2: 2616.23 | BP2: 5808.17 | BQ2: 9665.48 | BR2: 9227.7 | BS2: 12230.3 | BT2: 22085.29 | BU2: 4550.8 | BV2: 28518.45 | BW2: 13238.13 | BX2: 6479.99 | BY2: 17366.11 | BZ2: 7885.72 | CA2: 16076.11 | CB2: 8048.22 | CC2: 5763.49 | CD2: 22696.351 | CE2: 32431.439 | CF2: 13221.23 | CG2: 10103.58 | CH2: =[2]Impostos!C4 -> 16946.33 | CI2: =[2]Impostos!D4 -> 0 | CJ2: =[2]Impostos!E4 -> 24363.39 | CK2: =[2]Impostos!F4 -> 0 | CL2: =[2]Impostos!G4 -> 0 | CM2: =[2]Impostos!H4 -> 0 | CN2: =[2]Impostos!I4 -> 0 | CO2: =[2]Impostos!J4 -> 0 | ... CS2: =[2]Impostos!N4 -> 0
A3: CSLL Recolhida | B3: 30516.43 | C3: 30621.97 | D3: 30770.53 | E3: 21608.56 | F3: 21824.64 | G3: 21941.33 | H3: 30645.24 | I3: 30951.69 | J3: 31104.91 | K3: 29966.34 | L3: 30266 | M3: 30379.87 | N3: 35221.68 | O3: 35573.89 | P3: 0 | Q3: 0 | R3: 2734.23 | S3: 0 | T3: 33470.29 | U3: 36577.49 | V3: 36500.2 | W3: 43207.35 | X3: 40806.92 | Y3: 43657.22 | Z3: 44673.81 | AA3: 45096.71 | AB3: 47565.53 | AC3: 31765.9 | AD3: 31656.15 | AE3: 31740.64 | AF3: 42008.69 | AG3: 42410.32 | AH3: 42590.56 | AI3: 45522.38 | AJ3: 45962.37 | AK3: 46230.2 | AL3: 44703.38 | AM3: 45141.24 | AN3: 45479.62 | AO3: 39625.63 | AP3: 40014.99 | AQ3: 42329.5 | AR3: 45263.03 | AS3: 45713.24 | AT3: 46239.03 | AU3: 43232.98 | AV3: 43661.72 | AW3: 44098.48 | AX3: 3233.77 | AY3: 3264.39 | AZ3: 3289.55 | BA3: 39835.84 | BB3: 40226.13 | BC3: 40060.9 | BD3: 50985.89 | BE3: 51531.25 | BF3: 52148.2 | BG3: 57728.71 | BH3: 58335.43 | BI3: 58893.6 | BJ3: 58433.25 | BK3: 58508.64 | BL3: 59550.05 | BM3: 48308.54 | BN3: 45424.83 | BO3: 45798.12 | BP3: 67192.46 | BQ3: 67127.12 | BR3: 67705.34 | BS3: 74586.89 | BT3: 75332.75 | BU3: 98648.61 | BV3: 92138.91 | BW3: 93060.29 | BX3: 93972.47 | BY3: 68239.29 | BZ3: 68921.66 | CA3: 69699.59 | CB3: 90109.98 | CC3: 91011.06 | CD3: 92428.34 | CE3: 85634.73 | CF3: 86491.05 | CG3: 87390.22 | CH3: =[2]Impostos!C5 -> 97595.01 | CI3: =[2]Impostos!D5 -> 119937.81 | CJ3: =[2]Impostos!E5 -> 99546.91 | CK3: =[2]Impostos!F5 -> 0 | CL3: =[2]Impostos!G5 -> 0 | CM3: =[2]Impostos!H5 -> 0 | CN3: =[2]Impostos!I5 -> 0 | CO3: =[2]Impostos!J5 -> 0 | ... CS3: =[2]Impostos!N5 -> 0
A4: DARF - Simples | B4: 38991.56 | C4: 9062.79 | D4: 33802.26 | E4: 50979.6 | F4: 18032.19 | G4: 52918.52 | H4: 41475.32 | I4: 47302.21 | J4: 43067.86 | K4: 28750.7 | L4: 60284.77 | M4: 43056.94 | N4: 65116.44 | O4: 56316.93 | P4: 50842.12 | Q4: 0 | R4: 0 | S4: 0 | T4: 52406.52 | U4: 60126.91 | V4: 56907.83 | W4: 90536.28 | X4: 90211.54 | Y4: 62367.89 | Z4: 34736.89 | AA4: 31466.1 | AB4: 26539.97 | AC4: 0 | AD4: 0 | AE4: 0 | AF4: 50590.17 | AG4: 48348.23 | AH4: 85524.57 | AI4: 88400.27 | AJ4: 74718.77 | AK4: 75100.62 | AL4: 46679.24 | AM4: 46712.89 | AN4: 44798.78 | AO4: 40851.59 | AP4: 61505.2 | AQ4: 54546.5 | AR4: 58951.46 | AS4: 58525.71 | AT4: 60171.53 | AU4: 60232.48 | AV4: 59326.86 | AW4: 67136.54 | AX4: 68613.35 | AY4: 52242.38 | AZ4: 76206.24 | BA4: 74163.88 | BB4: 76009.39 | BC4: 65971.43 | BD4: 109784.82 | BE4: 91959.89 | BF4: 87017.33 | BG4: 123250.38 | BH4: 117181.37 | BI4: 142646.35 | BJ4: 180525.97 | BK4: 96987.43 | BL4: 147949.14 | BM4: 110136.22 | BN4: 77376.65 | BO4: 110181 | BP4: 119745.35 | BQ4: 106490 | BR4: 82945.48 | BS4: 112666.7 | BT4: 98586.67 | BU4: 179033.23 | BV4: 285443.07 | BW4: 97621.11 | BX4: 151733.52 | BY4: 121768.54 | BZ4: 119760.11 | CA4: 108454.55 | CB4: 130515.63 | CC4: 128701.34 | CD4: 184283.14 | CE4: 115288.85 | CF4: 214972.4 | CG4: 254324.55 | CH4: =[2]Impostos!C6 -> 97807.56 | CI4: =[2]Impostos!D6 -> 27148.89 | CJ4: =[2]Impostos!E6 -> 12031.93 | CK4: =[2]Impostos!F6 -> 0 | CL4: =[2]Impostos!G6 -> 0 | CM4: =[2]Impostos!H6 -> 0 | CN4: =[2]Impostos!I6 -> 0 | CO4: =[2]Impostos!J6 -> 0 | ... CS4: =[2]Impostos!N6 -> 0
A5: IRPJ Recolhida | B5: 103380.25 | C5: 103853.36 | D5: 104357.2 | E5: 72691.39 | F5: 73418.3 | G5: 73810.83 | H5: 103953.89 | I5: 104993.42 | J5: 105513.19 | K5: 101606.69 | L5: 102622.75 | M5: 103008.86 | N5: 119776.68 | O5: 120974.44 | P5: 0 | Q5: 0 | R5: 0 | S5: 0 | T5: 113534.26 | U5: 124090.62 | V5: 123819.63 | W5: 147255.17 | X5: 139102.81 | Y5: 148788.83 | Z5: 152117.12 | AA5: 153557.27 | AB5: 153817.68 | AC5: 105716.82 | AD5: 106698.1 | AE5: 106982.87 | AF5: 142617.89 | AG5: 143981.39 | AH5: 144593.26 | AI5: 154168.11 | AJ5: 155658.05 | AK5: 156565.06 | AL5: 151926.82 | AM5: 153414.93 | AN5: 154564.95 | AO5: 133312.17 | AP5: 134621.17 | AQ5: 135985.72 | AR5: 152548.97 | AS5: 154066.24 | AT5: 155838.19 | AU5: 145886.23 | AV5: 147332.91 | AW5: 148806.62 | AX5: 10988.4 | AY5: 11092.46 | AZ5: 11177.94 | BA5: 135152.52 | BB5: 136476.65 | BC5: 136021.31 | BD5: 173150.71 | BE5: 174850.16 | BF5: 176782.78 | BG5: 193766.09 | BH5: 195665.61 | BI5: 197413.18 | BJ5: 196020.74 | BK5: 197435.89 | BL5: 200855.8 | BM5: 163151.72 | BN5: 154560.28 | BO5: 155830.43 | BP5: 225959.79 | BQ5: 228219.38 | BR5: 230185.23 | BS5: 249110.96 | BT5: 251602.07 | BU5: 253570.05 | BV5: 304569.49 | BW5: 307615.18 | BX5: 310630.42 | BY5: 225849.64 | BZ5: 228108.12 | CA5: 230682.81 | CB5: 271385.43 | CC5: 274031.24 | CD5: 270799.63 | CE5: 279098.39 | CF5: 281889.36 | CG5: 284819.89 | CH5: =[2]Impostos!C7 -> 318073.24 | CI5: =[2]Impostos!D7 -> 321186.05 | CJ5: =[2]Impostos!E7 -> 317507.6 | CK5: =[2]Impostos!F7 -> 0 | CL5: =[2]Impostos!G7 -> 0 | CM5: =[2]Impostos!H7 -> 0 | CN5: =[2]Impostos!I7 -> 0 | CO5: =[2]Impostos!J7 -> 0 | ... CS5: =[2]Impostos!N7 -> 0
A6: IRPJ Retido | B6: 0 | C6: 0 | D6: 0 | E6: 0 | F6: 0 | G6: 0 | H6: 0 | I6: 0 | J6: 0 | K6: 0 | L6: 0 | M6: 0 | N6: 0 | O6: 0 | P6: 0 | Q6: 0 | R6: 9290.95 | S6: 0 | T6: 0 | U6: 0 | V6: 0 | W6: 0 | X6: 0 | Y6: 0 | Z6: 0 | AA6: 0 | AB6: 709.45 | AC6: 120 | AD6: 0 | AE6: 0 | AF6: 0 | AG6: 0 | AH6: 0 | AI6: 0 | AJ6: 0 | AK6: 0 | AL6: 0 | AM6: 0 | AN6: 0 | AO6: 0 | AP6: 0 | AQ6: 0 | AR6: 0 | AS6: 0 | AT6: 0 | AU6: 0 | AV6: 0 | AW6: 0 | AX6: 0 | AY6: 0 | AZ6: 0 | BA6: 0 | BB6: 0 | BC6: 0 | BD6: 0 | BE6: 0 | BF6: 0 | BG6: 0 | BH6: 0 | BI6: 0 | BJ6: 0 | BK6: 0 | BL6: 0 | BM6: 0 | BN6: 0 | BO6: 0 | BP6: 0 | BQ6: 0 | BR6: 0 | BS6: 0 | BT6: 0 | BU6: 0 | BV6: 0 | BW6: 0 | BX6: 0 | BY6: 0 | BZ6: 0 | CA6: 0 | CB6: 0 | CC6: 0 | CD6: 0 | CE6: 0 | CF6: 0 | CG6: 0 | CH6: =[2]Impostos!C8 -> 0 | CI6: =[2]Impostos!D8 -> 0 | CJ6: =[2]Impostos!E8 -> 0 | CK6: =[2]Impostos!F8 -> 0 | CL6: =[2]Impostos!G8 -> 0 | CM6: =[2]Impostos!H8 -> 0 | CN6: =[2]Impostos!I8 -> 0 | CO6: =[2]Impostos!J8 -> 0 | ... CS6: =[2]Impostos!N8 -> 0
A7: ISS | B7: 20802.55 | C7: 21605.63 | D7: 21605.63 | E7: 21605.63 | F7: 21605.63 | G7: 21605.63 | H7: 21605.63 | I7: 21605.63 | J7: 21605.63 | K7: 21605.63 | L7: 21605.63 | M7: 21605.63 | N7: 21605.63 | O7: 0 | P7: 23448.11 | Q7: 359.22 | R7: 362.81 | S7: 23176.03 | T7: 49001.16 | U7: 23190.39 | V7: 23197.57 | W7: 23204.75 | X7: 49136.55 | Y7: 49143.73 | Z7: 48916.48 | AA7: 50958.9 | AB7: 50966.39 | AC7: 50973.87 | AD7: 50981.39 | AE7: 50988.88 | AF7: 53503.53 | AG7: 53511.02 | AH7: 53503.49 | AI7: 53518.5 | AJ7: 53463.17 | AK7: 53091.66 | AL7: 53560.34 | AM7: 59054.73 | AN7: 59063 | AO7: 59071.26 | AP7: 59079.53 | AQ7: 59087.83 | AR7: 59096.1 | AS7: 73561.38 | AT7: 73569.65 | AU7: 73577.96 | AV7: 73586.22 | AW7: 73902.08 | AX7: 73662.38 | AY7: 77954.08 | AZ7: 77962.83 | BA7: 77971.58 | BB7: 77980.38 | BC7: 77989.13 | BD7: 78975.12 | BE7: 78006.68 | BF7: 78015.48 | BG7: 78024.23 | BH7: 78032.98 | BI7: 78041.73 | BJ7: 78105.97 | BK7: 97470.02 | BL7: 105384.63 | BM7: 99456.35 | BN7: 93312.04 | BO7: 97401.7 | BP7: 92385.38 | BQ7: 86781.63 | BR7: 76029.36 | BS7: 86019.39 | BT7: 77547.89 | BU7: 80598.18 | BV7: 80034.92 | BW7: 83801.9 | BX7: 106164.46 | BY7: 101541.53 | BZ7: 100805.94 | CA7: 93301.43 | CB7: 102044.51 | CC7: 102919.67 | CD7: 115852.94 | CE7: 97414.05 | CF7: 140805.56 | CG7: 154661.1 | CH7: =[2]Impostos!C9 -> 116848.13 | CI7: =[2]Impostos!D9 -> 104440.97 | CJ7: =[2]Impostos!E9 -> 95340.9 | CK7: =[2]Impostos!F9 -> 0 | CL7: =[2]Impostos!G9 -> 0 | CM7: =[2]Impostos!H9 -> 0 | CN7: =[2]Impostos!I9 -> 0 | CO7: =[2]Impostos!J9 -> 0 | ... CS7: =[2]Impostos!N9 -> 0
A8: ISS Unidade Vitória | B8: 0 | C8: 0 | D8: 0 | E8: 0 | F8: 0 | G8: 0 | H8: 0 | I8: 0 | J8: 0 | K8: 0 | L8: 0 | M8: 0 | N8: 997.7 | O8: 997.7 | P8: 0 | Q8: 367.1 | R8: 367.1 | S8: 367.1 | T8: 367.1 | U8: 367.1 | V8: 367.1 | W8: 367.1 | X8: 367.1 | Y8: 367.1 | Z8: 382.63 | AA8: 382.63 | AB8: 382.63 | AC8: 382.63 | AD8: 382.63 | AE8: 382.63 | AF8: 382.63 | AG8: 382.63 | AH8: 382.63 | AI8: 382.63 | AJ8: 382.63 | AK8: 382.63 | AL8: 422.5 | AM8: 422.5 | AN8: 422.5 | AO8: 422.5 | AP8: 422.5 | AQ8: 422.5 | AR8: 422.5 | AS8: 422.5 | AT8: 422.5 | AU8: 422.5 | AV8: 422.5 | AW8: 422.5 | AX8: 447.42 | AY8: 447.42 | AZ8: 447.42 | BA8: 447.42 | BB8: 447.42 | BC8: 447.42 | BD8: 447.42 | BE8: 447.42 | BF8: 447.42 | BG8: 447.42 | BH8: 0 | BI8: 0 | BJ8: 0 | BK8: 0 | BL8: 0 | BM8: 0 | BN8: 0 | BO8: 0 | BP8: 0 | BQ8: 0 | BR8: 0 | BS8: 0 | BT8: 0 | BU8: 0 | BV8: 0 | BW8: 0 | BX8: 0 | BY8: 0 | BZ8: 0 | CA8: 0 | CB8: 0 | CC8: 0 | CD8: 0 | CE8: 0 | CF8: 0 | CG8: 0 | CH8: 0 | CI8: 0 | CJ8: 0 | CK8: 0 | CL8: 0 | CM8: 0 | CN8: 0 | CO8: 0 | CP8: 0 | CQ8: 0 | CR8: 0 | CS8: 0
A9: PIS Recolhido | B9: 0 | C9: 19.74 | D9: 0 | E9: 0 | F9: 0 | G9: 0 | H9: 0 | I9: 0 | J9: 0 | K9: 0 | L9: 0 | M9: 0 | N9: 0 | O9: 0 | P9: 14.17 | Q9: 0 | R9: 40.09 | S9: 44.74 | T9: 102.9 | U9: 0 | V9: 14.76 | W9: 40.09 | X9: 122.99 | Y9: 105.11 | Z9: 0 | AA9: 0 | AB9: 379.86 | AC9: 177.11 | AD9: 301.48 | AE9: 141.09 | AF9: 13.42 | AG9: 408.33 | AH9: 207.03 | AI9: 434.84 | AJ9: 191.1 | AK9: 133.14 | AL9: 0 | AM9: 1027.32 | AN9: 170.75 | AO9: 311.86 | AP9: 609.07 | AQ9: 410.49 | AR9: 738.83 | AS9: 141.74 | AT9: 871.33 | AU9: 385.02 | AV9: 481.5 | AW9: 1139.52 | AX9: 1257.71 | AY9: 0 | AZ9: 253.65 | BA9: 125.53 | BB9: 242.98 | BC9: 106.29 | BD9: 565.46 | BE9: 555.99 | BF9: 873.25 | BG9: 1707.65 | BH9: 889.02 | BI9: 302.32 | BJ9: 1718.94 | BK9: 433.3 | BL9: 0 | BM9: 34.66 | BN9: 0 | BO9: 566.76 | BP9: 1258.36 | BQ9: 2094.06 | BR9: 1999.3 | BS9: 2649.84 | BT9: 4785.12 | BU9: 985.91 | BV9: 6178.91 | BW9: 2868.19 | BX9: 1403.88 | BY9: 3762.55 | BZ9: 1708.48 | CA9: 3483.06 | CB9: 1743.65 | CC9: 1248.66 | CD9: 4917.4694 | CE9: 3439.091 | CF9: 2864.52 | CG9: 2189.05 | CH9: =[2]Impostos!C10 -> 3671.59 | CI9: =[2]Impostos!D10 -> 0 | CJ9: =[2]Impostos!E10 -> 5278.59 | CK9: =[2]Impostos!F10 -> 0 | CL9: =[2]Impostos!G10 -> 0 | CM9: =[2]Impostos!H10 -> 0 | CN9: =[2]Impostos!I10 -> 0 | CO9: =[2]Impostos!J10 -> 0 | ... CS9: =[2]Impostos!N10 -> 0
A10: Parcelamentos | B10: 0 | C10: 0 | D10: 0 | E10: 0 | F10: 0 | G10: 0 | H10: 0 | I10: 0 | J10: 0 | K10: 0 | L10: 0 | M10: 0 | N10: 7055.23 | O10: 7077.02 | P10: 7093.65 | Q10: 7113.15 | R10: 1667.45 | S10: 1670.07 | T10: 1672.35 | U10: 12657.44 | V10: 7175.11 | W10: 12690.68 | X10: 7193.46 | Y10: 12722.85 | Z10: 7211.24 | AA10: 7219.84 | AB10: 7227.31 | AC10: 7238.77 | AD10: 7250.82 | AE10: 7266.31 | AF10: 7284.09 | AG10: 7304.73 | AH10: 7329.4 | AI10: 7354.65 | AJ10: 7382.75 | AK10: 7416.59 | AL10: 7460.76 | AM10: 7502.63 | AN10: 7546.23 | AO10: 7599.57 | AP10: 7647.17 | AQ10: 7706.26 | AR10: 7764.77 | AS10: 7823.85 | AT10: 7890.95 | AU10: 7952.33 | AV10: 8010.84 | AW10: 8069.34 | AX10: 8133.6 | AY10: 8197.83 | AZ10: 20189.55 | BA10: 20376.03 | BB10: 20538.66 | BC10: 23288.22 | BD10: 23478.26 | BE10: 23668.31 | BF10: 23870.78 | BG10: 24043.06 | BH10: 24220.68 | BI10: 24384.09 | BJ10: 12410.04 | BK10: 25752.78 | BL10: 25916.06 | BM10: 25003.94 | BN10: 39990.27 | BO10: 40245.94 | BP10: 40489.74 | BQ10: 40769.21 | BR10: 41036.77 | BS10: 41295.43 | BT10: 41580.81 | BU10: 41824.64 | BV10: 39629.28 | BW10: 42482.75 | BX10: 42786.41 | BY10: 43081.12 | BZ10: 25971.45 | CA10: 26182.54 | CB10: 26386.61 | CC10: 26622.43 | CD10: 26837.12 | CE10: 27062.35 | CF10: 26506.06 | CG10: 26696.45 | CH10: =[2]Impostos!C11 -> 26948.5 | CI10: =[2]Impostos!D11 -> 27158.59 | CJ10: =[2]Impostos!E11 -> 27340.36 | CK10: =[2]Impostos!F11 -> 0 | CL10: =[2]Impostos!G11 -> 0 | CM10: =[2]Impostos!H11 -> 0 | CN10: =[2]Impostos!I11 -> 0 | CO10: =[2]Impostos!J11 -> 0 | ... CS10: =[2]Impostos!N11 -> 0
A11: Imposto Retido s/ NF | B11: 77520.69 | C11: 66168.546 | D11: 69573.95 | E11: 72145.667 | F11: 97609.772 | G11: 121924.73 | H11: 116444 | I11: 110070.38 | J11: 109661.16 | K11: 85999.196 | L11: 128773.39 | M11: 99692.177 | N11: 113042.14 | O11: 81506.076 | P11: 138998.55 | Q11: 117160.41 | R11: 104571.09 | S11: 99798.284 | T11: 129302.12 | U11: 88354.81 | V11: 146786.89 | W11: 97632.29 | X11: 160958.73 | Y11: 144202.1 | Z11: 117766.74 | AA11: 94436.29 | AB11: 78355.95 | AC11: 124383.63 | AD11: 149085.49 | AE11: 113676.88 | AF11: 123678.31 | AG11: 119639.86 | AH11: 112599.46 | AI11: 127625.71 | AJ11: 137986.43 | AK11: 156896.82 | AL11: 119008.85 | AM11: 78366.48 | AN11: 105536.64 | AO11: 142981.32 | AP11: 171486.91 | AQ11: 122758.99 | AR11: 136247.08 | AS11: 104293.73 | AT11: 126319.12 | AU11: 130498.76 | AV11: 132235.32 | AW11: 133600.15 | AX11: 151943.48 | AY11: 103914.1 | AZ11: 113472.18 | BA11: 160869.88 | BB11: 144245.81 | BC11: 126675.16 | BD11: 141784.08 | BE11: 174504.38 | BF11: 120939.29 | BG11: 144609.72 | BH11: 164600.82 | BI11: 215167.66 | BJ11: 145046.36 | BK11: 152083.04 | BL11: 110495.65 | BM11: 106642.8 | BN11: 165768.84 | BO11: 200839.05 | BP11: 217214.83 | BQ11: 152998.14 | BR11: 206261.21 | BS11: 207841.8 | BT11: 283258.97 | BU11: 194131.24 | BV11: 204134.38 | BW11: 198673.46 | BX11: 195732.17 | BY11: 192391.36 | BZ11: 159509.92 | CA11: 223001.11 | CB11: 246883.33 | CC11: 218240.87 | CD11: 216145.88 | CE11: 201568.34 | CF11: 233669.05 | CG11: 401095.77 | CH11: =[2]Impostos!C15 -> 204949.16 | CI11: =[2]Impostos!D15 -> 195642.45 | CJ11: =[2]Impostos!E15 -> 252702.91 | CK11: =[2]Impostos!F15 -> 0 | CL11: =[2]Impostos!G15 -> 0 | CM11: =[2]Impostos!H15 -> 0 | CN11: =[2]Impostos!I15 -> 0 | CO11: =[2]Impostos!J15 -> 0 | ... CS11: =[2]Impostos!N15 -> 0

Sheet Resultado Intercompany
A1: Tipo | B1: CARTEIRA | C1: Valor
A2: Com Intercompany | B2: Mercado Livre | C2: 677682.34
A3: Com Intercompany | B3: Santander | C3: 653876.92
A4: Com Intercompany | B4: Valor Legal | C4: 527207.81
A5: Com Intercompany | B5: Estratégico | C5: 523432.46
A6: Com Intercompany | B6: Vivo | C6: 360105.85
A7: Com Intercompany | B7: Enel | C7: 194149.91
A8: Com Intercompany | B8: Imobiliário | C8: 131952.7
A9: Com Intercompany | B9: Claro | C9: 128722.86
A10: Com Intercompany | B10: MRS | C10: 20605.23
A11: Com Intercompany | B11: Naturgy | C11: 11871.8
A12: Com Intercompany | B12: XS4 CAP | C12: 1989.12
A13: Com Intercompany | B13: Madeira Madeira | C13: -20353.41
... A41: Sem Intercompany | B41: Saneamento | C41: -670167.96

Sheet Cotas
A1: Mês | B1: Cotas | C1: Diferença | D1: %
A2: 44927 | B2: 16589.65
A3: 44958 | B3: 17224.61 | C3: =B3-B2 -> 634.96 | D3: =B3/B2-1 -> 0.038274466
A4: 44986 | B4: 16802.19 | C4: =B4-B3 -> -422.42 | D4: =B4/B3-1 -> -0.024524213
A5: 45017 | B5: 17625.67 | C5: =B5-B4 -> 823.48 | D5: =B5/B4-1 -> 0.049010278
A6: 45047 | B6: 17969.13 | C6: =B6-B5 -> 343.46 | D6: =B6/B5-1 -> 0.019486351
A7: 45078 | B7: 18272.67 | C7: =B7-B6 -> 303.54 | D7: =B7/B6-1 -> 0.016892304
A8: 45108 | B8: 18547.68 | C8: =B8-B7 -> 275.01 | D8: =B8/B7-1 -> 0.015050346
A9: 45139 | B9: 18543.23 | C9: =B9-B8 -> -4.45 | D9: =B9/B8-1 -> -0.00023992219
A10: 45170 | B10: 18952.33 | C10: =B10-B9 -> 409.1 | D10: =B10/B9-1 -> 0.02206196
A11: 45200 | B11: 19412.77 | C11: =B11-B10 -> 460.44 | D11: =B11/B10-1 -> 0.024294638
A12: 45231 | B12: 19587.5 | C12: =B12-B11 -> 174.73 | D12: =B12/B11-1 -> 0.0090007763
A13: 45261 | B13: 19743.61 | C13: =B13-B12 -> 156.11 | D13: =B13/B12-1 -> 0.0079698787
A14: 45292 | B14: 20643.29 | C14: =B14-B13 -> 899.68 | D14: =B14/B13-1 -> 0.045568161
... A40: 46082 | B40: 31681.81 | C40: =B40-B39 -> 207.06 | D40: =B40/B39-1 -> 0.0065786067

Sheet Pessoas
A1: Tipo | B1: Função | C1: 2019 | D1: 2020 | E1: 2021 | F1: 2022 | G1: 2023 | H1: 2024 | I1: 2025 | J1: 2026 | M1: Função | N1: 2019 | O1: 2020 | P1: 2021 | Q1: 2022 | R1: 2023 | S1: 2024 | T1: 2025 | U1: 2026
A2: Total | B2: Sócios | C2: =4+178+1+7+0 -> 190 | D2: =3+201+1+11+0 -> 216 | E2: =3+244+1+11+1 -> 260 | F2: 269 | G2: 310 | H2: 355 | I2: 437 | J2: 438 | M2: Sócios | R2: 37 | S2: 46 | T2: 59
A3: Total | B3: Celetistas | C3: =53 -> 53 | D3: =55 -> 55 | E3: =78 -> 78 | F3: 91 | G3: 107 | H3: 107 | I3: 124 | J3: 123 | M3: Celetistas | R3: 51 | S3: 54 | T3: 65
A4: Total | B4: Estagiários | C4: =23+2 -> 25 | D4: =23+3 -> 26 | E4: =27+2 -> 29 | F4: =30+1 -> 31 | G4: 44 | H4: 37 | I4: 35 | J4: 32 | M4: Estagiários | R4: 7 | S4: 11 | T4: 11
A5: Total | B5: Total | C5: =C2+C3+C4*0.5 -> 255.5 | D5: =D2+D3+D4*0.5 -> 284 | E5: =E2+E3+E4*0.5 -> 352.5 | F5: =F2+F3+F4*0.5 -> 375.5 | G5: =G2+G3+G4*0.5 -> 439 | H5: =H2+H3+H4*0.5 -> 480.5 | I5: =I2+I3+I4*0.5 -> 578.5 | J5: =J2+J3+J4*0.5 -> 577
A6: Total | B6: Estoque | C6: 56316 | D6: 69272 | E6: 84832 | F6: 103779 | G6: 119211 | H6: 117977 | I6: 113619 | J6: 116095
A7: Sem times de suporte | B7: Função | E7: 2021 | F7: 2022 | G7: 2023 | H7: 2024 | I7: 2025 | J7: 2026
A8: Sem times de suporte | B8: Sócios | E8: 216 | F8: 229 | G8: 273 | H8: 309 | I8: 376 | J8: 375
A9: Sem times de suporte | B9: Celetistas | E9: 28 | F9: 42 | G9: 56 | H9: 53 | I9: 59 | J9: 60
A10: Sem times de suporte | B10: Estagiários | E10: 23 | F10: 34 | G10: 37 | H10: 26 | I10: 23 | J10: 22
A11: Sem times de suporte | B11: Total | E11: =E8+E9+E10*0.5 -> 255.5 | F11: =F8+F9+F10*0.5 -> 288 | G11: =G8+G9+G10*0.5 -> 347.5 | H11: =H8+H9+H10*0.5 -> 375 | I11: =I8+I9+I10*0.5 -> 446.5 | J11: =J8+J9+J10*0.5 -> 446
A12: Sem times de suporte | B12: Estoque | E12: 84832 | F12: 103779 | G12: 119211 | H12: 117977 | I12: 113619 | J12: 116095

Sheet DRE
A1: # | B1: GRUPO | C1: MARC | D1: Lançamento | E1: 45413 | F1: % s/ Tot - mai 24 | G1: 45444 | H1: % s/ Tot - jun 24 | I1: 45474 | J1: % s/ Tot - jul 24 | K1: 45505 | L1: % s/ Tot - ago 24 | M1: 45536 | N1: % s/ Tot - set 24 | O1: 45566 | P1: % s/ Tot - out 24 | Q1: 45597 | R1: % s/ Tot - nov 24 | S1: 45627 | T1: % s/ Tot - dez 24 | U1: Total - 2024 | V1: % s/ Total Desp Acum 24 | W1: 45658 | X1: % s/ Tot - jan 25 | Y1: 45689 | Z1: % s/ Tot - fev 25 | AA1: 45717 | AB1: % s/ Tot - mar 25 | AC1: 45748 | AD1: % s/ Tot - abr 25 | AE1: 45778 | AF1: % s/ Tot - mai 25 | AG1: 45809 | AH1: % s/ Tot - jun 25 | AI1: 45839 | AJ1: % s/ Tot - jul 25 | AK1: 45870 | AL1: % s/ Tot - ago 25 | AM1: 45901 | AN1: % s/ Tot - set 25 | AO1: 45931 | AP1: % s/ Tot - out 25 | AQ1: 45962 | AR1: % s/ Tot - nov 25 | AS1: 45992 | AT1: % s/ Tot - dez 25 | AU1: Total - 2025 | AV1: % s/ Total Desp Acum | AW1: % Evolução
A2: 1 | D2: RECEITAS BRUTA PREST SERVIÇOS | E2: 3629988.7 | G2: 4068124.1 | I2: 4640246.4 | K2: 3454210 | M2: 4253136.9 | O2: 4658140.7 | Q2: 6144339 | S2: 5312105.9 | U2: =E2+G2+I2+K2+M2+O2+Q2+S2 -> 36160292 | W2: 4402653.9 | Y2: 4086254.3 | AA2: 4048194.3 | AC2: 3939627.5 | AE2: 3548210.9 | AG2: 4304516.3 | AI2: 4526009.4 | AK2: 4828600.7 | AM2: 4420476.6 | AO2: 4300330.3 | AQ2: 4681796.7 | AS2: 7347433 | AU2: =W2+Y2+AA2+AC2+AE2+AG2+AI2+AK2+AM2+AO2+AQ2+AS2 -> 54434104 | AW2: 0.56936182
A3: 2 | D3: Deduções da Receita | E3: -206846.93 | F3: =F4+F5 -> 1 | G3: -232543.67 | H3: =H4+H5 -> 1 | I3: -254841.8 | J3: =J4+J5 -> 1 | K3: -185496.52 | L3: =L4+L5 -> 1 | M3: -237694.88 | N3: =N4+N5 -> 1 | O3: -239568.6 | P3: =P4+P5 -> 1 | Q3: -288343.16 | R3: =R4+R5 -> 1 | S3: -206248.81 | T3: =T4+T5 -> 1 | U3: =E3+G3+I3+K3+M3+O3+Q3+S3 -> -1851584.4 | V3: =V4+V5 -> 1 | W3: -214931.8 | X3: =X4+X5 -> 1 | Y3: -206349.57 | Z3: =Z4+Z5 -> 1 | AA3: -201311.21 | AB3: =AB4+AB5 -> 1 | AC3: -211344.98 | AD3: =AD4+AD5 -> 1 | AE3: -165020.36 | AF3: =AF4+AF5 -> 1 | AG3: -232285.09 | AH3: =AH4+AH5 -> 1 | AI3: -252123.92 | AJ3: =AJ4+AJ5 -> 1 | AK3: -219001.12 | AL3: =AL4+AL5 -> 1 | AM3: -220555.46 | AN3: =AN4+AN5 -> 1 | AO3: -210641.86 | AP3: =AP4+AP5 -> 1 | AQ3: -258689.86 | AR3: =AR4+AR5 -> 1 | AS3: -452319.85 | AT3: =AT4+AT5 -> 1 | AU3: =W3+Y3+AA3+AC3+AE3+AG3+AI3+AK3+AM3+AO3+AQ3+AS3 -> -2844575.1 | AV3: =AV4+AV5 -> 1 | AW3: 0.74850242
A4: 3 | B4: CUSTOS E DESPESAS | D4: (-) Impostos Retidos s/Fatur | E4: -165768.84 | F4: =E4/E3 -> 0.80140827 | G4: -200839.05 | H4: =G4/G3 -> 0.86366165 | I4: -217214.83 | J4: =I4/I3 -> 0.85235166 | K4: -152998.14 | L4: =K4/K3 -> 0.82480329 | M4: -206261.21 | N4: =M4/M3 -> 0.86775622 | O4: -207841.8 | P4: =O4/O3 -> 0.86756695 | Q4: -283258.97 | R4: =Q4/Q3 -> 0.98236757 | S4: -194131.24 | T4: =S4/S3 -> 0.94124781 | U4: =E4+G4+I4+K4+M4+O4+Q4+S4 -> -1628314.1 | V4: =U4/U3 -> 0.87941663 | W4: -204134.38 | X4: =W4/W3 -> 0.94976351 | Y4: -198673.46 | Z4: =Y4/Y3 -> 0.96280046 | AA4: -195732.17 | AB4: =AA4/AA3 -> 0.97228649 | AC4: -192391.36 | AD4: =AC4/AC3 -> 0.91031904 | AE4: -159509.92 | AF4: =AE4/AE3 -> 0.96660751 | AG4: -223001.11 | AH4: =AG4/AG3 -> 0.96003196 | AI4: -246883.33 | AJ4: =AI4/AI3 -> 0.97921423 | AK4: -218240.87 | AL4: =AK4/AK3 -> 0.99652856 | AM4: -216145.88 | AN4: =AM4/AM3 -> 0.98000693 | AO4: -201568.34 | AP4: =AO4/AO3 -> 0.95692442 | AQ4: -233669.05 | AR4: =AQ4/AQ3 -> 0.90327874 | AS4: -401095.77 | AT4: =AS4/AS3 -> 0.88675254 | AU4: =W4+Y4+AA4+AC4+AE4+AG4+AI4+AK4+AM4+AO4+AQ4+AS4 -> -2691045.6 | AV4: =AU4/AU3 -> 0.94602729 | AW4: 0.71651218
A5: 4 | D5: (-) Descontos- Duplicidades Clientes | E5: -41078.09 | F5: =SUM(F6:F9) -> 0.19859173 | G5: -31704.62 | H5: =SUM(H6:H9) -> 0.13633835 | I5: -37626.97 | J5: =SUM(J6:J9) -> 0.14764834 | K5: -32498.38 | L5: =SUM(L6:L9) -> 0.17519671 | M5: -31433.67 | N5: =SUM(N6:N9) -> 0.13224378 | O5: -31726.8 | P5: =SUM(P6:P9) -> 0.13243305 | Q5: -5084.19 | R5: =SUM(R6:R9) -> 0.017632428 | S5: -12117.57 | T5: =SUM(T6:T9) -> 0.058752194 | U5: =E5+G5+I5+K5+M5+O5+Q5+S5 -> -223270.29 | V5: =SUM(V6:V9) -> 0.12058337 | W5: -10797.42 | X5: =SUM(X6:X9) -> 0.050236494 | Y5: -7676.11 | Z5: =SUM(Z6:Z9) -> 0.037199544 | AA5: -5579.04 | AB5: =SUM(AB6:AB9) -> 0.027713509 | AC5: -18953.62 | AD5: =SUM(AD6:AD9) -> 0.089680957 | AE5: -5510.44 | AF5: =SUM(AF6:AF9) -> 0.033392486 | AG5: -9283.98 | AH5: =SUM(AH6:AH9) -> 0.039968041 | AI5: -5240.59 | AJ5: =SUM(AJ6:AJ9) -> 0.020785771 | AK5: -760.25 | AL5: =SUM(AL6:AL9) -> 0.0034714434 | AM5: -4409.58 | AN5: =SUM(AN6:AN9) -> 0.019993067 | AO5: -9073.52 | AP5: =SUM(AP6:AP9) -> 0.043075579 | AQ5: -25020.81 | AR5: =SUM(AR6:AR9) -> 0.096721263 | AS5: -51224.075 | AT5: =SUM(AT6:AT9) -> 0.11324746 | AU5: =W5+Y5+AA5+AC5+AE5+AG5+AI5+AK5+AM5+AO5+AQ5+AS5 -> -153529.43 | AV5: =SUM(AV6:AV9) -> 0.053972713 | AW5: 1.0472589
A6: 5 | B6: CUSTOS E DESPESAS | D6: Glosas - Desconto s/ líquido da NF | E6: 0 | F6: =E6/E3 -> 0 | G6: 0 | H6: =G6/G3 -> 0 | I6: 0 | J6: =I6/I3 -> 0 | K6: 0 | L6: =K6/K3 -> 0 | M6: 0 | N6: =M6/M3 -> 0 | O6: -379.93 | P6: =O6/O3 -> 0.0015858923 | Q6: -4189.25 | R6: =Q6/Q3 -> 0.014528696 | S6: -11743.11 | T6: =S6/S3 -> 0.056936619 | U6: =E6+G6+I6+K6+M6+O6+Q6+S6 -> -16312.29 | V6: =U6/$U$3 -> 0.0088099091 | W6: -10130.86 | X6: =W6/W3 -> 0.047135231 | Y6: -3222.51 | Z6: =Y6/Y3 -> 0.015616752 | AA6: -5578.97 | AB6: =AA6/AA3 -> 0.027713161 | AC6: -18374.26 | AD6: =AC6/AC3 -> 0.086939657 | AE6: -5121.73 | AF6: =AE6/AE3 -> 0.031036958 | AG6: -9252.07 | AH6: =AG6/AG3 -> 0.039830667 | AI6: -5240.53 | AJ6: =AI6/AI3 -> 0.020785533 | AK6: -756.69 | AL6: =AK6/AK3 -> 0.0034551878 | AM6: -4409.56 | AN6: =AM6/AM3 -> 0.019992976 | AO6: -9073.56 | AP6: =AO6/AO3 -> 0.043075769 | AQ6: -25020.85 | AR6: =AQ6/AQ3 -> 0.096721418 | AS6: -10477.135 | AT6: =AS6/AS3 -> 0.023163111 | AU6: =W6+Y6+AA6+AC6+AE6+AG6+AI6+AK6+AM6+AO6+AQ6+AS6 -> -106658.72 | AV6: =AU6/AU3 -> 0.037495486 | AW6: -0.58126383
A7: 6 | B7: CUSTOS E DESPESAS | D7: Duplicidade Itaú | E7: -31292.27 | F7: =E7/$E$3 -> 0.15128225 | G7: -31704.62 | H7: =G7/$G$3 -> 0.13633835 | I7: -32652.85 | J7: =I7/I3 -> 0.12812988 | K7: -32498.45 | L7: =K7/K3 -> 0.17519709 | M7: -31418.74 | N7: =M7/M3 -> 0.13218097 | O7: -31346.8 | P7: =O7/O3 -> 0.13084686 | Q7: 0 | R7: =Q7/Q3 -> 0 | S7: 0 | T7: =S7/S3 -> 0 | U7: =E7+G7+I7+K7+M7+O7+Q7+S7 -> -190913.73 | V7: =U7/$U$3 -> 0.10310831 | W7: 0 | X7: =W7/W3 -> 0 | Y7: 0 | Z7: =Y7/Y3 -> 0 | AA7: 0 | AB7: =AA7/AA3 -> 0 | AC7: -566.15 | AD7: =AC7/AC3 -> 0.0026787956 | AE7: -379.74 | AF7: =AE7/AE3 -> 0.0023011706 | AG7: -31.5 | AH7: =AG7/AG3 -> 0.00013560922 | AI7: 0 | AJ7: =AI7/AI3 -> 0 | AK7: 0 | AL7: =AK7/AK3 -> 0 | AM7: 0 | AN7: =AM7/AM3 -> 0 | AO7: 0 | AP7: =AO7/AO3 -> 0 | AQ7: 0 | AR7: =AQ7/AQ3 -> 0 | AS7: 0 | AT7: =AS7/AS3 -> 0 | AU7: =W7+Y7+AA7+AC7+AE7+AG7+AI7+AK7+AM7+AO7+AQ7+AS7 -> -977.39 | AV7: =AU7/AU3 -> 0.00034359789
A8: 7 | B8: CUSTOS E DESPESAS | D8: Juros Antecipação | E8: -9780.2 | F8: =E8/$E$3 -> 0.047282307 | G8: 0 | H8: =G8/$G$3 -> 0 | I8: -4959.67 | J8: =I8/I3 -> 0.01946176 | K8: 0 | L8: =K8/K3 -> 0 | M8: 0 | N8: =M8/M3 -> 0 | O8: 0 | P8: =O8/O3 -> 0 | Q8: 0 | R8: =Q8/Q3 -> 0 | S8: 0 | T8: =S8/S3 -> 0 | U8: =E8+G8+I8+K8+M8+O8+Q8+S8 -> -14739.87 | V8: =U8/$U$3 -> 0.0079606796 | W8: 0 | X8: =W8/W3 -> 0 | Y8: -4442.21 | Z8: =Y8/Y3 -> 0.021527595 | AA8: 0 | AB8: =AA8/AA3 -> 0 | AC8: 0 | AD8: =AC8/AC3 -> 0 | AE8: 0 | AF8: =AE8/AE3 -> 0 | AG8: 0 | AH8: =AG8/AG3 -> 0 | AI8: 0 | AJ8: =AI8/AI3 -> 0 | AK8: 0 | AL8: =AK8/AK3 -> 0 | AM8: 0 | AN8: =AM8/AM3 -> 0 | AO8: 0 | AP8: =AO8/AO3 -> 0 | AQ8: 0 | AR8: =AQ8/AQ3 -> 0 | AS8: -40746.93 | AT8: =AS8/AS3 -> 0.09008433 | AU8: =W8+Y8+AA8+AC8+AE8+AG8+AI8+AK8+AM8+AO8+AQ8+AS8 -> -45189.14 | AV8: =AU8/AU3 -> 0.015886077
A9: 8 | B9: CUSTOS E DESPESAS | D9: Outros | E9: -5.62 | F9: =E9/$E$3 -> 2.716985e-05 | G9: 0 | H9: =G9/$G$3 -> 0 | I9: -14.45 | J9: =I9/I3 -> 5.6701844e-05 | K9: 0.07 | L9: =K9/K3 -> -3.7736557e-07 | M9: -14.93 | N9: =M9/M3 -> 6.2811618e-05 | O9: -0.07 | P9: =O9/O3 -> 2.9219188e-07 | Q9: -894.94 | R9: =Q9/Q3 -> 0.0031037324 | S9: -374.46 | T9: =S9/S3 -> 0.0018155741 | U9: =E9+G9+I9+K9+M9+O9+Q9+S9 -> -1304.4 | V9: =U9/$U$3 -> 0.00070447775 | W9: -666.56 | X9: =W9/W3 -> 0.0031012628 | Y9: -11.39 | Z9: =Y9/Y3 -> 5.5197595e-05 | AA9: -0.07 | AB9: =AA9/AA3 -> 3.4772033e-07 | AC9: -13.21 | AD9: =AC9/AC3 -> 6.2504442e-05 | AE9: -8.97 | AF9: =AE9/AE3 -> 5.4356929e-05 | AG9: -0.41 | AH9: =AG9/AG3 -> 1.7650724e-06 | AI9: -0.06 | AJ9: =AI9/AI3 -> 2.3797821e-07 | AK9: -3.56 | AL9: =AK9/AK3 -> 1.6255625e-05 | AM9: -0.02 | AN9: =AM9/AM3 -> 9.068014e-08 | AO9: 0.04 | AP9: =AO9/AO3 -> -1.8989578e-07 | AQ9: 0.04 | AR9: =AQ9/AQ3 -> -1.5462531e-07 | AS9: -0.01 | AT9: =AS9/AS3 -> 2.210825e-08 | AU9: =W9+Y9+AA9+AC9+AE9+AG9+AI9+AK9+AM9+AO9+AQ9+AS9 -> -704.18 | AV9: =AU9/AU3 -> 0.00024755191 | AW9: -1.25
A10: 9 | B10: CUSTOS E DESPESAS | D10: (+) Juros - peq valores | F10: =E10/$E$3 -> 0 | H10: =G10/$G$3 -> 0 | J10: =I10/I3 -> 0 | L10: =K10/K3 -> 0 | N10: =M10/M3 -> 0 | P10: =O10/O3 -> 0 | R10: =Q10/Q3 -> 0 | T10: =S10/S3 -> 0 | U10: =E10+G10+I10+K10+M10+O10+Q10+S10 -> 0 | V10: =U10/$U$3 -> 0 | X10: =W10/W3 -> 0 | Z10: =Y10/Y3 -> 0 | AB10: =AA10/AA3 -> 0 | AD10: =AC10/AC3 -> 0 | AF10: =AE10/AE3 -> 0 | AH10: =AG10/AG3 -> 0 | AJ10: =AI10/AI3 -> 0 | AL10: =AK10/AK3 -> 0 | AN10: =AM10/AM3 -> 0 | AP10: =AO10/AO3 -> 0 | AR10: =AQ10/AQ3 -> 0 | AT10: =AS10/AS3 -> 0 | AU10: =W10+Y10+AA10+AC10+AE10+AG10+AI10+AK10+AM10+AO10+AQ10+AS10 -> 0 | AV10: =AU10/AU3 -> 0
A11: 10 | D11: RECEITA LIQUIDA PREST DE SERVIÇOS | E11: 3423141.8 | F11: =SUM(F12:F18) -> 1 | G11: 3835580.5 | H11: =SUM(H12:H18) -> 1 | I11: 4385404.6 | J11: =SUM(J12:J18) -> 1 | K11: 3268713.5 | L11: =SUM(L12:L18) -> 1 | M11: 4015442 | N11: =SUM(N12:N18) -> 1 | O11: 4418572.1 | P11: =SUM(P12:P18) -> 1 | Q11: 5855995.8 | R11: =SUM(R12:R18) -> 1 | S11: 5105857.1 | T11: =SUM(T12:T18) -> 1 | U11: =E11+G11+I11+K11+M11+O11+Q11+S11 -> 34308707 | V11: =SUM(V12:V18) -> 1 | W11: 4187254.5 | X11: =SUM(X12:X18) -> 1 | Y11: 3929711.2 | Z11: =SUM(Z12:Z18) -> 1 | AA11: 3502462.2 | AB11: =SUM(AB12:AB18) -> 1 | AC11: 3428282.7 | AD11: =SUM(AD12:AD18) -> 1 | AE11: 3183190.7 | AF11: =SUM(AF12:AF18) -> 1 | AG11: 3719416 | AH11: =SUM(AH12:AH18) -> 1 | AI11: 4273888.7 | AJ11: =SUM(AJ12:AJ18) -> 1 | AK11: 4609599.7 | AL11: =SUM(AL12:AL18) -> 1 | AM11: 4201923.1 | AN11: =SUM(AN12:AN18) -> 1 | AO11: 4089688.4 | AP11: =SUM(AP12:AP18) -> 1 | AQ11: 4387475.9 | AR11: =SUM(AR12:AR18) -> 1 | AS11: 6899702.6 | AT11: =SUM(AT12:AT18) -> 1 | AU11: =W11+Y11+AA11+AC11+AE11+AG11+AI11+AK11+AM11+AO11+AQ11+AS11 -> 50412596 | AV11: =SUM(AV12:AV18) -> 1 | AW11: 0.57259043
A12: 11 | D12: Clientes - Honorários Contratuais | E12: 3300568.8 | F12: =E12/E11 -> 0.96419285 | G12: 3630920.8 | H12: =G12/G11 -> 0.94664179 | I12: 3830477.2 | J12: =I12/I11 -> 0.87346039 | K12: 2964903.1 | L12: =K12/K11 -> 0.90705506 | M12: 3711576.5 | N12: =M12/M11 -> 0.92432577 | O12: 3617089.2 | P12: =O12/O11 -> 0.81861045 | Q12: 5152175.7 | R12: =Q12/Q11 -> 0.87981205 | S12: 3627014.8 | T12: =S12/S11 -> 0.71036356 | U12: =E12+G12+I12+K12+M12+O12+Q12+S12 -> 29834726 | V12: =U12/$U$11 -> 0.86959634 | W12: 3803079.1 | X12: =W12/W11 -> 0.90825124 | Y12: 3511184.9 | Z12: =Y12/Y11 -> 0.89349694 | AA12: 3100368.5 | AB12: =AA12/AA11 -> 0.88519685 | AC12: 3072786.7 | AD12: =AC12/AC11 -> 0.89630494 | AE12: 2666159.4 | AF12: =AE12/AE11 -> 0.83757451 | AG12: 3454392.3 | AH12: =AG12/AG11 -> 0.9287459 | AI12: 4153085.8 | AJ12: =AI12/AI11 -> 0.97173466 | AK12: 4015316.6 | AL12: =AK12/AK11 -> 0.87107706 | AM12: 3801030.5 | AN12: =AM12/AM11 -> 0.90459306 | AO12: 3646062.6 | AP12: =AO12/AO11 -> 0.89152577 | AQ12: 4129354.4 | AR12: =AQ12/AQ11 -> 0.94116856 | AS12: 6386309.3 | AT12: =AS12/AS11 -> 0.92559196 | AU12: =W12+Y12+AA12+AC12+AE12+AG12+AI12+AK12+AM12+AO12+AQ12+AS12 -> 45739130 | AV12: =AU12/AU11 -> 0.90729568 | AW12: 0.54656363
A13: 12 | D13: Clientes - Honorários de Sucumbência | E13: 112128.08 | F13: =E13/E11 -> 0.032755897 | G13: 187391.46 | H13: =G13/G11 -> 0.048856089 | I13: 410618.01 | J13: =I13/I11 -> 0.093632868 | K13: 303810.37 | L13: =K13/K11 -> 0.092944938 | M13: 300715.48 | N13: =M13/M11 -> 0.074889758 | O13: 777922.43 | P13: =O13/O11 -> 0.17605743 | Q13: 292277.13 | R13: =Q13/Q11 -> 0.049910748 | S13: 943376.74 | T13: =S13/S11 -> 0.18476364 | U13: =E13+G13+I13+K13+M13+O13+Q13+S13 -> 3328239.7 | V13: =U13/$U$11 -> 0.097008601 | W13: 367038.29 | X13: =W13/W11 -> 0.087656073 | Y13: 389371.93 | Z13: =Y13/Y11 -> 0.099084109 | AA13: 397295.7 | AB13: =AA13/AA11 -> 0.11343326 | AC13: 321630.05 | AD13: =AC13/AC11 -> 0.093816666 | AE13: 513933.32 | AF13: =AE13/AE11 -> 0.16145226 | AG13: 233201.97 | AH13: =AG13/AG11 -> 0.062698545 | AI13: 112779.26 | AJ13: =AI13/AI11 -> 0.026387973 | AK13: 579410.41 | AL13: =AK13/AK11 -> 0.12569647 | AM13: 387892.36 | AN13: =AM13/AM11 -> 0.092313055 | AO13: 426678.55 | AP13: =AO13/AO11 -> 0.10433033 | AQ13: 247509.19 | AR13: =AQ13/AQ11 -> 0.056412661 | AS13: 501699.87 | AT13: =AS13/AS11 -> 0.07271326 | AU13: =W13+Y13+AA13+AC13+AE13+AG13+AI13+AK13+AM13+AO13+AQ13+AS13 -> 4478440.9 | AV13: =AU13/AU11 -> 0.088835753 | AW13: 1.0269949
A14: 13 | D14: Clientes - Honorários de Prepostos | E14: 6500 | F14: =E14/E11 -> 0.0018988404 | G14: 4800 | H14: =G14/G11 -> 0.0012514403 | I14: 5000 | J14: =I14/I11 -> 0.0011401456 | K14: 0 | L14: =K14/K11 -> 0 | M14: 3150 | N14: =M14/M11 -> 0.00078447155 | O14: 5600 | P14: =O14/O11 -> 0.0012673778 | Q14: 0 | R14: =Q14/Q11 -> 0 | S14: 9750 | T14: =S14/S11 -> 0.0019095717 | U14: =E14+G14+I14+K14+M14+O14+Q14+S14 -> 34800 | V14: =U14/$U$11 -> 0.0010143198 | W14: 5150 | X14: =W14/W11 -> 0.0012299228 | Y14: 0 | Z14: =Y14/Y11 -> 0 | AA14: 0 | AB14: =AA14/AA11 -> 0 | AC14: 0 | AD14: =AC14/AC11 -> 0 | AE14: 0 | AF14: =AE14/AE11 -> 0 | AG14: 20700 | AH14: =AG14/AG11 -> 0.0055653899 | AI14: 0 | AJ14: =AI14/AI11 -> 0 | AK14: 0 | AL14: =AK14/AK11 -> 0 | AM14: 6400 | AN14: =AM14/AM11 -> 0.0015231121 | AO14: 10346.99 | AP14: =AO14/AO11 -> 0.0025300191 | AQ14: 4012.08 | AR14: =AQ14/AQ11 -> 0.00091443921 | AS14: 3026.68 | AT14: =AS14/AS11 -> 0.00043866818 | AU14: =W14+Y14+AA14+AC14+AE14+AG14+AI14+AK14+AM14+AO14+AQ14+AS14 -> 49635.75 | AV14: =AU14/AU11 -> 0.00098459025 | AW14: -0.24560826
A15: 14 | D15: Intercompany - Receita | E15: 0 | F15: =E15/E11 -> 0 | G15: 0 | H15: =G15/G11 -> 0 | I15: 0 | J15: =I15/I11 -> 0 | K15: 0 | L15: =K15/K11 -> 0 | M15: 0 | N15: =M15/M11 -> 0 | O15: 0 | P15: =O15/O11 -> 0 | Q15: 400000 | R15: =Q15/Q11 -> 0.068306059 | S15: 500000 | T15: =S15/S11 -> 0.097926752 | U15: =E15+G15+I15+K15+M15+O15+Q15+S15 -> 900000 | V15: =U15/$U$11 -> 0.026232408 | W15: 0 | X15: =W15/W11 -> 0 | Y15: 0 | Z15: =Y15/Y11 -> 0 | AA15: 0 | AB15: =AA15/AA11 -> 0 | AC15: 0 | AD15: =AC15/AC11 -> 0 | AE15: 0 | AF15: =AE15/AE11 -> 0 | AG15: 0 | AH15: =AG15/AG11 -> 0 | AI15: 0 | AJ15: =AI15/AI11 -> 0 | AK15: 0 | AL15: =AK15/AK11 -> 0 | AM15: 0 | AN15: =AM15/AM11 -> 0 | AO15: 0 | AP15: =AO15/AO11 -> 0 | AQ15: 0 | AR15: =AQ15/AQ11 -> 0 | AS15: 0 | AT15: =AS15/AS11 -> 0 | AU15: =W15+Y15+AA15+AC15+AE15+AG15+AI15+AK15+AM15+AO15+AQ15+AS15 -> 0 | AV15: =AU15/AU11 -> 0
A16: 15 | D16: Outras Receitas - Venda Imobilizados/Embratel | E16: 0 | F16: =E16/E11 -> 0 | G16: 0 | H16: =G16/G11 -> 0 | I16: 0 | J16: =I16/I11 -> 0 | K16: 0 | L16: =K16/K11 -> 0 | M16: 0 | N16: =M16/M11 -> 0 | O16: 0 | P16: =O16/O11 -> 0 | Q16: 0 | R16: =Q16/Q11 -> 0 | S16: 0 | T16: =S16/S11 -> 0 | U16: =E16+G16+I16+K16+M16+O16+Q16+S16 -> 0 | V16: =U16/$U$11 -> 0 | W16: 0 | X16: =W16/W11 -> 0 | Y16: 0 | Z16: =Y16/Y11 -> 0 | AA16: 0 | AB16: =AA16/AA11 -> 0 | AC16: 0 | AD16: =AC16/AC11 -> 0 | AE16: 0 | AF16: =AE16/AE11 -> 0 | AG16: 0 | AH16: =AG16/AG11 -> 0 | AI16: 0 | AJ16: =AI16/AI11 -> 0 | AK16: 0 | AL16: =AK16/AK11 -> 0 | AM16: 0 | AN16: =AM16/AM11 -> 0 | AO16: 0 | AP16: =AO16/AO11 -> 0 | AQ16: 0 | AR16: =AQ16/AQ11 -> 0 | AS16: 0 | AT16: =AS16/AS11 -> 0 | AU16: =W16+Y16+AA16+AC16+AE16+AG16+AI16+AK16+AM16+AO16+AQ16+AS16 -> 0 | AV16: =AU16/AU11 -> 0
A17: 16 | D17: Outras Receitas - Honorários e Sucumb Retro | E17: 0 | F17: =E17/E11 -> 0 | G17: 0 | H17: =G17/G11 -> 0 | I17: 0 | J17: =I17/I11 -> 0 | K17: 0 | L17: =K17/K11 -> 0 | M17: 0 | N17: =M17/M11 -> 0 | O17: 14862.39 | P17: =O17/O11 -> 0.0033636183 | Q17: 0 | R17: =Q17/Q11 -> 0 | S17: 23224.43 | T17: =S17/S11 -> 0.004548586 | U17: =E17+G17+I17+K17+M17+O17+Q17+S17 -> 38086.82 | V17: =U17/$U$11 -> 0.0011101211 | W17: 8889.12 | X17: =W17/W11 -> 0.0021228994 | Y17: 24806.33 | Z17: =Y17/Y11 -> 0.0063125072 | AA17: 0 | AB17: =AA17/AA11 -> 0 | AC17: 25000 | AD17: =AC17/AC11 -> 0.0072922809 | AE17: 0 | AF17: =AE17/AE11 -> 0 | AG17: 0 | AH17: =AG17/AG11 -> 0 | AI17: 0 | AJ17: =AI17/AI11 -> 0 | AK17: 0 | AL17: =AK17/AK11 -> 0 | AM17: 0 | AN17: =AM17/AM11 -> 0 | AO17: 0 | AP17: =AO17/AO11 -> 0 | AQ17: 0 | AR17: =AQ17/AQ11 -> 0 | AS17: 0 | AT17: =AS17/AS11 -> 0 | AU17: =W17+Y17+AA17+AC17+AE17+AG17+AI17+AK17+AM17+AO17+AQ17+AS17 -> 58695.45 | AV17: =AU17/AU11 -> 0.0011643013
A18: 17 | D18: Glosa - Desconto Bruto NF | E18: 3944.87 | F18: =E18/E11 -> 0.0011524121 | G18: 12468.24 | H18: =G18/G11 -> 0.0032506788 | I18: 139309.38 | J18: =I18/I11 -> 0.031766597 | K18: 0 | L18: =K18/K11 -> 0 | M18: 0 | N18: =M18/M11 -> 0 | O18: 3098 | P18: =O18/O11 -> 0.00070113149 | Q18: 11543 | R18: =Q18/Q11 -> 0.0019711421 | S18: 2491.09 | T18: =S18/S11 -> 0.0004878887 | U18: =E18+G18+I18+K18+M18+O18+Q18+S18 -> 172854.58 | V18: =U18/$U$11 -> 0.0050382131 | W18: 3098 | X18: =W18/W11 -> 0.00073986427 | Y18: 4348 | Z18: =Y18/Y11 -> 0.0011064426 | AA18: 4798 | AB18: =AA18/AA11 -> 0.0013698935 | AC18: 8865.92 | AD18: =AC18/AC11 -> 0.0025861111 | AE18: 3098 | AF18: =AE18/AE11 -> 0.00097323733 | AG18: 11121.65 | AH18: =AG18/AG11 -> 0.0029901603 | AI18: 8023.65 | AJ18: =AI18/AI11 -> 0.0018773652 | AK18: 14872.72 | AL18: =AK18/AK11 -> 0.0032264667 | AM18: 6600.27 | AN18: =AM18/AM11 -> 0.0015707736 | AO18: 6600.27 | AP18: =AO18/AO11 -> 0.0016138809 | AQ18: 6600.27 | AR18: =AQ18/AQ11 -> 0.0015043433 | AS18: 8666.78 | AT18: =AS18/AS11 -> 0.0012561092 | AU18: =W18+Y18+AA18+AC18+AE18+AG18+AI18+AK18+AM18+AO18+AQ18+AS18 -> 86693.53 | AV18: =AU18/AU11 -> 0.00171968 | AW18: 0.31309477
A19: 18 | D19: CUSTOS OPERACIONAIS | E19: -1565135 | F19: =SUM(F20:F23) -> 0.95112748 | G19: -1492450.1 | H19: =SUM(H20:H23) -> 1 | I19: -1637052.3 | J19: =SUM(J20:J23) -> 1 | K19: -1570621.1 | L19: =SUM(L20:L23) -> 1 | M19: -1612226.3 | N19: =SUM(N20:N23) -> 1 | O19: -1713951.6 | P19: =SUM(P20:P23) -> 1 | Q19: -1715154.5 | R19: =SUM(R20:R23) -> 1 | S19: -1702156 | T19: =SUM(T20:T23) -> 1 | U19: =E19+G19+I19+K19+M19+O19+Q19+S19 -> -13008747 | V19: =SUM(V20:V23) -> 0.99411995 | W19: -1668331.1 | X19: =SUM(X20:X23) -> 1 | Y19: -1655218.1 | Z19: =SUM(Z20:Z23) -> 1 | AA19: -1624745.7 | AB19: =SUM(AB20:AB23) -> 1 | AC19: -1783445.9 | AD19: =SUM(AD20:AD23) -> 1 | AE19: -1812291.4 | AF19: =SUM(AF20:AF23) -> 1 | AG19: -1997303 | AH19: =SUM(AH20:AH23) -> 1 | AI19: -1890421.5 | AJ19: =SUM(AJ20:AJ23) -> 1 | AK19: -1887948.2 | AL19: =SUM(AL20:AL23) -> 1 | AM19: -2122887.2 | AN19: =SUM(AN20:AN23) -> 1 | AO19: -1935758.4 | AP19: =SUM(AP20:AP23) -> 1 | AQ19: -2019919.6 | AR19: =SUM(AR20:AR23) -> 1 | AS19: -2005996.6 | AT19: =SUM(AT20:AT23) -> 1 | AU19: =W19+Y19+AA19+AC19+AE19+AG19+AI19+AK19+AM19+AO19+AQ19+AS19 -> -22404267 | AV19: =SUM(AV20:AV23) -> 1 | AW19: -0.0068928463
A20: 19 | B20: CUSTOS E DESPESAS | D20: Condenações + Glosas | E20: -69000.39 | F20: =E20/$E$19 -> 0.044085902 | G20: -43713.2 | H20: =G20/$G$19 -> 0.029289556 | I20: -150696.85 | J20: =I20/I19 -> 0.092053779 | K20: -78157.04 | L20: =K20/K19 -> 0.049761868 | M20: -45044.93 | N20: =M20/M19 -> 0.027939583 | O20: -101101.63 | P20: =O20/O19 -> 0.058987449 | Q20: -36733.81 | R20: =Q20/Q19 -> 0.021417202 | S20: -39949.51 | T20: =S20/S19 -> 0.023469946 | U20: =E20+G20+I20+K20+M20+O20+Q20+S20 -> -564397.36 | V20: =U20/$U$19 -> 0.04338599 | W20: -18249.39 | X20: =W20/W19 -> 0.01093871 | Y20: -43101.16 | Z20: =Y20/Y19 -> 0.026039566 | AA20: -24888.149 | AB20: =AA20/AA19 -> 0.015318182 | AC20: -29440.554 | AD20: =AC20/AC19 -> 0.01650768 | AE20: 30743.61 | AF20: =AE20/AE19 -> -0.016963944 | AG20: -131593.7 | AH20: =AG20/AG19 -> 0.065885699 | AI20: -30931.2 | AJ20: =AI20/AI19 -> 0.016362065 | AK20: -20964.84 | AL20: =AK20/AK19 -> 0.011104563 | AM20: -247883.56 | AN20: =AM20/AM19 -> 0.11676718 | AO20: -22536.2 | AP20: =AO20/AO19 -> 0.011642052 | AQ20: -38473.2 | AR20: =AQ20/AQ19 -> 0.019046896 | AS20: -11083.78 | AT20: =AS20/AS19 -> 0.0055253233 | AU20: =W20+Y20+AA20+AC20+AE20+AG20+AI20+AK20+AM20+AO20+AQ20+AS20 -> -588402.12 | AV20: =AU20/AU19 -> 0.026262949 | AW20: -0.71190907
A21: 20 | B21: CUSTOS E DESPESAS | D21: Custo Operacional - Correspondentes | E21: -138202.63 | F21: =E21/$E$19 -> 0.088300771 | G21: -165444.51 | H21: =G21/$G$19 -> 0.1108543 | I21: -169686.16 | J21: =I21/I19 -> 0.10365348 | K21: -165603.8 | L21: =K21/K19 -> 0.10543842 | M21: -198728.85 | N21: =M21/M19 -> 0.12326362 | O21: -216962.07 | P21: =O21/O19 -> 0.12658588 | Q21: -264809.08 | R21: =Q21/Q19 -> 0.15439372 | S21: -254639.2 | T21: =S21/S19 -> 0.14959804 | U21: =E21+G21+I21+K21+M21+O21+Q21+S21 -> -1574076.3 | V21: =U21/$U$19 -> 0.12100138 | W21: -217634.95 | X21: =W21/W19 -> 0.13045069 | Y21: -151787.51 | Z21: =Y21/Y19 -> 0.091702424 | AA21: -127979.75 | AB21: =AA21/AA19 -> 0.078769098 | AC21: -227020.69 | AD21: =AC21/AC19 -> 0.12729328 | AE21: -197541.58 | AF21: =AE21/AE19 -> 0.109001 | AG21: -195387.87 | AH21: =AG21/AG19 -> 0.097825856 | AI21: -196590.73 | AJ21: =AI21/AI19 -> 0.10399306 | AK21: -173444.26 | AL21: =AK21/AK19 -> 0.091869186 | AM21: -188176.32 | AN21: =AM21/AM19 -> 0.088641696 | AO21: -191160.75 | AP21: =AO21/AO19 -> 0.098752381 | AQ21: -197274.26 | AR21: =AQ21/AQ19 -> 0.097664411 | AS21: -201028.6 | AT21: =AS21/AS19 -> 0.10021383 | AU21: =W21+Y21+AA21+AC21+AE21+AG21+AI21+AK21+AM21+AO21+AQ21+AS21 -> -2265027.3 | AV21: =AU21/AU19 -> 0.10109803 | AW21: 0.019031069
A22: 21 | B22: DISTRIBUIÇÃO LUCROS | C22: 1 | D22: Custo Operacional - Jurídico | E22: -1261018.9 | F22: =E22/$E$19 -> 0.80569338 | G22: -1247698.2 | H22: =G22/$G$19 -> 0.83600668 | I22: -1257014.5 | J22: =I22/I19 -> 0.7678524 | K22: -1275862.2 | L22: =K22/K19 -> 0.81232969 | M22: -1300087.4 | N22: =M22/M19 -> 0.80639263 | O22: -1339147.3 | P22: =O22/O19 -> 0.78132156 | Q22: -1351942.4 | R22: =Q22/Q19 -> 0.78823359 | S22: -1333428.8 | T22: =S22/S19 -> 0.78337636 | U22: =E22+G22+I22+K22+M22+O22+Q22+S22 -> -10366200 | V22: =U22/$U$19 -> 0.79686382 | W22: -1388902.3 | X22: =W22/W19 -> 0.83250997 | Y22: -1404814.5 | Z22: =Y22/Y19 -> 0.84871871 | AA22: -1420450.2 | AB22: =AA22/AA19 -> 0.87426003 | AC22: -1483785.8 | AD22: =AC22/AC19 -> 0.83197688 | AE22: -1575153.4 | AF22: =AE22/AE19 -> 0.86915017 | AG22: -1596757.1 | AH22: =AG22/AG19 -> 0.79945664 | AI22: -1594773.2 | AJ22: =AI22/AI19 -> 0.84360716 | AK22: -1598716.6 | AL22: =AK22/AK19 -> 0.84680113 | AM22: -1618700.9 | AN22: =AM22/AM19 -> 0.7624997 | AO22: -1632905.2 | AP22: =AO22/AO19 -> 0.84354803 | AQ22: -1653420.7 | AR22: =AQ22/AQ19 -> 0.81855769 | AS22: -1708820.5 | AT22: =AS22/AS19 -> 0.85185612 | AU22: =W22+Y22+AA22+AC22+AE22+AG22+AI22+AK22+AM22+AO22+AQ22+AS22 -> -18677200 | AV22: =AU22/AU19 -> 0.8336448 | AW22: 0.03350615
A23: 22 | B23: CUSTOS E DESPESAS | D23: Custo Operacional - Processos Trabalhistas | E23: -20420.99 | F23: =E23/$E$19 -> 0.01304743 | G23: -35594.14 | H23: =G23/$G$19 -> 0.023849468 | I23: -59654.75 | J23: =I23/I19 -> 0.036440345 | K23: -50998.1 | L23: =K23/K19 -> 0.032470021 | M23: -68365.11 | N23: =M23/M19 -> 0.042404166 | O23: -56740.55 | P23: =O23/O19 -> 0.033105107 | Q23: -61669.21 | R23: =Q23/Q19 -> 0.035955484 | S23: -74138.52 | T23: =S23/S19 -> 0.043555655 | U23: =E23+G23+I23+K23+M23+O23+Q23+S23 -> -427581.37 | V23: =U23/$U$19 -> 0.032868759 | W23: -43544.49 | X23: =W23/W19 -> 0.026100628 | Y23: -55514.86 | Z23: =Y23/Y19 -> 0.033539303 | AA23: -51427.57 | AB23: =AA23/AA19 -> 0.03165269 | AC23: -43198.91 | AD23: =AC23/AC19 -> 0.024222158 | AE23: -70340.05 | AF23: =AE23/AE19 -> 0.038812771 | AG23: -73564.28 | AH23: =AG23/AG19 -> 0.036831809 | AI23: -68126.46 | AJ23: =AI23/AI19 -> 0.036037708 | AK23: -94822.42 | AL23: =AK23/AK19 -> 0.050225118 | AM23: -68126.46 | AN23: =AM23/AM19 -> 0.032091418 | AO23: -89156.27 | AP23: =AO23/AO19 -> 0.04605754 | AQ23: -130751.42 | AR23: =AQ23/AQ19 -> 0.064731001 | AS23: -85063.74 | AT23: =AS23/AS19 -> 0.042404727 | AU23: =W23+Y23+AA23+AC23+AE23+AG23+AI23+AK23+AM23+AO23+AQ23+AS23 -> -873636.93 | AV23: =AU23/AU19 -> 0.038994221 | AW23: -0.34942397
A24: 23 | D24: RESULTADO BRUTO | E24: 1858006.8 | F24: =E24/E2 -> 0.51184918 | G24: 2343130.4 | H24: =G24/G2 -> 0.57597317 | I24: 2748352.3 | J24: =I24/I2 -> 0.59228586 | K24: 1698092.4 | L24: =K24/K2 -> 0.49160079 | M24: 2403215.7 | N24: =M24/M2 -> 0.56504547 | O24: 2704620.5 | P24: =O24/O2 -> 0.58062234 | Q24: 4140841.4 | R24: =Q24/Q2 -> 0.67392788 | S24: 3403701.1 | T24: =S24/S2 -> 0.64074421 | U24: =E24+G24+I24+K24+M24+O24+Q24+S24 -> 21299961 | V24: =U24/U2 -> 0.58904283 | W24: 2518923.4 | X24: =W24/W2 -> 0.5721375 | Y24: 2274493.1 | Z24: =Y24/Y2 -> 0.55662055 | AA24: 1877716.5 | AB24: =AA24/AA2 -> 0.46384051 | AC24: 1644836.7 | AD24: =AC24/AC2 -> 0.41751072 | AE24: 1370899.3 | AF24: =AE24/AE2 -> 0.38636354 | AG24: 1722113 | AH24: =AG24/AG2 -> 0.4000712 | AI24: 2383467.1 | AJ24: =AI24/AI2 -> 0.5266156 | AK24: 2721651.6 | AL24: =AK24/AK2 -> 0.56365223 | AM24: 2079035.9 | AN24: =AM24/AM2 -> 0.4703194 | AO24: 2153930 | AP24: =AO24/AO2 -> 0.50087549 | AQ24: 2367556.3 | AR24: =AQ24/AQ2 -> 0.50569395 | AS24: 4893706 | AT24: =AS24/AS2 -> 0.66604295 | AU24: =W24+Y24+AA24+AC24+AE24+AG24+AI24+AK24+AM24+AO24+AQ24+AS24 -> 28008329 | AV24: =AU24/AU2 -> 0.51453642
A25: 24 | D25: DESPESAS OPERACIONAIS | E25: -594460.91 | F25: =F35+F34+F33+F26 -> 1 | G25: -646297.59 | H25: =H26+H33+H34+H35 -> 1 | I25: -685485.38 | J25: =J35+J34+J33+J26 -> 1 | K25: -695251.1 | L25: =L35+L34+L33+L26 -> 1 | M25: -706999.54 | N25: =N35+N34+N33+N26 -> 1 | O25: -861161.45 | P25: =P35+P34+P33+P26 -> 1 | Q25: -837267.47 | R25: =R35+R34+R33+R26 -> 1 | S25: -887861.65 | T25: =T35+T34+T33+T26 -> 1 | U25: =E25+G25+I25+K25+M25+O25+Q25+S25 -> -5914785.1 | V25: =V26+V33+V34+V35 -> 1 | W25: -748877.5 | X25: =X35+X34+X33+X26 -> 1 | Y25: -824323.64 | Z25: =Z35+Z34+Z33+Z26 -> 1 | AA25: -843251.59 | AB25: =AB35+AB34+AB33+AB26 -> 1 | AC25: -842331.81 | AD25: =AD35+AD34+AD33+AD26 -> 1 | AE25: -856311.02 | AF25: =AF35+AF34+AF33+AF26 -> 1 | AG25: -807805.05 | AH25: =AH35+AH34+AH33+AH26 -> 1 | AI25: -884228.52 | AJ25: =AJ35+AJ34+AJ33+AJ26 -> 1 | AK25: -800815.43 | AL25: =AL35+AL34+AL33+AL26 -> 1 | AM25: -881286.32 | AN25: =AN35+AN34+AN33+AN26 -> 1 | AO25: -821074.84 | AP25: =AP35+AP34+AP33+AP26 -> 1 | AQ25: -973085.07 | AR25: =AR35+AR34+AR33+AR26 -> 1 | AS25: -1177991.9 | AT25: =AT35+AT34+AT33+AT26 -> 1 | AU25: =W25+Y25+AA25+AC25+AE25+AG25+AI25+AK25+AM25+AO25+AQ25+AS25 -> -10461383 | AV25: =AV35+AV34+AV33+AV26 -> 1 | AW25: 0.21057443
A26: 25 | D26: Administrativas | E26: -159350.02 | F26: =SUM(F27:F32) -> 0.26805803 | G26: -152360.52 | H26: =SUM(H27:H32) -> 0.2357436 | I26: -137491.99 | J26: =SUM(J27:J32) -> 0.20057611 | K26: -134159.91 | L26: =SUM(L27:L32) -> 0.19296612 | M26: -134726.97 | N26: =SUM(N27:N32) -> 0.19056161 | O26: -273507.59 | P26: =SUM(P27:P32) -> 0.31760315 | Q26: -148715.63 | R26: =SUM(R27:R32) -> 0.17762022 | S26: -183752.81 | T26: =SUM(T27:T32) -> 0.20696108 | U26: =E26+G26+I26+K26+M26+O26+Q26+S26 -> -1324065.4 | V26: =SUM(V27:V32) -> 0.2238569 | W26: -168400.93 | X26: =SUM(X27:X32) -> 0.22487113 | Y26: -266652.54 | Z26: =SUM(Z27:Z32) -> 0.3234804 | AA26: -252778.66 | AB26: =SUM(AB27:AB32) -> 0.2997666 | AC26: -245101.42 | AD26: =SUM(AD27:AD32) -> 0.29097965 | AE26: -222600.33 | AF26: =SUM(AF27:AF32) -> 0.25995266 | AG26: -184180.7 | AH26: =SUM(AH27:AH32) -> 0.22800142 | AI26: -212716.87 | AJ26: =SUM(AJ27:AJ32) -> 0.24056776 | AK26: -174431.74 | AL26: =SUM(AL27:AL32) -> 0.21781765 | AM26: -204599.31 | AN26: =SUM(AN27:AN32) -> 0.23215986 | AO26: -207743.44 | AP26: =SUM(AP27:AP32) -> 0.25301401 | AQ26: -224878.85 | AR26: =SUM(AR27:AR32) -> 0.23109886 | AS26: -216488.39 | AT26: =SUM(AT27:AT32) -> 0.18377749 | AU26: =W26+Y26+AA26+AC26+AE26+AG26+AI26+AK26+AM26+AO26+AQ26+AS26 -> -2580573.2 | AV26: =SUM(AV27:AV32) -> 0.24667611 | AW26: -0.037311023
A27: 26 | B27: CUSTOS E DESPESAS | D27: Comunicação | E27: -28028.56 | F27: =E27/$E$25 -> 0.047149543 | G27: -8354.27 | H27: =G27/$G$25 -> 0.012926352 | I27: -45328.1 | J27: =I27/I25 -> 0.066125553 | K27: -28179.51 | L27: =K27/K25 -> 0.040531414 | M27: -28715.68 | N27: =M27/M25 -> 0.040616264 | O27: -28290.78 | P27: =O27/O25 -> 0.032851889 | Q27: -27886.19 | R27: =Q27/Q25 -> 0.033306191 | S27: -25292.07 | T27: =S27/S25 -> 0.028486499 | U27: =E27+G27+I27+K27+M27+O27+Q27+S27 -> -220075.16 | V27: =U27/$U$25 -> 0.037207634 | W27: -31228.29 | X27: =W27/W25 -> 0.041700131 | Y27: -30476.55 | Z27: =Y27/Y25 -> 0.036971583 | AA27: -29928.35 | AB27: =AA27/AA25 -> 0.035491602 | AC27: -30332.78 | AD27: =AC27/AC25 -> 0.036010488 | AE27: -32032.74 | AF27: =AE27/AE25 -> 0.037407833 | AG27: -35458.79 | AH27: =AG27/AG25 -> 0.043895232 | AI27: -34319.3 | AJ27: =AI27/AI25 -> 0.038812704 | AK27: -14345.43 | AL27: =AK27/AK25 -> 0.017913528 | AM27: -54951.46 | AN27: =AM27/AM25 -> 0.062353697 | AO27: -37318.82 | AP27: =AO27/AO25 -> 0.04545118 | AQ27: -32876.86 | AR27: =AQ27/AQ25 -> 0.033786214 | AS27: -34309.64 | AT27: =AS27/AS25 -> 0.029125531 | AU27: =W27+Y27+AA27+AC27+AE27+AG27+AI27+AK27+AM27+AO27+AQ27+AS27 -> -397579.01 | AV27: =AU27/AU25 -> 0.038004442 | AW27: 0.043580196
A28: 27 | B28: CUSTOS E DESPESAS | D28: Consumo de Material | E28: -11955.59 | F28: =E28/$E$25 -> 0.02011165 | G28: -13545.1 | H28: =G28/$G$25 -> 0.020957992 | I28: 5548.51 | J28: =I28/I25 -> -0.0080942791 | K28: -10241.26 | L28: =K28/K25 -> 0.014730304 | M28: -5992.55 | N28: =M28/M25 -> 0.008476031 | O28: -13795.05 | P28: =O28/O25 -> 0.016019122 | Q28: -1860.3 | R28: =Q28/Q25 -> 0.0022218706 | S28: -7664.79 | T28: =S28/S25 -> 0.0086328653 | U28: =E28+G28+I28+K28+M28+O28+Q28+S28 -> -59506.13 | V28: =U28/$U$25 -> 0.010060573 | W28: -1521.59 | X28: =W28/W25 -> 0.0020318276 | Y28: -9308.48 | Z28: =Y28/Y25 -> 0.011292264 | AA28: -6626.51 | AB28: =AA28/AA25 -> 0.0078582834 | AC28: -13965.56 | AD28: =AC28/AC25 -> 0.016579642 | AE28: -10636.71 | AF28: =AE28/AE25 -> 0.01242155 | AG28: -8552.37 | AH28: =AG28/AG25 -> 0.010587171 | AI28: -10680.49 | AJ28: =AI28/AI25 -> 0.01207888 | AK28: -13945.19 | AL28: =AK28/AK25 -> 0.017413738 | AM28: -20066.42 | AN28: =AM28/AM25 -> 0.022769467 | AO28: -14131.07 | AP28: =AO28/AO25 -> 0.017210453 | AQ28: -14821.91 | AR28: =AQ28/AQ25 -> 0.015231875 | AS28: -20825.16 | AT28: =AS28/AS25 -> 0.017678526 | AU28: =W28+Y28+AA28+AC28+AE28+AG28+AI28+AK28+AM28+AO28+AQ28+AS28 -> -145081.46 | AV28: =AU28/AU25 -> 0.013868287 | AW28: 0.4050254
A29: 28 | B29: CUSTOS E DESPESAS | D29: Despesas Gerais | E29: -57562.55 | F29: =E29/$E$25 -> 0.096831514 | G29: -66297.6 | H29: =G29/$G$25 -> 0.10258061 | I29: -37082.65 | J29: =I29/I25 -> 0.054096923 | K29: -37925.61 | L29: =K29/K25 -> 0.054549515 | M29: -39556.86 | N29: =M29/M25 -> 0.055950333 | O29: -71752.91 | P29: =O29/O25 -> 0.083321089 | Q29: -35357.48 | R29: =Q29/Q25 -> 0.042229612 | S29: -82781.58 | T29: =S29/S25 -> 0.093237026 | U29: =E29+G29+I29+K29+M29+O29+Q29+S29 -> -428317.24 | V29: =U29/$U$25 -> 0.072414675 | W29: -48394.3 | X29: =W29/W25 -> 0.064622452 | Y29: -133784.15 | Z29: =Y29/Y25 -> 0.16229566 | AA29: -106129.57 | AB29: =AA29/AA25 -> 0.12585754 | AC29: -87698.49 | AD29: =AC29/AC25 -> 0.10411395 | AE29: -73021.13 | AF29: =AE29/AE25 -> 0.085274075 | AG29: -35093.23 | AH29: =AG29/AG25 -> 0.043442697 | AI29: -63291.36 | AJ29: =AI29/AI25 -> 0.071578058 | AK29: -43428.37 | AL29: =AK29/AK25 -> 0.054230186 | AM29: -31737.89 | AN29: =AM29/AM25 -> 0.036013143 | AO29: -59990.23 | AP29: =AO29/AO25 -> 0.073063048 | AQ29: -67344.96 | AR29: =AQ29/AQ25 -> 0.06920768 | AS29: -54501.75 | AT29: =AS29/AS25 -> 0.046266659 | AU29: =W29+Y29+AA29+AC29+AE29+AG29+AI29+AK29+AM29+AO29+AQ29+AS29 -> -804415.43 | AV29: =AU29/AU25 -> 0.076893796 | AW29: -0.19070781
A30: 29 | B30: CUSTOS E DESPESAS | D30: Equipamentos | E30: -7231.53 | F30: =E30/$E$25 -> 0.012164854 | G30: -5268.5 | H30: =G30/$G$25 -> 0.0081518175 | I30: -4922.48 | J30: =I30/I25 -> 0.0071810138 | K30: -4773.74 | L30: =K30/K25 -> 0.0068662099 | M30: -4733.74 | N30: =M30/M25 -> 0.0066955348 | O30: -5213.74 | P30: =O30/O25 -> 0.0060543119 | Q30: -5887.36 | R30: =Q30/Q25 -> 0.0070316359 | S30: -5727.88 | T30: =S30/S25 -> 0.0064513204 | U30: =E30+G30+I30+K30+M30+O30+Q30+S30 -> -43758.97 | V30: =U30/$U$25 -> 0.007398235 | W30: -8625.29 | X30: =W30/W25 -> 0.011517625 | Y30: -8967.49 | Z30: =Y30/Y25 -> 0.010878603 | AA30: -15225.14 | AB30: =AA30/AA25 -> 0.018055276 | AC30: -10504.51 | AD30: =AC30/AC25 -> 0.012470751 | AE30: -7660.46 | AF30: =AE30/AE25 -> 0.0089458851 | AG30: -6240.99 | AH30: =AG30/AG25 -> 0.0077258616 | AI30: -7958.13 | AJ30: =AI30/AI25 -> 0.009000083 | AK30: -5897.39 | AL30: =AK30/AK25 -> 0.0073642312 | AM30: -6085.92 | AN30: =AM30/AM25 -> 0.0069057239 | AO30: -7944.2 | AP30: =AO30/AO25 -> 0.0096753665 | AQ30: -5678.95 | AR30: =AQ30/AQ25 -> 0.0058360262 | AS30: -6292.98 | AT30: =AS30/AS25 -> 0.005342125 | AU30: =W30+Y30+AA30+AC30+AE30+AG30+AI30+AK30+AM30+AO30+AQ30+AS30 -> -97081.45 | AV30: =AU30/AU25 -> 0.0092799827 | AW30: 0.10812386
A31: 30 | B31: CUSTOS E DESPESAS | D31: Localização / Ocupação | E31: -37496.6 | F31: =E31/$E$25 -> 0.063076645 | G31: -40796.76 | H31: =G31/$G$25 -> 0.0631238 | I31: -36780.47 | J31: =I31/I25 -> 0.053656097 | K31: -34695.78 | L31: =K31/K25 -> 0.049903956 | M31: -37222.89 | N31: =M31/M25 -> 0.052649101 | O31: -137704.1 | P31: =O31/O25 -> 0.15990509 | Q31: -43561.63 | R31: =Q31/Q25 -> 0.052028332 | S31: -42967.49 | T31: =S31/S25 -> 0.048394353 | U31: =E31+G31+I31+K31+M31+O31+Q31+S31 -> -411225.72 | V31: =U31/$U$25 -> 0.069525048 | W31: -50914.1 | X31: =W31/W25 -> 0.067987221 | Y31: -65071.91 | Z31: =Y31/Y25 -> 0.07893976 | AA31: -62148.17 | AB31: =AA31/AA25 -> 0.073700626 | AC31: -69780.524 | AD31: =AC31/AC25 -> 0.082842085 | AE31: -64244.51 | AF31: =AE31/AE25 -> 0.075024738 | AG31: -65298.07 | AH31: =AG31/AG25 -> 0.080833946 | AI31: -64024.16 | AJ31: =AI31/AI25 -> 0.072406803 | AK31: -64368.57 | AL31: =AK31/AK25 -> 0.080378783 | AM31: -65033.29 | AN31: =AM31/AM25 -> 0.0737936 | AO31: -65030.33 | AP31: =AO31/AO25 -> 0.079201465 | AQ31: -67681.41 | AR31: =AQ31/AQ25 -> 0.069553436 | AS31: -63040.48 | AT31: =AS31/AS25 -> 0.053515207 | AU31: =W31+Y31+AA31+AC31+AE31+AG31+AI31+AK31+AM31+AO31+AQ31+AS31 -> -766635.52 | AV31: =AU31/AU25 -> 0.073282428 | AW31: -0.068570232
A32: 31 | B32: CUSTOS E DESPESAS | D32: Prestadores de Serviço | E32: -17075.19 | F32: =E32/$E$25 -> 0.028723823 | G32: -18098.29 | H32: =G32/$G$25 -> 0.028003029 | I32: -18926.8 | J32: =I32/I25 -> 0.0276108 | K32: -18344.01 | L32: =K32/K25 -> 0.026384726 | M32: -18505.25 | N32: =M32/M25 -> 0.026174345 | O32: -16751.01 | P32: =O32/O25 -> 0.019451649 | Q32: -34162.67 | R32: =Q32/Q25 -> 0.040802577 | S32: -19319 | T32: =S32/S25 -> 0.021759021 | U32: =E32+G32+I32+K32+M32+O32+Q32+S32 -> -161182.22 | V32: =U32/$U$25 -> 0.027250731 | W32: -27717.36 | X32: =W32/W25 -> 0.037011874 | Y32: -19043.96 | Z32: =Y32/Y25 -> 0.023102528 | AA32: -32720.92 | AB32: =AA32/AA25 -> 0.038803271 | AC32: -32819.554 | AD32: =AC32/AC25 -> 0.038962738 | AE32: -35004.78 | AF32: =AE32/AE25 -> 0.040878582 | AG32: -33537.25 | AH32: =AG32/AG25 -> 0.041516514 | AI32: -32443.43 | AJ32: =AI32/AI25 -> 0.036691228 | AK32: -32446.79 | AL32: =AK32/AK25 -> 0.040517189 | AM32: -26724.33 | AN32: =AM32/AM25 -> 0.030324231 | AO32: -23328.79 | AP32: =AO32/AO25 -> 0.028412501 | AQ32: -36474.76 | AR32: =AQ32/AQ25 -> 0.037483629 | AS32: -37518.38 | AT32: =AS32/AS25 -> 0.031849438 | AU32: =W32+Y32+AA32+AC32+AE32+AG32+AI32+AK32+AM32+AO32+AQ32+AS32 -> -369780.3 | AV32: =AU32/AU25 -> 0.035347173 | AW32: 0.028612114
A33: 32 | B33: CUSTOS E DESPESAS | D33: Marketing | E33: -52394.22 | F33: =E33/$E$25 -> 0.088137368 | G33: -41642.62 | H33: =G33/$G$25 -> 0.064432578 | I33: -48085.99 | J33: =I33/I25 -> 0.070148819 | K33: -53139.99 | L33: =K33/K25 -> 0.076432802 | M33: -57899.24 | N33: =M33/M25 -> 0.081894311 | O33: -60817.24 | P33: =O33/O25 -> 0.070622344 | Q33: -81642.24 | R33: =Q33/Q25 -> 0.097510345 | S33: -82098.93 | T33: =S33/S25 -> 0.092468156 | U33: =E33+G33+I33+K33+M33+O33+Q33+S33 -> -477720.47 | V33: =U33/$U$25 -> 0.080767173 | W33: -47101.6 | X33: =W33/W25 -> 0.062896268 | Y33: -78225.32 | Z33: =Y33/Y25 -> 0.094896369 | AA33: -60110.36 | AB33: =AA33/AA25 -> 0.071284016 | AC33: -50886.614 | AD33: =AC33/AC25 -> 0.060411602 | AE33: -77283.78 | AF33: =AE33/AE25 -> 0.090251997 | AG33: -73052.55 | AH33: =AG33/AG25 -> 0.090433391 | AI33: -79528.5 | AJ33: =AI33/AI25 -> 0.089941117 | AK33: -58336.51 | AL33: =AK33/AK25 -> 0.072846386 | AM33: -82813.67 | AN33: =AM33/AM25 -> 0.093969086 | AO33: -85090.01 | AP33: =AO33/AO25 -> 0.10363247 | AQ33: -84249.94 | AR33: =AQ33/AQ25 -> 0.086580241 | AS33: -83355.8 | AT33: =AS33/AS25 -> 0.070760928 | AU33: =W33+Y33+AA33+AC33+AE33+AG33+AI33+AK33+AM33+AO33+AQ33+AS33 -> -860034.65 | AV33: =AU33/AU25 -> 0.082210419 | AW33: -0.010612945
A34: 33 | B34: DISTRIBUIÇÃO LUCROS | C34: 1 | D34: Pessoal Adm | E34: -377876.51 | F34: =E34/$E$25 -> 0.6356625 | G34: -447513.51 | H34: =G34/$G$25 -> 0.69242639 | I34: -494827.37 | J34: =I34/I25 -> 0.72186422 | K34: -502670.66 | L34: =K34/K25 -> 0.72300592 | M34: -508838.19 | N34: =M34/M25 -> 0.71971502 | O34: -521239.39 | P34: =O34/O25 -> 0.60527488 | Q34: -600306.93 | R34: =Q34/Q25 -> 0.71698346 | S34: -615099.83 | T34: =S34/S25 -> 0.69278792 | U34: =E34+G34+I34+K34+M34+O34+Q34+S34 -> -4068372.4 | V34: =U34/$U$25 -> 0.68783097 | W34: -526895.43 | X34: =W34/W25 -> 0.70358026 | Y34: -475823.34 | Z34: =Y34/Y25 -> 0.57722879 | AA34: -522863.83 | AB34: =AA34/AA25 -> 0.62005674 | AC34: -540123.74 | AD34: =AC34/AC25 -> 0.64122444 | AE34: -556426.91 | AF34: =AE34/AE25 -> 0.64979534 | AG34: -550571.8 | AH34: =AG34/AG25 -> 0.68156519 | AI34: -591983.15 | AJ34: =AI34/AI25 -> 0.66949113 | AK34: -568047.18 | AL34: =AK34/AK25 -> 0.70933596 | AM34: -593873.34 | AN34: =AM34/AM25 -> 0.67387105 | AO34: -528241.39 | AP34: =AO34/AO25 -> 0.64335352 | AQ34: -663956.28 | AR34: =AQ34/AQ25 -> 0.6823209 | AS34: -878147.71 | AT34: =AS34/AS25 -> 0.74546159 | AU34: =W34+Y34+AA34+AC34+AE34+AG34+AI34+AK34+AM34+AO34+AQ34+AS34 -> -6996954.1 | AV34: =AU34/AU25 -> 0.66883645 | AW34: 0.3225987
